Workbook
Name \b: #REF!
Name \c: #REF!
Name \d: #REF!
Name \e: #REF!
Name \f: #REF!
Name \g: #REF!
Name \h: #REF!
Name \i: #REF!
Name \j: #N/A
Name \k: #REF!
Name \l: #REF!
Name \m: #REF!
Name \p: #REF!
Name \q: #REF!
Name \s: #REF!
Name \u: #REF!
Name \v: #N/A
Name \x: #REF!
Name \z: #REF!
Name _______DAT1: #REF!
Name _______DAT2: #REF!
Name _______DAT3: #REF!
Name _______DAT4: #REF!
Name _______DAT5: #REF!
Name _______DAT6: #REF!
Name _______DAT7: #REF!
Name _______DAT8: #REF!
Name _______DCF2: #REF!
Name _______EPS94: #REF!
Name _______EPS95: #REF!
Name _______EPS96: #REF!
Name _______EPS97: #REF!
Name _______EPS98: #REF!
Name _______rev1997: #REF!
Name _______rev1999: #REF!
Name _______rev2000: #REF!
Name _______rev2001: #REF!
Name _______rev2002: #REF!
Name _______rev2003: #REF!
Name _______REV89: #REF!
Name _______REV90: #REF!
Name _______REV91: #REF!
Name _______REV92: #REF!
Name _______REV93: #REF!
Name _______REV94: #REF!
Name _______REV95: #REF!
Name _______REV96: #REF!
Name _______REV97: #REF!
Name _______REV98: #REF!
Name ______DAT1: #REF!
Name ______DAT2: #REF!
Name ______DAT3: #REF!
Name ______DAT4: #REF!
Name ______DAT5: #REF!
Name ______DAT6: #REF!
Name ______DAT7: #REF!
Name ______DAT8: #REF!
Name ______DCF2: #REF!
Name ______EPS94: #REF!
Name ______EPS95: #REF!

Sheet XN
A1: Code | B1: OR | C1: Please enter the ticker in B1, e.g. 700 HK
A2: Last annual report | B2: 45657 | C2: Please enter the date in B2, e.g. 2020/3/31
A3: Start year | B3: 2024
A4: Currency | B4: US$
A5: Unit | B5: mn
A6: =B4&" "&B5 -> US$ mn | B6: =TEXT(DATE($B$3,MONTH($B$2),DAY($B$2)),"mmm-yy")&IF($B$3>YEAR($B$2),"E","A") -> Dec-24A | C6: =TEXT(DATE($B$3+1,MONTH($B$2),DAY($B$2)),"mmm-yy")&IF($B$3+1>YEAR($B$2),"E","A") -> Dec-25E | D6: =TEXT(DATE($B$3+2,MONTH($B$2),DAY($B$2)),"mmm-yy")&IF($B$3+2>YEAR($B$2),"E","A") -> Dec-26E | E6: =TEXT(DATE($B$3+3,MONTH($B$2),DAY($B$2)),"mmm-yy")&IF($B$3+3>YEAR($B$2),"E","A") -> Dec-27E
A7: P&L
A8: Revenue | B8: ='PL-CF-BS'!H6 -> 43486.8 | C8: ='PL-CF-BS'!I6 -> 44052 | D8: ='PL-CF-BS'!J6 -> 46055.159 | E8: ='PL-CF-BS'!K6 -> 48398.286
A9: (+/-) | B9: ='PL-CF-BS'!H7 -> 0.055950814 | C9: ='PL-CF-BS'!I7 -> 0.012997047 | D9: ='PL-CF-BS'!J7 -> 0.045472611 | E9: ='PL-CF-BS'!K7 -> 0.05087653
A10: Net profit | B10: ='PL-CF-BS'!H49 -> 6408.7 | C10: ='PL-CF-BS'!I49 -> 6127.2 | D10: ='PL-CF-BS'!J49 -> 6786.0987 | E10: ='PL-CF-BS'!K49 -> 7382.0999
A11: (+/-) | B11: ='PL-CF-BS'!H50 -> 0.036335705 | C11: ='PL-CF-BS'!I50 -> -0.043924665 | D11: ='PL-CF-BS'!J50 -> 0.10753668 | E11: ='PL-CF-BS'!K50 -> 0.08782678
A12: ="Diluted EPS ("&B4&")" -> Diluted EPS (US$) | B12: ='PL-CF-BS'!H62 -> 11.954781 | C12: ='PL-CF-BS'!I62 -> 11.444496 | D12: ='PL-CF-BS'!J62 -> 12.6952 | E12: ='PL-CF-BS'!K62 -> 13.829726
A13: GPM | B13: ='PL-CF-BS'!H165 -> 0.7418297 | C13: ='PL-CF-BS'!I165 -> 0.74318079 | D13: ='PL-CF-BS'!J165 -> 0.74418079 | E13: ='PL-CF-BS'!K165 -> 0.74718079 | F13: e.g. 50.5%
A14: ROE | B14: ='PL-CF-BS'!H170 -> 0.20604235 | C14: ='PL-CF-BS'!I170 -> 0.17998282 | D14: ='PL-CF-BS'!J170 -> 0.18762282 | E14: ='PL-CF-BS'!K170 -> 0.19010214 | F14: e.g. 50.5%
A15: EBITDA | B15: ='PL-CF-BS'!H26 -> 10105.1 | C15: ='PL-CF-BS'!I26 -> 10173.74 | D15: ='PL-CF-BS'!J26 -> 10899.278 | E15: ='PL-CF-BS'!K26 -> 11663.501
A16: EBIT | B16: ='DCF '!F7 -> 8249.8 | C16: ='DCF '!G7 -> 8386.5 | D16: ='DCF '!H7 -> 9024.139 | E16: ='DCF '!I7 -> 9732.3131
A17: Interest Revenue | B17: ='PL-CF-BS'!H31 -> 148.7 | C17: ='PL-CF-BS'!I31 -> 167.7 | D17: ='PL-CF-BS'!J31 -> 230 | E17: ='PL-CF-BS'!K31 -> 200
A18: Interest Expense | B18: ='PL-CF-BS'!H30 -> -373.4 | C18: ='PL-CF-BS'!I30 -> -365.8 | D18: ='PL-CF-BS'!J30 -> -366 | E18: ='PL-CF-BS'!K30 -> -259.04
A19: Operating Profit | B19: ='PL-CF-BS'!H22 -> 8249.8 | C19: ='PL-CF-BS'!I22 -> 8386.5 | D19: ='PL-CF-BS'!J22 -> 9024.139 | E19: ='PL-CF-BS'!K22 -> 9732.3131
A20: Gross Profit | B20: ='PL-CF-BS'!H9 -> 32259.8 | C20: ='PL-CF-BS'!I9 -> 32738.6 | D20: ='PL-CF-BS'!J9 -> 34273.365 | E20: ='PL-CF-BS'!K9 -> 36162.269
A21: Depreciation | B21: ='PL-CF-BS'!H73 -> 1855.3 | C21: ='PL-CF-BS'!I73 -> 1817.4 | D21: ='PL-CF-BS'!J73 -> 1900.0419 | E21: ='PL-CF-BS'!K73 -> 1996.7095
A22: Pre-Tax Profit | B22: ='PL-CF-BS'!H40 -> 8432.9 | C22: ='PL-CF-BS'!I40 -> 8502.3 | D22: ='PL-CF-BS'!J40 -> 9207.3175 | E22: ='PL-CF-BS'!K40 -> 10003.167
A23: Balance Sheet
A24: Total Assets | B24: ='PL-CF-BS'!H125 -> 56353.4 | C24: ='PL-CF-BS'!I125 -> 61821.2 | D24: ='PL-CF-BS'!J125 -> 66152.243 | E24: ='PL-CF-BS'!K125 -> 70538.685
A25: Total Liabilities | B25: ='PL-CF-BS'!H145 -> 23215.6 | C25: ='PL-CF-BS'!I145 -> 26817.4 | D25: ='PL-CF-BS'!J145 -> 28763.273 | E25: ='PL-CF-BS'!K145 -> 30254.089
A26: Shareholder Equity | B26: ='PL-CF-BS'!H159 -> 33137.8 | C26: ='PL-CF-BS'!I159 -> 35003.8 | D26: ='PL-CF-BS'!J159 -> 37388.97 | E26: ='PL-CF-BS'!K159 -> 40284.596
A27: Total Equity | B27: ='PL-CF-BS'!H159 -> 33137.8 | C27: ='PL-CF-BS'!I155 -> 34953.2 | D27: ='PL-CF-BS'!J155 -> 37384.47 | E27: ='PL-CF-BS'!K155 -> 40280.096
A28: Cash Flow
A29: Profit before tax | B29: =B22 -> 8432.9 | C29: =C22 -> 8502.3 | D29: =D22 -> 9207.3175 | E29: =E22 -> 10003.167
A30: Net Cash from operations | B30: ='PL-CF-BS'!H76 -> 8286 | C30: ='PL-CF-BS'!I76 -> 8656.9 | D30: ='PL-CF-BS'!J76 -> 8495.086 | E30: ='PL-CF-BS'!K76 -> 9071.6143
A31: Net Cash from investment activity | B31: ='PL-CF-BS'!H84 -> -3703.9 | C31: ='PL-CF-BS'!I84 -> -1407.2 | D31: ='PL-CF-BS'!J84 -> -3188.9738 | E31: ='PL-CF-BS'!K84 -> -2909.6715
A32: Net Cash from financing activity | B32: ='PL-CF-BS'!H98 -> -4785.05 | C32: ='PL-CF-BS'!I98 -> -1397.8 | D32: ='PL-CF-BS'!J98 -> -2884.7118 | E32: ='PL-CF-BS'!K98 -> -3235.0188
A33: Net change in Cash | B33: ='PL-CF-BS'!H100 -> -235.7 | C33: ='PL-CF-BS'!I100 -> 5812.7 | D33: ='PL-CF-BS'!J100 -> 2421.4004 | E33: ='PL-CF-BS'!K100 -> 2926.9241
A34: Implied cash at end of period | B34: ='PL-CF-BS'!H101 -> 4288 | C34: ='PL-CF-BS'!I101 -> 4052.3 | D34: ='PL-CF-BS'!J101 -> 9865 | E34: ='PL-CF-BS'!K101 -> 12286.4
A35: Free Cash Flow | B35: ='DCF '!F14 -> 6174.35 | C35: ='DCF '!G14 -> 6939.375 | D35: ='DCF '!H14 -> 6823.3844 | E35: ='DCF '!I14 -> 7243.6666
A40: EPS | B40: =B12 -> 11.954781 | C40: =C12 -> 11.444496 | D40: =D12 -> 12.6952 | E40: =E12 -> 13.829726
A41: EPS1 | B41: =IF(A43-YEAR($B$2)>=0,VLOOKUP((A43-B3+1),A45:B48,2,FALSE),"na") -> 12.6952
A42: EPS2 | B42: =IF(A43-YEAR($B$2)>=0,VLOOKUP((A43-B3+2),A45:B48,2,FALSE),"na") -> 13.829726
A43: =YEAR(TODAY()) -> 2026
A44: =YEAR(TODAY()) -> 2026
A45: 1 | B45: =B40 -> 11.954781
A46: 2 | B46: =C40 -> 11.444496
A47: 3 | B47: =D40 -> 12.6952
A48: 4 | B48: =E40 -> 13.829726
A49: v2
A50: modeltype | B50: 1
A51: code | B51: smdrmb
A53: Supported format: Link and paste as value

Sheet XN-output
B2: 资产负债表（百万美元） | C2: =K18 -> 2023 | D2: =L18 -> 2024 | E2: =M18 -> 2025 | F2: =N18 -> 2026E | G2: =O18 -> 2027E | H2: 2028E | J2: 利润表（百万美元） | K2: =K18 -> 2023 | L2: =L18 -> 2024 | M2: =M18 -> 2025 | N2: =N18 -> 2026E | O2: =O18 -> 2027E | P2: 2028E | R2: BS (Euro mn) | S2: =C2 -> 2023 | T2: =D2 -> 2024 | U2: =E2 -> 2025 | V2: =F2 -> 2026E | W2: =G2 -> 2027E | X2: 2028E | Z2: IS (Euro mn) | AA2: =K2 -> 2023 | AB2: =L2 -> 2024 | AC2: =M2 -> 2025 | AD2: =N2 -> 2026E | AE2: =O2 -> 2027E | AF2: 2028E
B3: 现金及现金等价物 | C3: ='PL-CF-BS'!G111 -> 4288 | D3: ='PL-CF-BS'!H111 -> 4052.3 | E3: ='PL-CF-BS'!I111 -> 9865 | F3: ='PL-CF-BS'!J111 -> 12286.4 | G3: ='PL-CF-BS'!K111 -> 15213.324 | H3: ='PL-CF-BS'!L111 -> 19654.289 | J3: 营业收入 | K3: ='PL-CF-BS'!G6 -> 41182.6 | L3: ='PL-CF-BS'!H6 -> 43486.8 | M3: ='PL-CF-BS'!I6 -> 44052 | N3: ='PL-CF-BS'!J6 -> 46055.159 | O3: ='PL-CF-BS'!K6 -> 48398.286 | P3: ='PL-CF-BS'!L6 -> 50952.563 | R3: Cash and Cash Equivalents | T3: =D3 -> 4052.3 | U3: =E3 -> 9865 | V3: =F3 -> 12286.4 | W3: =G3 -> 15213.324 | X3: =H3 -> 19654.289 | Z3: Revenue | AA3: =K3 -> 41182.6 | AB3: =L3 -> 43486.8 | AC3: =M3 -> 44052 | AD3: =N3 -> 46055.159 | AE3: =O3 -> 48398.286 | AF3: =P3 -> 50952.563
B4: 应收款项 | C4: ='PL-CF-BS'!G108 -> 5092.7 | D4: ='PL-CF-BS'!H108 -> 5601.8 | E4: ='PL-CF-BS'!I108 -> 5500.3 | F4: ='PL-CF-BS'!J108 -> 5775.649 | G4: ='PL-CF-BS'!K108 -> 6082.9872 | H4: ='PL-CF-BS'!L108 -> 6429.813 | J4: 营业成本 | K4: ='PL-CF-BS'!G8 -> 10767 | L4: ='PL-CF-BS'!H8 -> 11227 | M4: ='PL-CF-BS'!I8 -> 11313.4 | N4: ='PL-CF-BS'!J8 -> 11781.795 | O4: ='PL-CF-BS'!K8 -> 12236.017 | P4: ='PL-CF-BS'!L8 -> 12728.929 | R4: Accounts Receivable | T4: =D4 -> 5601.8 | U4: =E4 -> 5500.3 | V4: =F4 -> 5775.649 | W4: =G4 -> 6082.9872 | X4: =H4 -> 6429.813 | Z4: Cost of Revenue | AA4: =K4 -> 10767 | AB4: =L4 -> 11227 | AC4: =M4 -> 11313.4 | AD4: =N4 -> 11781.795 | AE4: =O4 -> 12236.017 | AF4: =P4 -> 12728.929
B5: 存货净额 | C5: ='PL-CF-BS'!G107 -> 4482.4 | D5: ='PL-CF-BS'!H107 -> 4630.1 | E5: ='PL-CF-BS'!I107 -> 4543.3 | F5: ='PL-CF-BS'!J107 -> 4894.1616 | G5: ='PL-CF-BS'!K107 -> 5138.8791 | H5: ='PL-CF-BS'!L107 -> 5376.1661 | J5: 毛利 | K5: ='PL-CF-BS'!G9 -> 30415.6 | L5: ='PL-CF-BS'!H9 -> 32259.8 | M5: ='PL-CF-BS'!I9 -> 32738.6 | N5: ='PL-CF-BS'!J9 -> 34273.365 | O5: ='PL-CF-BS'!K9 -> 36162.269 | P5: ='PL-CF-BS'!L9 -> 38223.633 | R5: Net Inventories | T5: =D5 -> 4630.1 | U5: =E5 -> 4543.3 | V5: =F5 -> 4894.1616 | W5: =G5 -> 5138.8791 | X5: =H5 -> 5376.1661 | Z5: Gross Profit | AA5: =K5 -> 30415.6 | AB5: =L5 -> 32259.8 | AC5: =M5 -> 32738.6 | AD5: =N5 -> 34273.365 | AE5: =O5 -> 36162.269 | AF5: =P5 -> 38223.633
B6: 其他流动资产 | C6: ='PL-CF-BS'!G109 -> 2270.6 | D6: ='PL-CF-BS'!H109 -> 1955.3 | E6: ='PL-CF-BS'!I109 -> 2063.8 | F6: ='PL-CF-BS'!J109 -> 2063.8 | G6: ='PL-CF-BS'!K109 -> 2063.8 | H6: ='PL-CF-BS'!L109 -> 2063.8 | J6: 研究与创新费用 | K6: ='PL-CF-BS'!G12 -> 1288.9 | L6: ='PL-CF-BS'!H12 -> 1354.7 | M6: ='PL-CF-BS'!I12 -> 1380.6 | N6: ='PL-CF-BS'!J12 -> 1427.7099 | O6: ='PL-CF-BS'!K12 -> 1500.3469 | P6: ='PL-CF-BS'!L12 -> 1579.5294 | R6: Other Current Assets | T6: =D6 -> 1955.3 | U6: =E6 -> 2063.8 | V6: =F6 -> 2063.8 | W6: =G6 -> 2063.8 | X6: =H6 -> 2063.8 | Z6: Research and Innovation Expenses | AA6: =K6 -> 1288.9 | AB6: =L6 -> 1354.7 | AC6: =M6 -> 1380.6 | AD6: =N6 -> 1427.7099 | AE6: =O6 -> 1500.3469 | AF6: =P6 -> 1579.5294
B7: 流动资产合计 | C7: ='PL-CF-BS'!G113 -> 16325.3 | D7: ='PL-CF-BS'!H113 -> 16473.6 | E7: ='PL-CF-BS'!I113 -> 22198.4 | F7: ='PL-CF-BS'!J113 -> 25246.011 | G7: ='PL-CF-BS'!K113 -> 28724.991 | H7: ='PL-CF-BS'!L113 -> 33750.069 | J7: 广告及促销费用 | K7: ='PL-CF-BS'!G14 -> 13356.6 | L7: ='PL-CF-BS'!H14 -> 14008.9 | M7: ='PL-CF-BS'!I14 -> 14177.8 | N7: ='PL-CF-BS'!J14 -> 14645.541 | O7: ='PL-CF-BS'!K14 -> 15342.257 | P7: ='PL-CF-BS'!L14 -> 16151.962 | R7: Total Current Assets | T7: =D7 -> 16473.6 | U7: =E7 -> 22198.4 | V7: =F7 -> 25246.011 | W7: =G7 -> 28724.991 | X7: =H7 -> 33750.069 | Z7: Advertising and Promotion Expenses | AA7: =K7 -> 13356.6 | AB7: =L7 -> 14008.9 | AC7: =M7 -> 14177.8 | AD7: =N7 -> 14645.541 | AE7: =O7 -> 15342.257 | AF7: =P7 -> 16151.962
B8: 其他无形资产 | C8: ='PL-CF-BS'!G116 -> 4287.2 | D8: ='PL-CF-BS'!H116 -> 4594.8 | E8: ='PL-CF-BS'!I116 -> 5072 | F8: ='PL-CF-BS'!J116 -> 5072 | G8: ='PL-CF-BS'!K116 -> 5072 | H8: ='PL-CF-BS'!L116 -> 5072 | J8: 管理费用 | K8: ='PL-CF-BS'!G16 -> 7626.7 | L8: ='PL-CF-BS'!H16 -> 8208.7 | M8: ='PL-CF-BS'!I16 -> 8288.3 | N8: ='PL-CF-BS'!J16 -> 8704.4251 | O8: ='PL-CF-BS'!K16 -> 9098.8778 | P8: ='PL-CF-BS'!L16 -> 9528.1292 | R8: Other Intangible Assets | T8: =D8 -> 4594.8 | U8: =E8 -> 5072 | V8: =F8 -> 5072 | W8: =G8 -> 5072 | X8: =H8 -> 5072 | Z8: Administrative Expenses | AA8: =K9 -> -64.6 | AB8: =L8 -> 8208.7 | AC8: =M8 -> 8288.3 | AD8: =N8 -> 8704.4251 | AE8: =O8 -> 9098.8778 | AF8: =P8 -> 9528.1292
B9: 商誉 | C9: ='PL-CF-BS'!G115 -> 13102.6 | D9: ='PL-CF-BS'!H115 -> 13382 | E9: ='PL-CF-BS'!I115 -> 14469.7 | F9: ='PL-CF-BS'!J115 -> 16160.583 | G9: ='PL-CF-BS'!K115 -> 17582.694 | H9: ='PL-CF-BS'!L115 -> 19429.226 | J9: 财务费用 | K9: ='PL-CF-BS'!G29 -> -64.6 | L9: ='PL-CF-BS'!H29 -> -224.7 | M9: ='PL-CF-BS'!I29 -> -198.1 | N9: ='PL-CF-BS'!J29 -> -136 | O9: ='PL-CF-BS'!K29 -> -59.04 | P9: ='PL-CF-BS'!L29 -> -89.04 | R9: Goodwill | T9: =D9 -> 13382 | U9: =E9 -> 14469.7 | V9: =F9 -> 16160.583 | W9: =G9 -> 17582.694 | X9: =H9 -> 19429.226 | Z9: Finance Costs | AA9: =K10 -> 0 | AB9: =L9 -> -224.7 | AC9: =M9 -> -198.1 | AD9: =N9 -> -136 | AE9: =O9 -> -59.04 | AF9: =P9 -> -89.04
B10: 其他无形资产使用权资产 | C10: ='PL-CF-BS'!F117 -> 1482.7 | D10: ='PL-CF-BS'!G117 -> 1692.4 | E10: ='PL-CF-BS'!H117 -> 1763.2 | F10: ='PL-CF-BS'!I117 -> 1663.2 | G10: ='PL-CF-BS'!J117 -> 1663.2 | H10: ='PL-CF-BS'!K117 -> 1663.2 | J10: 其他费用/（-收入） | K10: ='PL-CF-BS'!G35 -> 0 | L10: ='PL-CF-BS'!H35 -> 0 | M10: ='PL-CF-BS'!I35 -> 0 | N10: ='PL-CF-BS'!J35 -> 0 | O10: ='PL-CF-BS'!K35 -> 0 | P10: ='PL-CF-BS'!L35 -> 0 | R10: Right-of-Use Assets | T10: =D10 -> 1692.4 | U10: =E10 -> 1763.2 | V10: =F10 -> 1663.2 | W10: =G10 -> 1663.2 | X10: =H10 -> 1663.2 | Z10: Other Expenses / (Income) | AA10: =K11 -> 0 | AB10: =L10 -> 0 | AC10: =M10 -> 0 | AD10: =N10 -> 0 | AE10: =O10 -> 0 | AF10: =P10 -> 0
B11: 不动产、厂房及设备 | C11: ='PL-CF-BS'!F118 -> 3481.7 | D11: ='PL-CF-BS'!G118 -> 3867.7 | E11: ='PL-CF-BS'!H118 -> 4202 | F11: ='PL-CF-BS'!I118 -> 4211.9 | G11: ='PL-CF-BS'!J118 -> 3947.0652 | H11: ='PL-CF-BS'!K118 -> 3677.6383 | J11: 营业外净收支 | K11: ='PL-CF-BS'!G39 -> 0 | L11: ='PL-CF-BS'!H39 -> 0 | M11: ='PL-CF-BS'!I39 -> 0 | N11: ='PL-CF-BS'!J39 -> 0 | O11: ='PL-CF-BS'!K39 -> 0 | P11: ='PL-CF-BS'!L39 -> 0 | R11: Property, Plant and Equipment (PPE) | T11: =D11 -> 3867.7 | U11: =E11 -> 4202 | V11: =F11 -> 4211.9 | W11: =G11 -> 3947.0652 | X11: =H11 -> 3677.6383 | Z11: Net Non-operating Income / (Loss) | AA11: =K12 -> 8000.9 | AB11: =L11 -> 0 | AC11: =M11 -> 0 | AD11: =N11 -> 0 | AE11: =O11 -> 0 | AF11: =P11 -> 0
B12: 非流动金融资产 | C12: ='PL-CF-BS'!F119 -> 11652.8 | D12: ='PL-CF-BS'!G119 -> 11631.6 | E12: ='PL-CF-BS'!H119 -> 14838.1 | F12: ='PL-CF-BS'!I119 -> 12867.3 | G12: ='PL-CF-BS'!J119 -> 12730.183 | H12: ='PL-CF-BS'!K119 -> 12490.461 | J12: 利润总额 | K12: ='PL-CF-BS'!G40 -> 8000.9 | L12: ='PL-CF-BS'!H40 -> 8432.9 | M12: ='PL-CF-BS'!I40 -> 8502.3 | N12: ='PL-CF-BS'!J40 -> 9207.3175 | O12: ='PL-CF-BS'!K40 -> 10003.167 | P12: ='PL-CF-BS'!L40 -> 10735.891 | R12: Non-current Financial Assets | T12: =D12 -> 11631.6 | U12: =E12 -> 14838.1 | V12: =F12 -> 12867.3 | W12: =G12 -> 12730.183 | X12: =H12 -> 12490.461 | Z12: Total Profit | AA12: =K13 -> 1810.6 | AB12: =L12 -> 8432.9 | AC12: =M12 -> 8502.3 | AD12: =N12 -> 9207.3175 | AE12: =O12 -> 10003.167 | AF12: =P12 -> 10735.891
B13: 对联营企业的投资 | C13: ='PL-CF-BS'!F120 -> 18.4 | D13: ='PL-CF-BS'!G120 -> 27 | E13: ='PL-CF-BS'!H120 -> 126.4 | F13: ='PL-CF-BS'!I120 -> 376 | G13: ='PL-CF-BS'!J120 -> 370.5 | H13: ='PL-CF-BS'!K120 -> 365 | J13: 所得税费用 | K13: ='PL-CF-BS'!G41 -> 1810.6 | L13: ='PL-CF-BS'!H41 -> 2015.1 | M13: ='PL-CF-BS'!I41 -> 2363.1 | N13: ='PL-CF-BS'!J41 -> 2409.2187 | O13: ='PL-CF-BS'!K41 -> 2609.067 | P13: ='PL-CF-BS'!L41 -> 2791.8224 | R13: Investment in Associates | T13: =D13 -> 27 | U13: =E13 -> 126.4 | V13: =F13 -> 376 | W13: =G13 -> 370.5 | X13: =H13 -> 365 | Z13: Income Tax Expense | AA13: =K14 -> 6184 | AB13: =L13 -> 2015.1 | AC13: =M13 -> 2363.1 | AD13: =N13 -> 2409.2187 | AE13: =O13 -> 2609.067 | AF13: =P13 -> 2791.8224
B14: 递延税项资产 | C14: ='PL-CF-BS'!F121 -> 801.1 | D14: ='PL-CF-BS'!G121 -> 921.2 | E14: ='PL-CF-BS'!H121 -> 973.3 | F14: ='PL-CF-BS'!I121 -> 962.7 | G14: ='PL-CF-BS'!J121 -> 962.7 | H14: ='PL-CF-BS'!K121 -> 962.7 | J14: 净利润 | K14: ='PL-CF-BS'!G49 -> 6184 | L14: ='PL-CF-BS'!H49 -> 6408.7 | M14: ='PL-CF-BS'!I49 -> 6127.2 | N14: ='PL-CF-BS'!J49 -> 6786.0987 | O14: ='PL-CF-BS'!K49 -> 7382.0999 | P14: ='PL-CF-BS'!L49 -> 7932.0682 | R14: Deferred Tax Assets | T14: =D14 -> 921.2 | U14: =E14 -> 973.3 | V14: =F14 -> 962.7 | W14: =G14 -> 962.7 | X14: =H14 -> 962.7 | Z14: Net Profit | AA14: =K15 -> -6.5 | AB14: =L14 -> 6408.7 | AC14: =M14 -> 6127.2 | AD14: =N14 -> 6786.0987 | AE14: =O14 -> 7382.0999 | AF14: =P14 -> 7932.0682
B15: 非流动资产合计 | C15: ='PL-CF-BS'!G123 -> 35529.7 | D15: ='PL-CF-BS'!H123 -> 39879.8 | E15: ='PL-CF-BS'!I123 -> 39622.8 | F15: ='PL-CF-BS'!J123 -> 40906.232 | G15: ='PL-CF-BS'!K123 -> 41813.694 | H15: ='PL-CF-BS'!L123 -> 42407.635 | J15: 少数股东损益 | K15: ='PL-CF-BS'!G47 -> -6.5 | L15: ='PL-CF-BS'!H47 -> -7.8 | M15: ='PL-CF-BS'!I47 -> -6.5 | N15: ='PL-CF-BS'!J47 -> -6.5 | O15: ='PL-CF-BS'!K47 -> -6.5 | P15: ='PL-CF-BS'!L47 -> -6.5 | R15: Total Non-current Assets | T15: =D15 -> 39879.8 | U15: =E15 -> 39622.8 | V15: =F15 -> 40906.232 | W15: =G15 -> 41813.694 | X15: =H15 -> 42407.635 | Z15: Minority Interest | AA15: =K16 -> 6184 | AB15: =L15 -> -7.8 | AC15: =M15 -> -6.5 | AD15: =N15 -> -6.5 | AE15: =O15 -> -6.5 | AF15: =P15 -> -6.5
B16: 资产总计 | C16: ='PL-CF-BS'!G125 -> 51855 | D16: ='PL-CF-BS'!H125 -> 56353.4 | E16: ='PL-CF-BS'!I125 -> 61821.2 | F16: ='PL-CF-BS'!J125 -> 66152.243 | G16: ='PL-CF-BS'!K125 -> 70538.685 | H16: ='PL-CF-BS'!L125 -> 76157.704 | J16: 归母净利润 | K16: ='PL-CF-BS'!G49 -> 6184 | L16: ='PL-CF-BS'!H49 -> 6408.7 | M16: ='PL-CF-BS'!I49 -> 6127.2 | N16: ='PL-CF-BS'!J49 -> 6786.0987 | O16: ='PL-CF-BS'!K49 -> 7382.0999 | P16: ='PL-CF-BS'!L49 -> 7932.0682 | R16: Total Assets | T16: =D16 -> 56353.4 | U16: =E16 -> 61821.2 | V16: =F16 -> 66152.243 | W16: =G16 -> 70538.685 | X16: =H16 -> 76157.704 | Z16: Net Profit Attributable to Owners of the Parent | AB16: =L16 -> 6408.7 | AC16: =M16 -> 6127.2 | AD16: =N16 -> 6786.0987 | AE16: =O16 -> 7382.0999 | AF16: =P16 -> 7932.0682
T17: =D17 -> 0 | U17: =E17 -> 0 | V17: =F17 -> 0 | W17: =G17 -> 0 | X17: =H17 -> 0
B18: 应付账款 | C18: ='PL-CF-BS'!G128 -> 6347 | D18: ='PL-CF-BS'!H128 -> 6468.3 | E18: ='PL-CF-BS'!I128 -> 6727.7 | F18: ='PL-CF-BS'!J128 -> 7155.0559 | G18: ='PL-CF-BS'!K128 -> 7392.1166 | H18: ='PL-CF-BS'!L128 -> 7764.6223 | J18: 财务指标 | K18: 2023 | L18: 2024 | M18: 2025 | N18: 2026E | O18: 2027E | P18: 2028E | R18: Accounts Payable | T18: =D18 -> 6468.3 | U18: =E18 -> 6727.7 | V18: =F18 -> 7155.0559 | W18: =G18 -> 7392.1166 | X18: =H18 -> 7764.6223 | Z18: Financial Ratios | AA18: =K18 -> 2023 | AB18: =L18 -> 2024 | AC18: =M18 -> 2025 | AD18: =N18 -> 2026E | AE18: =O18 -> 2027E | AF18: 2028E
B19: 负债及费用准备金其他流动负债 | C19: ='PL-CF-BS'!G129 -> 977.1 | D19: ='PL-CF-BS'!H129 -> 1093.1 | E19: ='PL-CF-BS'!I129 -> 1117.7 | F19: ='PL-CF-BS'!J129 -> 1117.7 | G19: ='PL-CF-BS'!K129 -> 1117.7 | H19: ='PL-CF-BS'!L129 -> 1117.7 | J19: 盈利能力 | R19: Provisions and Other Current Liabilities | T19: =D19 -> 1093.1 | U19: =E19 -> 1117.7 | V19: =F19 -> 1117.7 | W19: =G19 -> 1117.7 | X19: =H19 -> 1117.7 | Z19: Profitability ratios
B20: 其他流动负债 | C20: ='PL-CF-BS'!G130 -> 4816.1 | D20: ='PL-CF-BS'!H130 -> 4949.6 | E20: ='PL-CF-BS'!I130 -> 4782.9 | F20: ='PL-CF-BS'!J130 -> 4782.9 | G20: ='PL-CF-BS'!K130 -> 4782.9 | H20: ='PL-CF-BS'!L130 -> 4782.9 | J20: ROE | K20: ='PL-CF-BS'!G170 -> 0.21986461 | L20: ='PL-CF-BS'!H170 -> 0.20604235 | M20: ='PL-CF-BS'!I170 -> 0.17998282 | N20: ='PL-CF-BS'!J170 -> 0.18762282 | O20: ='PL-CF-BS'!K170 -> 0.19010214 | P20: ='PL-CF-BS'!L170 -> 0.18910157 | R20: Other Current Liabilities | T20: =D20 -> 4949.6 | U20: =E20 -> 4782.9 | V20: =F20 -> 4782.9 | W20: =G20 -> 4782.9 | X20: =H20 -> 4782.9 | Z20: ROE | AA20: =K20 -> 0.21986461 | AB20: =L20 -> 0.20604235 | AC20: =M20 -> 0.17998282 | AD20: =N20 -> 0.18762282 | AE20: =O20 -> 0.19010214 | AF20: =P20 -> 0.18910157
B21: 所得税 | C21: ='PL-CF-BS'!G131 -> 208.1 | D21: ='PL-CF-BS'!H131 -> 275.1 | E21: ='PL-CF-BS'!I131 -> 254.8 | F21: ='PL-CF-BS'!J131 -> 254.8 | G21: ='PL-CF-BS'!K131 -> 254.8 | H21: ='PL-CF-BS'!L131 -> 254.8 | J21: 毛利率 | K21: ='PL-CF-BS'!G165 -> 0.73855463 | L21: ='PL-CF-BS'!H165 -> 0.7418297 | M21: ='PL-CF-BS'!I165 -> 0.74318079 | N21: ='PL-CF-BS'!J165 -> 0.74418079 | O21: ='PL-CF-BS'!K165 -> 0.74718079 | P21: ='PL-CF-BS'!L165 -> 0.75018079 | R21: Income Tax Payable | T21: =D21 -> 275.1 | U21: =E21 -> 254.8 | V21: =F21 -> 254.8 | W21: =G21 -> 254.8 | X21: =H21 -> 254.8 | Z21: Gross profit margin | AA21: =K21 -> 0.73855463 | AB21: =L21 -> 0.7418297 | AC21: =M21 -> 0.74318079 | AD21: =N21 -> 0.74418079 | AE21: =O21 -> 0.74718079 | AF21: =P21 -> 0.75018079
B22: 当前借款及债务 | C22: ='PL-CF-BS'!G132 -> 2091.5 | D22: ='PL-CF-BS'!H132 -> 1381.3 | E22: ='PL-CF-BS'!I132 -> 2048.9 | F22: ='PL-CF-BS'!J132 -> 979.13333 | G22: ='PL-CF-BS'!K132 -> -172.65556 | H22: ='PL-CF-BS'!L132 -> -1116.4074 | I22: ='PL-CF-BS'!M132 -> -2171.5099 | J22: 营业利润率 | K22: ='PL-CF-BS'!G167 -> 0.5517403 | L22: ='PL-CF-BS'!H167 -> 0.55212156 | M22: ='PL-CF-BS'!I167 -> 0.5528035 | N22: ='PL-CF-BS'!J167 -> 0.54823881 | O22: ='PL-CF-BS'!K167 -> 0.54609282 | P22: ='PL-CF-BS'!L167 -> 0.54442077 | R22: Current Borrowings and Debt | T22: =D22 -> 1381.3 | U22: =E22 -> 2048.9 | V22: =F22 -> 979.13333 | W22: =G22 -> -172.65556 | X22: =H22 -> -1116.4074 | Z22: Operating profit margin | AA22: =K22 -> 0.5517403 | AB22: =L22 -> 0.55212156 | AC22: =M22 -> 0.5528035 | AD22: =N22 -> 0.54823881 | AE22: =O22 -> 0.54609282 | AF22: =P22 -> 0.54442077
B23: 当前租赁债务 | C23: ='PL-CF-BS'!G133 -> 459.8 | D23: ='PL-CF-BS'!H133 -> 468.6 | E23: ='PL-CF-BS'!I133 -> 434.5 | F23: ='PL-CF-BS'!J133 -> 434.5 | G23: ='PL-CF-BS'!K133 -> 434.5 | H23: ='PL-CF-BS'!L133 -> 434.5 | J23: 归母净利率 | K23: ='PL-CF-BS'!G169 -> 0.1501605 | L23: ='PL-CF-BS'!H169 -> 0.14737116 | M23: ='PL-CF-BS'!I169 -> 0.13909017 | N23: ='PL-CF-BS'!J169 -> 0.1473472 | O23: ='PL-CF-BS'!K169 -> 0.15252813 | P23: ='PL-CF-BS'!L169 -> 0.15567555 | R23: Current Lease Liabilities | T23: =D23 -> 468.6 | U23: =E23 -> 434.5 | V23: =F23 -> 434.5 | W23: =G23 -> 434.5 | X23: =H23 -> 434.5 | Z23: Net profit margin | AA23: =K23 -> 0.1501605 | AB23: =L23 -> 0.14737116 | AC23: =M23 -> 0.13909017 | AD23: =N23 -> 0.1473472 | AE23: =O23 -> 0.15252813 | AF23: =P23 -> 0.15567555
B24: 流动负债合计 | C24: ='PL-CF-BS'!G136 -> 14899.6 | D24: ='PL-CF-BS'!H136 -> 14636 | E24: ='PL-CF-BS'!I136 -> 15366.5 | F24: ='PL-CF-BS'!J136 -> 14724.089 | G24: ='PL-CF-BS'!K136 -> 13809.361 | H24: ='PL-CF-BS'!L136 -> 13238.115 | I24: ='PL-CF-BS'!K155 -> 40280.096 | J24: 成长能力 | R24: Total Current Liabilities | T24: =D24 -> 14636 | U24: =E24 -> 15366.5 | V24: =F24 -> 14724.089 | W24: =G24 -> 13809.361 | X24: =H24 -> 13238.115 | Z24: Growth rates
B25: 员工退休义务准备金 | C25: ='PL-CF-BS'!G138 -> 562 | D25: ='PL-CF-BS'!H138 -> 668.9 | E25: ='PL-CF-BS'!I138 -> 684 | F25: ='PL-CF-BS'!J138 -> 684 | G25: ='PL-CF-BS'!K138 -> 684 | H25: ='PL-CF-BS'!L138 -> 684 | J25: 营业收入增长率 | K25: ='PL-CF-BS'!G7 -> 0.076368179 | L25: ='PL-CF-BS'!H7 -> 0.055950814 | M25: ='PL-CF-BS'!I7 -> 0.012997047 | N25: ='PL-CF-BS'!J7 -> 0.045472611 | O25: ='PL-CF-BS'!K7 -> 0.05087653 | P25: ='PL-CF-BS'!L7 -> 0.052776175 | R25: Employee Retirement Benefit Obligations | T25: =D25 -> 668.9 | U25: =E25 -> 684 | V25: =F25 -> 684 | W25: =G25 -> 684 | X25: =H25 -> 684 | Z25: Revenue growth rate | AA25: =K25 -> 0.076368179 | AB25: =L25 -> 0.055950814 | AC25: =M25 -> 0.012997047 | AD25: =N25 -> 0.045472611 | AE25: =O25 -> 0.05087653 | AF25: =P25 -> 0.052776175
B26: 负债及费用及其他项目的准备金 | C26: ='PL-CF-BS'!G139 -> 68.8 | D26: ='PL-CF-BS'!H139 -> 76.8 | E26: ='PL-CF-BS'!I139 -> 84.5 | F26: ='PL-CF-BS'!J139 -> 84.5 | G26: ='PL-CF-BS'!K139 -> 84.5 | H26: ='PL-CF-BS'!L139 -> 84.5 | J26: 营业利润增长率 | K26: ='PL-CF-BS'!G10 -> 0.098698493 | L26: ='PL-CF-BS'!H10 -> 0.060633359 | M26: ='PL-CF-BS'!I10 -> 0.014842002 | N26: ='PL-CF-BS'!J10 -> 0.046879365 | O26: ='PL-CF-BS'!K10 -> 0.055112906 | P26: ='PL-CF-BS'!L10 -> 0.057003169 | R26: Provisions and Other Liabilities | T26: =D26 -> 76.8 | U26: =E26 -> 84.5 | V26: =F26 -> 84.5 | W26: =G26 -> 84.5 | X26: =H26 -> 84.5 | Z26: Operating profit growth rate | AA26: =K26 -> 0.098698493 | AB26: =L26 -> 0.060633359 | AC26: =M26 -> 0.014842002 | AD26: =N26 -> 0.046879365 | AE26: =O26 -> 0.055112906 | AF26: =P26 -> 0.057003169
B27: 递延税项负债 | C27: ='PL-CF-BS'!G140 -> 1102.2 | D27: ='PL-CF-BS'!H140 -> 1188.8 | E27: ='PL-CF-BS'!I140 -> 1249.8 | F27: ='PL-CF-BS'!J140 -> 1249.8 | G27: ='PL-CF-BS'!K140 -> 1249.8 | H27: ='PL-CF-BS'!L140 -> 1249.8 | J27: 净利润增长率 | K27: ='PL-CF-BS'!G50 -> 0.083657519 | L27: ='PL-CF-BS'!H50 -> 0.036335705 | M27: ='PL-CF-BS'!I50 -> -0.043924665 | N27: ='PL-CF-BS'!J50 -> 0.10753668 | O27: ='PL-CF-BS'!K50 -> 0.08782678 | P27: ='PL-CF-BS'!L50 -> 0.074500252 | R27: Deferred Tax Liabilities | T27: =D27 -> 1188.8 | U27: =E27 -> 1249.8 | V27: =F27 -> 1249.8 | W27: =G27 -> 1249.8 | X27: =H27 -> 1249.8 | Z27: Net profit growth rate | AA27: =K27 -> 0.083657519 | AB27: =L27 -> 0.036335705 | AC27: =M27 -> -0.043924665 | AD27: =N27 -> 0.10753668 | AE27: =O27 -> 0.08782678 | AF27: =P27 -> 0.074500252
B28: 非流动负债及债务 | C28: ='PL-CF-BS'!G141 -> 4746.7 | D28: ='PL-CF-BS'!H141 -> 5187.1 | E28: ='PL-CF-BS'!I141 -> 8069.7 | F28: ='PL-CF-BS'!J141 -> 11110.8 | G28: ='PL-CF-BS'!K141 -> 13976.567 | H28: ='PL-CF-BS'!L141 -> 17290.422 | J28: 偿债能力 | R28: Non-current Borrowings and Debt | T28: =D28 -> 5187.1 | U28: =E28 -> 8069.7 | V28: =F28 -> 11110.8 | W28: =G28 -> 13976.567 | X28: =H28 -> 17290.422 | Z28: Liquidity & Solvency ratio
B29: 非流动租赁债务 | C29: ='PL-CF-BS'!G142 -> 1394.2 | D29: ='PL-CF-BS'!H142 -> 1458 | E29: ='PL-CF-BS'!I142 -> 1362.9 | F29: ='PL-CF-BS'!J142 -> 910.08333 | G29: ='PL-CF-BS'!K142 -> 449.86111 | H29: ='PL-CF-BS'!L142 -> -5.6851852 | J29: 流动比 | K29: ='PL-CF-BS'!G113/'PL-CF-BS'!G136 -> 1.0956871 | L29: ='PL-CF-BS'!H113/'PL-CF-BS'!H136 -> 1.1255534 | M29: ='PL-CF-BS'!I113/'PL-CF-BS'!I136 -> 1.444597 | N29: ='PL-CF-BS'!J113/'PL-CF-BS'!J136 -> 1.7146059 | O29: ='PL-CF-BS'!K113/'PL-CF-BS'!K136 -> 2.0801101 | P29: ='PL-CF-BS'!L113/'PL-CF-BS'!L136 -> 2.5494618 | R29: Non-current Lease Liabilities | T29: =D29 -> 1458 | U29: =E29 -> 1362.9 | V29: =F29 -> 910.08333 | W29: =G29 -> 449.86111 | X29: =H29 -> -5.6851852 | Z29: Current ratio | AA29: =K29 -> 1.0956871 | AB29: =L29 -> 1.1255534 | AC29: =M29 -> 1.444597 | AD29: =N29 -> 1.7146059 | AE29: =O29 -> 2.0801101 | AF29: =P29 -> 2.5494618
B30: 长期负债合计 | C30: ='PL-CF-BS'!G143 -> 7873.9 | D30: ='PL-CF-BS'!H143 -> 8579.6 | E30: ='PL-CF-BS'!I143 -> 11450.9 | F30: ='PL-CF-BS'!J143 -> 14039.183 | G30: ='PL-CF-BS'!K143 -> 16444.728 | H30: ='PL-CF-BS'!L143 -> 19303.037 | J30: 速动比 | K30: =('PL-CF-BS'!G113-'PL-CF-BS'!G108)/'PL-CF-BS'!G136 -> 0.75388601 | L30: =('PL-CF-BS'!H113-'PL-CF-BS'!H108)/'PL-CF-BS'!H136 -> 0.74281224 | M30: =('PL-CF-BS'!I113-'PL-CF-BS'!I108)/'PL-CF-BS'!I136 -> 1.086656 | N30: =('PL-CF-BS'!J113-'PL-CF-BS'!J108)/'PL-CF-BS'!J136 -> 1.3223475 | O30: =('PL-CF-BS'!K113-'PL-CF-BS'!K108)/'PL-CF-BS'!K136 -> 1.6396127 | P30: =('PL-CF-BS'!L113-'PL-CF-BS'!L108)/'PL-CF-BS'!L136 -> 2.0637572 | R30: Total Non-current Liabilities | T30: =D30 -> 8579.6 | U30: =E30 -> 11450.9 | V30: =F30 -> 14039.183 | W30: =G30 -> 16444.728 | X30: =H30 -> 19303.037 | Z30: Quick ratio | AA30: =K30 -> 0.75388601 | AB30: =L30 -> 0.74281224 | AC30: =M30 -> 1.086656 | AD30: =N30 -> 1.3223475 | AE30: =O30 -> 1.6396127 | AF30: =P30 -> 2.0637572
B31: 负债合计 | C31: ='PL-CF-BS'!G145 -> 22773.5 | D31: ='PL-CF-BS'!H145 -> 23215.6 | E31: ='PL-CF-BS'!I145 -> 26817.4 | F31: ='PL-CF-BS'!J145 -> 28763.273 | G31: ='PL-CF-BS'!K145 -> 30254.089 | H31: ='PL-CF-BS'!L145 -> 32541.152 | R31: Total Liabilities | T31: =D31 -> 23215.6 | U31: =E31 -> 26817.4 | V31: =F31 -> 28763.273 | W31: =G31 -> 30254.089 | X31: =H31 -> 32541.152
B32: 股本 | C32: ='PL-CF-BS'!G148 -> 106.9 | D32: ='PL-CF-BS'!H148 -> 106.9 | E32: ='PL-CF-BS'!I148 -> 106.8 | F32: ='PL-CF-BS'!J148 -> 152.46667 | G32: ='PL-CF-BS'!K148 -> 212.85556 | H32: ='PL-CF-BS'!L148 -> 270.07407 | J32: 每股指标与估值 | K32: =K18 -> 2023 | L32: =L18 -> 2024 | M32: =M18 -> 2025 | N32: =N18 -> 2026E | O32: =O18 -> 2027E | P32: 2028E | R32: Share Capital | T32: =D32 -> 106.9 | U32: =E32 -> 106.8 | V32: =F32 -> 152.46667 | W32: =G32 -> 212.85556 | X32: =H32 -> 270.07407 | Z32: Valuation | AA32: =K32 -> 2023 | AB32: =L32 -> 2024 | AC32: =M32 -> 2025 | AD32: =N32 -> 2026E | AE32: =O32 -> 2027E | AF32: 2028E
B33: 额外实收资本 | C33: ='PL-CF-BS'!G149 -> 3370.2 | D33: ='PL-CF-BS'!H149 -> 3444.3 | E33: ='PL-CF-BS'!I149 -> 3509.8 | F33: ='PL-CF-BS'!J149 -> 3509.8 | G33: ='PL-CF-BS'!K149 -> 3444.3 | H33: ='PL-CF-BS'!L149 -> 3444.3 | J33: 每股指标 | R33: Additional Paid-in Capital | T33: =D33 -> 3444.3 | U33: =E33 -> 3509.8 | V33: =F33 -> 3509.8 | W33: =G33 -> 3444.3 | X33: =H33 -> 3444.3 | Z33: Per share
B34: 其他储备金 | C34: ='PL-CF-BS'!G150 -> 13799.1 | D34: ='PL-CF-BS'!H150 -> 16144.8 | E34: ='PL-CF-BS'!I150 -> 18166.5 | F34: ='PL-CF-BS'!J150 -> 18166.5 | G34: ='PL-CF-BS'!K150 -> 18166.5 | H34: ='PL-CF-BS'!L150 -> 18166.5 | J34: EPS | K34: ='PL-CF-BS'!G58 -> 11.549062 | L34: ='PL-CF-BS'!H58 -> 11.994302 | M34: ='PL-CF-BS'!I58 -> 11.48238 | N34: ='PL-CF-BS'!J58 -> 12.749256 | O34: ='PL-CF-BS'!K58 -> 13.901774 | P34: ='PL-CF-BS'!L58 -> 14.970541 | R34: Other Reserves | T34: =D34 -> 16144.8 | U34: =E34 -> 18166.5 | V34: =F34 -> 18166.5 | W34: =G34 -> 18166.5 | X34: =H34 -> 18166.5 | Z34: EPS | AA34: =K34 -> 11.549062 | AB34: =L34 -> 11.994302 | AC34: =M34 -> 11.48238 | AD34: =N34 -> 12.749256 | AE34: =O34 -> 13.901774 | AF34: =P34 -> 14.970541
B35: 其他综合收益 | C35: ='PL-CF-BS'!G153 -> 12307.8 | D35: ='PL-CF-BS'!H153 -> 13686.5 | E35: ='PL-CF-BS'!I153 -> 13919.3 | F35: ='PL-CF-BS'!J153 -> 15804.904 | G35: ='PL-CF-BS'!K153 -> 18705.64 | H35: ='PL-CF-BS'!L153 -> 21980.378 | J35: BVPS | K35: ='PL-CF-BS'!G155/'PL-CF-BS'!G55 -> 54.298332 | L35: ='PL-CF-BS'!H155/'PL-CF-BS'!H55 -> 62.011145 | M35: ='PL-CF-BS'!I155/'PL-CF-BS'!I55 -> 65.50234 | N35: ='PL-CF-BS'!J155/'PL-CF-BS'!J55 -> 70.235371 | O35: ='PL-CF-BS'!K155/'PL-CF-BS'!K55 -> 75.854404 | P35: ='PL-CF-BS'!L155/'PL-CF-BS'!L55 -> 82.310943 | R35: Other Comprehensive Income (OCI) | T35: =D35 -> 13686.5 | U35: =E35 -> 13919.3 | V35: =F35 -> 15804.904 | W35: =G35 -> 18705.64 | X35: =H35 -> 21980.378 | Z35: BVPS | AA35: =K35 -> 54.298332 | AB35: =L35 -> 62.011145 | AC35: =M35 -> 65.50234 | AD35: =N35 -> 70.235371 | AE35: =O35 -> 75.854404 | AF35: =P35 -> 82.310943
B36: 归属于公司所有者的净利润 | C36: ='PL-CF-BS'!#REF! -> #REF! | D36: ='PL-CF-BS'!#REF! -> #REF! | E36: ='PL-CF-BS'!#REF! -> #REF! | F36: ='PL-CF-BS'!#REF! -> #REF! | G36: ='PL-CF-BS'!#REF! -> #REF! | H36: ='PL-CF-BS'!#REF! -> #REF! | J36: 估值 | R36: Net Income Attributable to Owners of the Company | T36: =T37+T38 -> 33142.3 | U36: =U37+U38 -> 35054.4 | V36: =V37+V38 -> 37393.47 | W36: =W37+W38 -> 40289.096 | X36: =X37+X38 -> 43621.052 | Z36: Valuation ratios
B37: 归母股东权益 | C37: ='PL-CF-BS'!G159 -> 29081.6 | D37: ='PL-CF-BS'!H159 -> 33137.8 | E37: ='PL-CF-BS'!I159 -> 35003.8 | F37: ='PL-CF-BS'!J159 -> 37388.97 | G37: ='PL-CF-BS'!K159 -> 40284.596 | H37: ='PL-CF-BS'!L159 -> 43616.552 | J37: P/E | K37: =K41/K34 -> 31.331549 | L37: =L41/L34 -> 30.16849 | M37: =M41/M34 -> 31.5135 | N37: =N41/N34 -> 28.382049 | O37: =O41/O34 -> 26.029052 | P37: =P41/P34 -> 24.170803 | R37: Equity Attributable to Owners of the Company | T37: =D37 -> 33137.8 | U37: =E37 -> 35003.8 | V37: =F37 -> 37388.97 | W37: =G37 -> 40284.596 | X37: =H37 -> 43616.552 | Z37: P/E | AA37: =K37 -> 31.331549 | AB37: =L37 -> 30.16849 | AC37: =M37 -> 31.5135 | AD37: =N37 -> 28.382049 | AE37: =O37 -> 26.029052 | AF37: =P37 -> 24.170803
B38: 少数股东权益 | C38: ='PL-CF-BS'!G158 -> 7.3 | D38: ='PL-CF-BS'!H158 -> 4.5 | E38: ='PL-CF-BS'!I158 -> 50.6 | F38: ='PL-CF-BS'!J158 -> 4.5 | G38: ='PL-CF-BS'!K158 -> 4.5 | H38: ='PL-CF-BS'!L158 -> 4.5 | J38: P/B | K38: =K41/K35 -> 6.6641089 | L38: =L41/L35 -> 5.8352414 | M38: =M41/M35 -> 5.5242301 | N38: =N41/N35 -> 5.1519625 | O38: =O41/O35 -> 4.7703229 | P38: =P41/P35 -> 4.3961348 | R38: Non-controlling Interests | T38: =D38 -> 4.5 | U38: =E38 -> 50.6 | V38: =F38 -> 4.5 | W38: =G38 -> 4.5 | X38: =H38 -> 4.5 | Z38: P/B | AA38: =K38 -> 6.6641089 | AB38: =L38 -> 5.8352414 | AC38: =M38 -> 5.5242301 | AD38: =N38 -> 5.1519625 | AE38: =O38 -> 4.7703229 | AF38: =P38 -> 4.3961348
B39: 权益总计 | C39: ='PL-CF-BS'!G159 -> 29081.6 | D39: ='PL-CF-BS'!H159 -> 33137.8 | E39: ='PL-CF-BS'!I159 -> 35003.8 | F39: ='PL-CF-BS'!J159 -> 37388.97 | G39: ='PL-CF-BS'!K159 -> 40284.596 | H39: ='PL-CF-BS'!L159 -> 43616.552 | J39: P/S | K39: =K41*'PL-CF-BS'!G55/'PL-CF-BS'!G6 -> 4.7047613 | L39: =L41*'PL-CF-BS'!H55/'PL-CF-BS'!H6 -> 4.4459653 | M39: =M41*'PL-CF-BS'!I55/'PL-CF-BS'!I6 -> 4.383218 | N39: =N41*'PL-CF-BS'!J55/'PL-CF-BS'!J6 -> 4.1820155 | O39: =O41*'PL-CF-BS'!K55/'PL-CF-BS'!K6 -> 3.9701625 | P39: =P41*'PL-CF-BS'!L55/'PL-CF-BS'!L6 -> 3.762803 | R39: Total Equity | T39: =D39 -> 33137.8 | U39: =E39 -> 35003.8 | V39: =F39 -> 37388.97 | W39: =G39 -> 40284.596 | X39: =H39 -> 43616.552 | Z39: P/S | AA39: =K39 -> 4.7047613 | AB39: =L39 -> 4.4459653 | AC39: =M39 -> 4.383218 | AD39: =N39 -> 4.1820155 | AE39: =O39 -> 3.9701625 | AF39: =P39 -> 3.762803
B40: 负债和股东权益总计 | C40: ='PL-CF-BS'!G159+'PL-CF-BS'!G145 -> 51855.1 | D40: ='PL-CF-BS'!H159+'PL-CF-BS'!H145 -> 56353.4 | E40: ='PL-CF-BS'!I159+'PL-CF-BS'!I145 -> 61821.2 | F40: ='PL-CF-BS'!J159+'PL-CF-BS'!J145 -> 66152.243 | G40: ='PL-CF-BS'!K159+'PL-CF-BS'!K145 -> 70538.685 | H40: ='PL-CF-BS'!L159+'PL-CF-BS'!L145 -> 76157.704 | R40: Total Liabilities and Equity | T40: =D40 -> 56353.4 | U40: =E40 -> 61821.2 | V40: =F40 -> 66152.243 | W40: =G40 -> 70538.685 | X40: =H40 -> 76157.704
K41: 361.85 | L41: 361.85 | M41: 361.85 | N41: 361.85 | O41: 361.85 | P41: 361.85
B42: 现金流量表（百万美元） | C42: =K18 -> 2023 | D42: =L18 -> 2024 | E42: =M18 -> 2025 | F42: =N18 -> 2026E | G42: =O18 -> 2027E | H42: 2028E | R42: CF/S (Euro mn) | S42: =C42 -> 2023 | T42: =D42 -> 2024 | U42: =E42 -> 2025 | V42: =F42 -> 2026E | W42: =G42 -> 2027E | X42: 2028E
B43: 归属于母公司股东的净利润 | C43: ='PL-CF-BS'!G72 -> 6184 | D43: ='PL-CF-BS'!H72 -> 6408.7 | E43: ='PL-CF-BS'!I72 -> 6127.2 | F43: ='PL-CF-BS'!J72 -> 6786.0987 | G43: ='PL-CF-BS'!K72 -> 7382.0999 | H43: ='PL-CF-BS'!L72 -> 7932.0682 | R43: Net income attributable to owners of the parent | S43: =C43 -> 6184 | T43: =D43 -> 6408.7 | U43: =E43 -> 6127.2 | V43: =F43 -> 6786.0987 | W43: =G43 -> 7382.0999 | X43: =H43 -> 7932.0682
B44: 折旧摊销 | C44: ='PL-CF-BS'!G73 -> 1715 | D44: ='PL-CF-BS'!H73 -> 1855.3 | E44: ='PL-CF-BS'!I73 -> 1817.4 | F44: ='PL-CF-BS'!J73 -> 1900.0419 | G44: ='PL-CF-BS'!K73 -> 1996.7095 | H44: ='PL-CF-BS'!L73 -> 2102.0882 | R44: Depreciation and amortization | S44: =C44 -> 1715 | T44: =D44 -> 1855.3 | U44: =E44 -> 1817.4 | V44: =F44 -> 1900.0419 | W44: =G44 -> 1996.7095 | X44: =H44 -> 2102.0882
B45: 营运资金变动 | C45: ='PL-CF-BS'!G74 -> -394.9 | D45: ='PL-CF-BS'!H74 -> -226.6 | E45: ='PL-CF-BS'!I74 -> 327.4 | F45: ='PL-CF-BS'!J74 -> -198.85467 | G45: ='PL-CF-BS'!K74 -> -314.99508 | H45: ='PL-CF-BS'!L74 -> -211.60712 | R45: Changes in working capital | S45: =C45 -> -394.9 | T45: =D45 -> -226.6 | U45: =E45 -> 327.4 | V45: =F45 -> -198.85467 | W45: =G45 -> -314.99508 | X45: =H45 -> -211.60712
B46: 其他 | C46: ='PL-CF-BS'!G75 -> 100.5 | D46: ='PL-CF-BS'!H75 -> 248.6 | E46: ='PL-CF-BS'!I75 -> 384.9 | F46: ='PL-CF-BS'!J75 -> 7.8 | G46: ='PL-CF-BS'!K75 -> 7.8 | H46: ='PL-CF-BS'!L75 -> 7.8 | R46: Others | S46: =C46 -> 100.5 | T46: =D46 -> 248.6 | U46: =E46 -> 384.9 | V46: =F46 -> 7.8 | W46: =G46 -> 7.8 | X46: =H46 -> 7.8
B47: 经营活动现金流 | C47: ='PL-CF-BS'!G76 -> 7604.6 | D47: ='PL-CF-BS'!H76 -> 8286 | E47: ='PL-CF-BS'!I76 -> 8656.9 | F47: ='PL-CF-BS'!J76 -> 8495.086 | G47: ='PL-CF-BS'!K76 -> 9071.6143 | H47: ='PL-CF-BS'!L76 -> 9830.3493 | R47: Cash flow from operating activities | S47: =C47 -> 7604.6 | T47: =D47 -> 8286 | U47: =E47 -> 8656.9 | V47: =F47 -> 8495.086 | W47: =G47 -> 9071.6143 | X47: =H47 -> 9830.3493
B48: 固定资产及无形资产的购置 | C48: ='PL-CF-BS'!G79 -> -1488.7 | D48: ='PL-CF-BS'!H79 -> -1641.7 | E48: ='PL-CF-BS'!I79 -> -1495.3 | F48: ='PL-CF-BS'!J79 -> -1645.9071 | G48: ='PL-CF-BS'!K79 -> -1737.2826 | H48: ='PL-CF-BS'!L79 -> -1825.7441 | R48: Purchase of property, plant and equipment and intangible assets | S48: =C48 -> -1488.7 | T48: =D48 -> -1641.7 | U48: =E48 -> -1495.3 | V48: =F48 -> -1645.9071 | W48: =G48 -> -1737.2826 | X48: =H48 -> -1825.7441
B49: 固定资产及无形资产的处置 | C49: ='PL-CF-BS'!G80 -> 12.8 | D49: ='PL-CF-BS'!H80 -> 13.6 | E49: ='PL-CF-BS'!I80 -> 5.7 | F49: ='PL-CF-BS'!J80 -> 10.7 | G49: ='PL-CF-BS'!K80 -> 10 | H49: ='PL-CF-BS'!L80 -> 8.8 | R49: Disposal of property, plant and equipment and intangible assets | S49: =C52 -> 0 | T49: =D49 -> 13.6 | U49: =E49 -> 5.7 | V49: =F49 -> 10.7 | W49: =G49 -> 10 | X49: =H49 -> 8.8
B50: 其他金融资产的变化 | C50: ='PL-CF-BS'!G81 -> -170.7 | D50: ='PL-CF-BS'!H81 -> -1926.95 | E50: ='PL-CF-BS'!I81 -> 2509 | F50: ='PL-CF-BS'!J81 -> 137.11667 | G50: ='PL-CF-BS'!K81 -> 239.72222 | H50: ='PL-CF-BS'!L81 -> 961.9463 | R50: Changes in other financial assets | S50: =C53 -> -4143.8 | T50: =D50 -> -1926.95 | U50: =E50 -> 2509 | V50: =F50 -> 137.11667 | W50: =G50 -> 239.72222 | X50: =H50 -> 961.9463
B51: 合并范围变化的影响 | C51: ='PL-CF-BS'!G82 -> -2497.2 | D51: ='PL-CF-BS'!H82 -> -148.85 | E51: ='PL-CF-BS'!I82 -> -2426.6 | F51: ='PL-CF-BS'!J82 -> -1690.8833 | G51: ='PL-CF-BS'!K82 -> -1422.1111 | H51: ='PL-CF-BS'!L82 -> -1846.5315 | R51: Impact of changes in consolidation scope | S51: =C62 -> 0 | T51: =D51 -> -148.85 | U51: =E51 -> -2426.6 | V51: =F51 -> -1690.8833 | W51: =G51 -> -1422.1111 | X51: =H51 -> -1846.5315
B52: 终止经营业务产生的净现金收入 | C52: ='PL-CF-BS'!G83 -> 0 | D52: ='PL-CF-BS'!H83 -> 0 | E52: ='PL-CF-BS'!I83 -> 0 | F52: ='PL-CF-BS'!J83 -> 0 | G52: ='PL-CF-BS'!K83 -> 0 | H52: ='PL-CF-BS'!L83 -> 0 | R52: Net cash inflow from discontinued operations | S52: ='PL-CF-BS'!G89+'PL-CF-BS'!G96+'PL-CF-BS'!#REF! -> #REF! | T52: =D52 -> 0 | U52: =E52 -> 0 | V52: =F52 -> 0 | W52: =G52 -> 0 | X52: =H52 -> 0
B53: 投资活动现金流 | C53: ='PL-CF-BS'!G84 -> -4143.8 | D53: ='PL-CF-BS'!H84 -> -3703.9 | E53: ='PL-CF-BS'!I84 -> -1407.2 | F53: ='PL-CF-BS'!J84 -> -3188.9738 | G53: ='PL-CF-BS'!K84 -> -2909.6715 | H53: ='PL-CF-BS'!L84 -> -2701.5293 | R53: Cash flow from investing activities | S53: =C63 -> -1614.6 | T53: =D53 -> -3703.9 | U53: =E53 -> -1407.2 | V53: =F53 -> -3188.9738 | W53: =G53 -> -2909.6715 | X53: =H53 -> -2701.5293
B54: 支付的股息 | C54: ='PL-CF-BS'!G89 -> -3425.6 | D54: ='PL-CF-BS'!H89 -> -3614.9 | E54: ='PL-CF-BS'!I89 -> -3917 | F54: ='PL-CF-BS'!J89 -> -3938.8285 | G54: ='PL-CF-BS'!K89 -> -4035.741 | H54: ='PL-CF-BS'!L89 -> -4146.368 | R54: Dividends paid | S54: =C64 -> 1846.2 | T54: =D54 -> -3614.9 | U54: =E54 -> -3917 | V54: =F54 -> -3938.8285 | W54: =G54 -> -4035.741 | X54: =H54 -> -4146.368
B55: 母公司增资 | C55: ='PL-CF-BS'!G90 -> 1.5 | D55: ='PL-CF-BS'!H90 -> 69.9 | E55: ='PL-CF-BS'!I90 -> 65.6 | F55: ='PL-CF-BS'!J90 -> 45.666667 | G55: ='PL-CF-BS'!K90 -> 60.388889 | H55: ='PL-CF-BS'!L90 -> 57.218519 | I55: ='PL-CF-BS'!M90 -> 54.424691 | R55: Capital injection from parent company | T55: =D55 -> 69.9 | U55: =E55 -> 65.6 | V55: =F55 -> 45.666667 | W55: =G55 -> 60.388889 | X55: =H55 -> 57.218519
B56: 处置（收购）库存股 | C56: ='PL-CF-BS'!G91 -> -503.3 | D56: ='PL-CF-BS'!H91 -> -497.5 | E56: ='PL-CF-BS'!I91 -> -501.5 | F56: ='PL-CF-BS'!J91 -> -500 | G56: ='PL-CF-BS'!K91 -> -500 | H56: ='PL-CF-BS'!L91 -> -500 | R56: Disposal (acquisition) of treasury shares | T56: =D56 -> -497.5 | U56: =E56 -> -501.5 | V56: =F56 -> -500 | W56: =G56 -> -500 | X56: =H56 -> -500
B57: 购买非控股权益 | C57: ='PL-CF-BS'!G92 -> 0 | D57: ='PL-CF-BS'!H92 -> -13.9 | E57: ='PL-CF-BS'!I92 -> -16.3 | F57: ='PL-CF-BS'!J92 -> -10.066667 | G57: ='PL-CF-BS'!K92 -> -13.422222 | H57: ='PL-CF-BS'!L92 -> -13.262963 | R57: Purchase of non-controlling interests | T57: =D57 -> -13.9 | U57: =E57 -> -16.3 | V57: =F57 -> -10.066667 | W57: =G57 -> -13.422222 | X57: =H57 -> -13.262963
B58: 发放（偿还）短期贷款 | C58: ='PL-CF-BS'!G93 -> -823.7 | D58: ='PL-CF-BS'!H93 -> -1775.9 | E58: ='PL-CF-BS'!I93 -> -609.7 | F58: ='PL-CF-BS'!J93 -> -1069.7667 | G58: ='PL-CF-BS'!K93 -> -1151.7889 | H58: ='PL-CF-BS'!L93 -> -943.75185 | R58: Issuance (repayment) of short-term loans | T58: =D58 -> -1775.9 | U58: =E58 -> -609.7 | V58: =F58 -> -1069.7667 | W58: =G58 -> -1151.7889 | X58: =H58 -> -943.75185
B59: 发行（偿还）长期借款 | C59: ='PL-CF-BS'!G94 -> 3567.1 | D59: ='PL-CF-BS'!H94 -> 1529.4 | E59: ='PL-CF-BS'!I94 -> 4057.3 | F59: ='PL-CF-BS'!J94 -> 3051.2667 | G59: ='PL-CF-BS'!K94 -> 2879.3222 | H59: ='PL-CF-BS'!L94 -> 3329.2963 | R59: Issuance (repayment) of long-term borrowings | T59: =D59 -> 1529.4 | U59: =E59 -> 4057.3 | V59: =F59 -> 3051.2667 | W59: =G59 -> 2879.3222 | X59: =H59 -> 3329.2963
B60: 偿还长期借款 | C60: ='PL-CF-BS'!G95 -> 0 | D60: ='PL-CF-BS'!H95 -> -7.9 | E60: ='PL-CF-BS'!I95 -> -22.6 | F60: ='PL-CF-BS'!J95 -> -10.166667 | G60: ='PL-CF-BS'!K95 -> -13.555556 | H60: ='PL-CF-BS'!L95 -> -15.440741 | R60: Repayment of long-term borrowings | T60: =D60 -> -7.9 | U60: =E60 -> -22.6 | V60: =F60 -> -10.166667 | W60: =G60 -> -13.555556 | X60: =H60 -> -15.440741
B61: 偿还租赁债务 | C61: ='PL-CF-BS'!G96 -> -430.6 | D61: ='PL-CF-BS'!H96 -> -474.25 | E61: ='PL-CF-BS'!I96 -> -453.6 | F61: ='PL-CF-BS'!J96 -> -452.81667 | G61: ='PL-CF-BS'!K96 -> -460.22222 | H61: ='PL-CF-BS'!L96 -> -455.5463 | R61: Repayment of lease liabilities | T61: =D61 -> -474.25 | U61: =E61 -> -453.6 | V61: =F61 -> -452.81667 | W61: =G61 -> -460.22222 | X61: =H61 -> -455.5463
B62: 终止经营业务产生的净现金收入 | C62: ='PL-CF-BS'!G97 -> 0 | D62: ='PL-CF-BS'!H97 -> 0 | E62: ='PL-CF-BS'!I97 -> 0 | F62: ='PL-CF-BS'!J97 -> 0 | G62: ='PL-CF-BS'!K97 -> 0 | H62: ='PL-CF-BS'!L97 -> 0 | R62: Net cash inflow from discontinued operations | T62: =D62 -> 0 | U62: =E62 -> 0 | V62: =F62 -> 0 | W62: =G62 -> 0 | X62: =H62 -> 0
B63: 筹资活动现金流 | C63: ='PL-CF-BS'!G98 -> -1614.6 | D63: ='PL-CF-BS'!H98 -> -4785.05 | E63: ='PL-CF-BS'!I98 -> -1397.8 | F63: ='PL-CF-BS'!J98 -> -2884.7118 | G63: ='PL-CF-BS'!K98 -> -3235.0188 | H63: ='PL-CF-BS'!L98 -> -2687.8551 | R63: Cash flow from financing activities | T63: =D63 -> -4785.05 | U63: =E63 -> -1397.8 | V63: =F63 -> -2884.7118 | W63: =G63 -> -3235.0188 | X63: =H63 -> -2687.8551
B64: 现金净增加额 | C64: =C47+C53+C63 -> 1846.2 | D64: =D47+D53+D63 -> -202.95 | E64: =E47+E53+E63 -> 5851.9 | F64: =F47+F53+F63 -> 2421.4004 | G64: =G47+G53+G63 -> 2926.9241 | H64: =H47+H53+H63 -> 4440.9649 | R64: Net increase in cash | T64: =D64 -> -202.95 | U64: =E64 -> 5851.9 | V64: =F64 -> 2421.4004 | W64: =G64 -> 2926.9241 | X64: =H64 -> 4440.9649

Sheet DCF 
A1: 1
C2: Discounted Cash Flow
C3: CNY mn
C4: Free cashflow forecast | E4: 2023 | F4: 2024 | G4: 2025E | H4: 2026E | I4: 2027E | J4: 2028E | K4: 2029E | L4: 2030E | M4: 2031E | N4: 2032E
C5: Net Revenue | E5: ='PL-CF-BS'!G6 -> 41182.6 | F5: ='PL-CF-BS'!H6 -> 43486.8 | G5: ='PL-CF-BS'!I6 -> 44052 | H5: ='PL-CF-BS'!J6 -> 46055.159 | I5: ='PL-CF-BS'!K6 -> 48398.286 | J5: ='PL-CF-BS'!L6 -> 50952.563 | K5: ='PL-CF-BS'!M6 -> 53661.992 | L5: ='PL-CF-BS'!N6 -> 56524.137 | ... N5: ='PL-CF-BS'!P6 -> 62743.114
D6: YoY | F6: =F5/E5-1 -> 0.055950814 | G6: =G5/F5-1 -> 0.012997047 | H6: =H5/G5-1 -> 0.045472611 | I6: =I5/H5-1 -> 0.05087653 | J6: =J5/I5-1 -> 0.052776175 | K6: =K5/J5-1 -> 0.05317553 | L6: =L5/K5-1 -> 0.05333654 | M6: =M5/L5-1 -> 0.053496771 | N6: =N5/M5-1 -> 0.053656185
C7: EBIT | E7: ='PL-CF-BS'!G22-'PL-CF-BS'!G39 -> 7693.4 | F7: ='PL-CF-BS'!H22-'PL-CF-BS'!H39 -> 8249.8 | G7: ='PL-CF-BS'!I22-'PL-CF-BS'!I39 -> 8386.5 | H7: ='PL-CF-BS'!J22-'PL-CF-BS'!J39 -> 9024.139 | I7: ='PL-CF-BS'!K22-'PL-CF-BS'!K39 -> 9732.3131 | J7: ='PL-CF-BS'!L22-'PL-CF-BS'!L39 -> 10484 | K7: ='PL-CF-BS'!M22-'PL-CF-BS'!M39 -> 11277.434 | L7: ='PL-CF-BS'!N22-'PL-CF-BS'!N39 -> 12132.973 | ... N7: ='PL-CF-BS'!P22-'PL-CF-BS'!P39 -> 14022.345
D8: YoY | F8: =F7/E7-1 -> 0.07232173 | G8: =G7/F7-1 -> 0.016570099 | H8: =H7/G7-1 -> 0.076031597 | I8: =I7/H7-1 -> 0.078475535 | J8: =J7/I7-1 -> 0.077236197 | K8: =K7/J7-1 -> 0.075680455 | L8: =L7/K7-1 -> 0.075862946 | M8: =M7/L7-1 -> 0.075167178 | N8: =N7/M7-1 -> 0.07492317
D9: EBIT Margin | E9: =E7/E5 -> 0.18681191 | F9: =F7/F5 -> 0.18970814 | G9: =G7/G5 -> 0.19037728 | H9: =H7/H5 -> 0.19594198 | I9: =I7/I5 -> 0.20108797 | J9: =J7/J5 -> 0.20576001 | K9: =K7/K5 -> 0.21015682 | L9: =L7/L5 -> 0.21465119 | ... N9: =N7/N5 -> 0.2234882
C10: EBIT*(1 - t) | E10: =E7*(1-年度版model!B68) -> 5337.3549 | F10: =F7*(1-$L$16) -> 6187.35 | G10: =G7*(1-$L$16) -> 6289.875 | H10: =H7*(1-$L$16) -> 6768.1042 | I10: =I7*(1-$L$16) -> 7299.2348 | J10: =J7*(1-$L$16) -> 7863 | K10: =K7*(1-$L$16) -> 8458.0754 | L10: =L7*(1-$L$16) -> 9099.7299 | M10: =M7*(1-$L$16) -> 9783.7309 | N10: =N7*(1-$L$16) -> 10516.759
C11: + | D11: Depreciation and Amortization | E11: ='PL-CF-BS'!G73 -> 1715 | F11: ='PL-CF-BS'!H73 -> 1855.3 | G11: ='PL-CF-BS'!I73 -> 1817.4 | H11: ='PL-CF-BS'!J73 -> 1900.0419 | I11: ='PL-CF-BS'!K73 -> 1996.7095 | J11: ='PL-CF-BS'!L73 -> 2102.0882 | K11: ='PL-CF-BS'!M73 -> 2213.8678 | L11: ='PL-CF-BS'!N73 -> 2331.9478 | ... N11: ='PL-CF-BS'!P73 -> 2588.5167
C12: - | D12: Change in working capital | E12: ='PL-CF-BS'!G74 -> -394.9 | F12: ='PL-CF-BS'!H74 -> -226.6 | G12: ='PL-CF-BS'!I74 -> 327.4 | H12: ='PL-CF-BS'!J74 -> -198.85467 | I12: ='PL-CF-BS'!K74 -> -314.99508 | J12: ='PL-CF-BS'!L74 -> -211.60712 | K12: ='PL-CF-BS'!M74 -> -117.9108 | L12: ='PL-CF-BS'!N74 -> -253.44116 | ... N12: ='PL-CF-BS'!P74 -> -241.04194
C13: - | D13: Capex | E13: ='PL-CF-BS'!G79 -> -1488.7 | F13: ='PL-CF-BS'!H79 -> -1641.7 | G13: ='PL-CF-BS'!I79 -> -1495.3 | H13: ='PL-CF-BS'!J79 -> -1645.9071 | I13: ='PL-CF-BS'!K79 -> -1737.2826 | J13: ='PL-CF-BS'!L79 -> -1825.7441 | K13: ='PL-CF-BS'!M79 -> -1897.0787 | L13: ='PL-CF-BS'!N79 -> -2018.1644 | ... N13: ='PL-CF-BS'!P79 -> -2236.5603
C14: Free Cash Flows | E14: =SUM(E10:E13) -> 5168.7549 | F14: =SUM(F10:F13) -> 6174.35 | G14: =SUM(G10:G13) -> 6939.375 | H14: =SUM(H10:H13) -> 6823.3844 | I14: =SUM(I10:I13) -> 7243.6666 | J14: =SUM(J10:J13) -> 7927.7369 | K14: =SUM(K10:K13) -> 8656.9538 | L14: =SUM(L10:L13) -> 9160.0723 | ... N14: =SUM(N10:N13) -> 10627.673
C15: DCF Analysis
D16: PV of FCF | E16: =NPV(L24,I14:N14)+H14 -> 49046.311 | K16: Tax rate | L16: 0.25
D17: Terminal value | E17: =N14*(1+L25)/(L24-L25) -> 257222.32 | K17: Debt ratio | L17: 0.1
D18: PV of terminal value | E18: =E17/(1+L24)^6 -> 173967.26 | K18: Beta | L18: 0.9
D19: Enterprise Value | E19: =E16+E18 -> 223013.57 | K19: Risk free rate | L19: 0.02
D20: Net Cash/(Debt), Minority interests | E20: =-年度版model!H163 -> -5225.6146 | K20: Risk premium | L20: 0.06
D21: Equity Value | E21: =E19+E20 -> 217787.96 | K21: Equity cost | L21: =L19+L18*L20 -> 0.074
D22: Equity value per share (EUR) | E22: =E21/'PL-CF-BS'!H55 -> 407.60445 | K22: Debt cost | L22: 0.01
K23: Debt cost (After tax) | L23: =L22*(1-L16) -> 0.0075
K24: WACC | L24: =L23*L17+L21*(1-L17) -> 0.06735
K25: Perpetual Growth | L25: 0.025
E28: Equity value per share (USD)
E29: Perpetual Growth | H29: =I29-0.1% -> 0.022 | I29: =J29-0.1% -> 0.023 | J29: =K29-0.1% -> 0.024 | K29: =L25 -> 0.025 | L29: =K29+0.1% -> 0.026 | M29: =L29+0.1% -> 0.027
E30: WACC | G30: =G31-0.1% -> 0.06435 | H30: =($E$20+(NPV($G30,$I$14:$N$14)+$H$14)+((($N$14*(1+H$29)/($G30-H$29)))/(1+$G30)^6))/'PL-CF-BS'!$H$55 -> 412.97017 | I30: =($E$20+(NPV($G30,$I$14:$N$14)+$H$14)+((($N$14*(1+I$29)/($G30-I$29)))/(1+$G30)^6))/'PL-CF-BS'!$H$55 -> 421.28574 | J30: =($E$20+(NPV($G30,$I$14:$N$14)+$H$14)+((($N$14*(1+J$29)/($G30-J$29)))/(1+$G30)^6))/'PL-CF-BS'!$H$55 -> 430.01348 | K30: =($E$20+(NPV($G30,$I$14:$N$14)+$H$14)+((($N$14*(1+K$29)/($G30-K$29)))/(1+$G30)^6))/'PL-CF-BS'!$H$55 -> 439.18482 | L30: =($E$20+(NPV($G30,$I$14:$N$14)+$H$14)+((($N$14*(1+L$29)/($G30-L$29)))/(1+$G30)^6))/'PL-CF-BS'!$H$55 -> 448.83445 | M30: =($E$20+(NPV($G30,$I$14:$N$14)+$H$14)+((($N$14*(1+M$29)/($G30-M$29)))/(1+$G30)^6))/'PL-CF-BS'!$H$55 -> 459.0008
G31: =G32-0.1% -> 0.06535 | H31: =($E$20+(NPV($G31,$I$14:$N$14)+$H$14)+((($N$14*(1+H$29)/($G31-H$29)))/(1+$G31)^6))/'PL-CF-BS'!$H$55 -> 403.27698 | I31: =($E$20+(NPV($G31,$I$14:$N$14)+$H$14)+((($N$14*(1+I$29)/($G31-I$29)))/(1+$G31)^6))/'PL-CF-BS'!$H$55 -> 411.17175 | J31: =($E$20+(NPV($G31,$I$14:$N$14)+$H$14)+((($N$14*(1+J$29)/($G31-J$29)))/(1+$G31)^6))/'PL-CF-BS'!$H$55 -> 419.44836 | K31: =($E$20+(NPV($G31,$I$14:$N$14)+$H$14)+((($N$14*(1+K$29)/($G31-K$29)))/(1+$G31)^6))/'PL-CF-BS'!$H$55 -> 428.13522 | L31: =($E$20+(NPV($G31,$I$14:$N$14)+$H$14)+((($N$14*(1+L$29)/($G31-L$29)))/(1+$G31)^6))/'PL-CF-BS'!$H$55 -> 437.26359 | M31: =($E$20+(NPV($G31,$I$14:$N$14)+$H$14)+((($N$14*(1+M$29)/($G31-M$29)))/(1+$G31)^6))/'PL-CF-BS'!$H$55 -> 446.86803
G32: =G33-0.1% -> 0.06635 | H32: =($E$20+(NPV($G32,$I$14:$N$14)+$H$14)+((($N$14*(1+H$29)/($G32-H$29)))/(1+$G32)^6))/'PL-CF-BS'!$H$55 -> 394.02192 | I32: =($E$20+(NPV($G32,$I$14:$N$14)+$H$14)+((($N$14*(1+I$29)/($G32-I$29)))/(1+$G32)^6))/'PL-CF-BS'!$H$55 -> 401.52538 | J32: =($E$20+(NPV($G32,$I$14:$N$14)+$H$14)+((($N$14*(1+J$29)/($G32-J$29)))/(1+$G32)^6))/'PL-CF-BS'!$H$55 -> 409.3832 | K32: =($E$20+(NPV($G32,$I$14:$N$14)+$H$14)+((($N$14*(1+K$29)/($G32-K$29)))/(1+$G32)^6))/'PL-CF-BS'!$H$55 -> 417.62108 | L32: =($E$20+(NPV($G32,$I$14:$N$14)+$H$14)+((($N$14*(1+L$29)/($G32-L$29)))/(1+$G32)^6))/'PL-CF-BS'!$H$55 -> 426.26728 | M32: =($E$20+(NPV($G32,$I$14:$N$14)+$H$14)+((($N$14*(1+M$29)/($G32-M$29)))/(1+$G32)^6))/'PL-CF-BS'!$H$55 -> 435.35293
G33: =L24 -> 0.06735 | H33: =($E$20+(NPV($G33,$I$14:$N$14)+$H$14)+((($N$14*(1+H$29)/($G33-H$29)))/(1+$G33)^6))/'PL-CF-BS'!$H$55 -> 385.17599 | I33: =($E$20+(NPV($G33,$I$14:$N$14)+$H$14)+((($N$14*(1+I$29)/($G33-I$29)))/(1+$G33)^6))/'PL-CF-BS'!$H$55 -> 392.315 | J33: =($E$20+(NPV($G33,$I$14:$N$14)+$H$14)+((($N$14*(1+J$29)/($G33-J$29)))/(1+$G33)^6))/'PL-CF-BS'!$H$55 -> 399.78338 | K33: =($E$20+(NPV($G33,$I$14:$N$14)+$H$14)+((($N$14*(1+K$29)/($G33-K$29)))/(1+$G33)^6))/'PL-CF-BS'!$H$55 -> 407.60445 | L33: =($E$20+(NPV($G33,$I$14:$N$14)+$H$14)+((($N$14*(1+L$29)/($G33-L$29)))/(1+$G33)^6))/'PL-CF-BS'!$H$55 -> 415.80381 | M33: =($E$20+(NPV($G33,$I$14:$N$14)+$H$14)+((($N$14*(1+M$29)/($G33-M$29)))/(1+$G33)^6))/'PL-CF-BS'!$H$55 -> 424.40959
G34: =G33+0.1% -> 0.06835 | H34: =($E$20+(NPV($G34,$I$14:$N$14)+$H$14)+((($N$14*(1+H$29)/($G34-H$29)))/(1+$G34)^6))/'PL-CF-BS'!$H$55 -> 376.7127 | I34: =($E$20+(NPV($G34,$I$14:$N$14)+$H$14)+((($N$14*(1+I$29)/($G34-I$29)))/(1+$G34)^6))/'PL-CF-BS'!$H$55 -> 383.51175 | J34: =($E$20+(NPV($G34,$I$14:$N$14)+$H$14)+((($N$14*(1+J$29)/($G34-J$29)))/(1+$G34)^6))/'PL-CF-BS'!$H$55 -> 390.61742 | K34: =($E$20+(NPV($G34,$I$14:$N$14)+$H$14)+((($N$14*(1+K$29)/($G34-K$29)))/(1+$G34)^6))/'PL-CF-BS'!$H$55 -> 398.05091 | L34: =($E$20+(NPV($G34,$I$14:$N$14)+$H$14)+((($N$14*(1+L$29)/($G34-L$29)))/(1+$G34)^6))/'PL-CF-BS'!$H$55 -> 405.83545 | M34: =($E$20+(NPV($G34,$I$14:$N$14)+$H$14)+((($N$14*(1+M$29)/($G34-M$29)))/(1+$G34)^6))/'PL-CF-BS'!$H$55 -> 413.99651
G35: =G34+0.1% -> 0.06935 | H35: =($E$20+(NPV($G35,$I$14:$N$14)+$H$14)+((($N$14*(1+H$29)/($G35-H$29)))/(1+$G35)^6))/'PL-CF-BS'!$H$55 -> 368.60781 | I35: =($E$20+(NPV($G35,$I$14:$N$14)+$H$14)+((($N$14*(1+I$29)/($G35-I$29)))/(1+$G35)^6))/'PL-CF-BS'!$H$55 -> 375.08929 | J35: =($E$20+(NPV($G35,$I$14:$N$14)+$H$14)+((($N$14*(1+J$29)/($G35-J$29)))/(1+$G35)^6))/'PL-CF-BS'!$H$55 -> 381.85661 | K35: =($E$20+(NPV($G35,$I$14:$N$14)+$H$14)+((($N$14*(1+K$29)/($G35-K$29)))/(1+$G35)^6))/'PL-CF-BS'!$H$55 -> 388.92911 | L35: =($E$20+(NPV($G35,$I$14:$N$14)+$H$14)+((($N$14*(1+L$29)/($G35-L$29)))/(1+$G35)^6))/'PL-CF-BS'!$H$55 -> 396.32791 | M35: =($E$20+(NPV($G35,$I$14:$N$14)+$H$14)+((($N$14*(1+M$29)/($G35-M$29)))/(1+$G35)^6))/'PL-CF-BS'!$H$55 -> 404.07612
G36: =G35+0.1% -> 0.07035 | H36: =($E$20+(NPV($G36,$I$14:$N$14)+$H$14)+((($N$14*(1+H$29)/($G36-H$29)))/(1+$G36)^6))/'PL-CF-BS'!$H$55 -> 360.83908 | I36: =($E$20+(NPV($G36,$I$14:$N$14)+$H$14)+((($N$14*(1+I$29)/($G36-I$29)))/(1+$G36)^6))/'PL-CF-BS'!$H$55 -> 367.02348 | J36: =($E$20+(NPV($G36,$I$14:$N$14)+$H$14)+((($N$14*(1+J$29)/($G36-J$29)))/(1+$G36)^6))/'PL-CF-BS'!$H$55 -> 373.47474 | K36: =($E$20+(NPV($G36,$I$14:$N$14)+$H$14)+((($N$14*(1+K$29)/($G36-K$29)))/(1+$G36)^6))/'PL-CF-BS'!$H$55 -> 380.21051 | L36: =($E$20+(NPV($G36,$I$14:$N$14)+$H$14)+((($N$14*(1+L$29)/($G36-L$29)))/(1+$G36)^6))/'PL-CF-BS'!$H$55 -> 387.25003 | M36: =($E$20+(NPV($G36,$I$14:$N$14)+$H$14)+((($N$14*(1+M$29)/($G36-M$29)))/(1+$G36)^6))/'PL-CF-BS'!$H$55 -> 394.61433
E37: % change from DCF TP upon WACC/perpetual growth change
E38: Perpetual Growth | H38: =H29 -> 0.022 | I38: =I29 -> 0.023 | J38: =J29 -> 0.024 | K38: =K29 -> 0.025 | L38: =L29 -> 0.026 | M38: =M29 -> 0.027
E39: WACC | G39: =G30 -> 0.06435 | H39: =H30/$K$33-1 -> 0.013164033 | I39: =I30/$K$33-1 -> 0.03356511 | J39: =J30/$K$33-1 -> 0.054977392 | K39: =K30/$K$33-1 -> 0.077477974 | L39: =L30/$K$33-1 -> 0.10115199 | M39: =M30/$K$33-1 -> 0.12609369
G40: =G31 -> 0.06535 | H40: =H31/$K$33-1 -> -0.010616829 | I40: =I31/$K$33-1 -> 0.0087518619 | J40: =J31/$K$33-1 -> 0.02905737 | K40: =K31/$K$33-1 -> 0.050369347 | L40: =L31/$K$33-1 -> 0.072764525 | M40: =M31/$K$33-1 -> 0.096327638
G41: =G32 -> 0.06635 | H41: =H32/$K$33-1 -> -0.033322825 | I41: =I32/$K$33-1 -> -0.01491414 | J41: =J32/$K$33-1 -> 0.004363903 | K41: =K32/$K$33-1 -> 0.024574379 | L41: =L32/$K$33-1 -> 0.045786614 | M41: =M32/$K$33-1 -> 0.06807698
G42: =G33 -> 0.06735 | H42: =H33/$K$33-1 -> -0.055025072 | I42: =I33/$K$33-1 -> -0.037510515 | J42: =J33/$K$33-1 -> -0.019187905 | K42: =K33/$K$33-1 -> 0 | L42: =L33/$K$33-1 -> 0.020115977 | M42: =M33/$K$33-1 -> 0.041229029
G43: =G34 -> 0.06835 | H43: =H34/$K$33-1 -> -0.07578855 | I43: =I34/$K$33-1 -> -0.059108032 | J43: =J34/$K$33-1 -> -0.041675292 | K43: =K34/$K$33-1 -> -0.023438274 | L43: =L34/$K$33-1 -> -0.0043400027 | M43: =M34/$K$33-1 -> 0.015682006
G44: =G35 -> 0.06935 | H44: =H35/$K$33-1 -> -0.095672753 | I44: =I35/$K$33-1 -> -0.079771357 | J44: =J35/$K$33-1 -> -0.063168686 | K44: =K35/$K$33-1 -> -0.045817305 | L44: =L35/$K$33-1 -> -0.027665399 | M44: =M35/$K$33-1 -> -0.0086562593
G45: =G36 -> 0.07035 | H45: =H36/$K$33-1 -> -0.11473225 | I45: =I36/$K$33-1 -> -0.099559689 | J45: =J36/$K$33-1 -> -0.083732436 | K45: =K36/$K$33-1 -> -0.067207178 | L45: =L36/$K$33-1 -> -0.0499367 | M45: =M36/$K$33-1 -> -0.031869429

Sheet Sheet1

Sheet PL-CF-BS
B2: Financial Statements | F2: =F125-F145-F159 -> 0 | G2: =G125-G145-G159 -> -0.1 | H2: =H125-H145-H159 -> 0 | I2: =I125-I145-I159 -> 0 | J2: =J125-J145-J159 -> 0 | K2: =K125-K145-K159 -> 0 | L2: =L125-L145-L159 -> 0 | M2: =M125-M145-M159 -> 0 | ... P2: =P125-P145-P159 -> 0
B3: ( in EUR mn)
F4: 2022 | G4: 2023 | H4: 2024 | I4: 2025 | J4: 2026E | K4: 2027E | L4: 2028E | M4: 2029E | N4: 2030E | O4: 2031E | P4: 2032E
B5: Income Statement
B6: Revenue | F6: =年度版model!E2 -> 38260.7 | G6: =年度版model!F2 -> 41182.6 | H6: =年度版model!G2 -> 43486.8 | I6: =年度版model!H2 -> 44052 | J6: =年度版model!I2 -> 46055.159 | K6: =年度版model!J2 -> 48398.286 | L6: =年度版model!K2 -> 50952.563 | M6: =年度版model!L2 -> 53661.992 | ... P6: =年度版model!O2 -> 62743.114
B7: yoy | F7: =F6/#REF!-1 -> #REF! | G7: =G6/F6-1 -> 0.076368179 | H7: =H6/G6-1 -> 0.055950814 | I7: =I6/H6-1 -> 0.012997047 | J7: =J6/I6-1 -> 0.045472611 | K7: =K6/J6-1 -> 0.05087653 | L7: =L6/K6-1 -> 0.052776175 | M7: =M6/L6-1 -> 0.05317553 | N7: =N6/M6-1 -> 0.05333654 | ... P7: =P6/O6-1 -> 0.053656185
B8: Cost of goods sold and service | F8: =-年度版model!E16 -> 10577.4 | G8: =-年度版model!F16 -> 10767 | H8: =-年度版model!G16 -> 11227 | I8: =-年度版model!H16 -> 11313.4 | J8: =-年度版model!I16 -> 11781.795 | K8: =-年度版model!J16 -> 12236.017 | L8: =-年度版model!K16 -> 12728.929 | M8: =-年度版model!L16 -> 13244.811 | ... P8: =-年度版model!O16 -> 14921.518
B9: Gross profit | F9: =F6-F8 -> 27683.3 | G9: =G6-G8 -> 30415.6 | H9: =H6-H8 -> 32259.8 | I9: =I6-I8 -> 32738.6 | J9: =J6-J8 -> 34273.365 | K9: =K6-K8 -> 36162.269 | L9: =L6-L8 -> 38223.633 | M9: =M6-M8 -> 40417.181 | ... P9: =P6-P8 -> 47821.596
C10: YoY | F10: =F9/#REF!-1 -> #REF! | G10: =G9/F9-1 -> 0.098698493 | H10: =H9/G9-1 -> 0.060633359 | I10: =I9/H9-1 -> 0.014842002 | J10: =J9/I9-1 -> 0.046879365 | K10: =K9/J9-1 -> 0.055112906 | L10: =L9/K9-1 -> 0.057003169 | M10: =M9/L9-1 -> 0.057387217 | N10: =N9/M9-1 -> 0.057532092 | ... P10: =P9/O9-1 -> 0.057819842
C11: Gross margin | F11: =F9/F6 -> 0.723544 | G11: =G9/G6 -> 0.73855463 | H11: =H9/H6 -> 0.7418297 | I11: =I9/I6 -> 0.74318079 | J11: =J9/J6 -> 0.74418079 | K11: =K9/K6 -> 0.74718079 | L11: =L9/L6 -> 0.75018079 | M11: =M9/M6 -> 0.75318079 | ... P11: =P9/P6 -> 0.76218079
B12: Research and innovation expenses | F12: =-年度版model!E23 -> 1138.6 | G12: =-年度版model!F23 -> 1288.9 | H12: =-年度版model!G23 -> 1354.7 | I12: =-年度版model!H23 -> 1380.6 | J12: =-年度版model!I23 -> 1427.7099 | K12: =-年度版model!J23 -> 1500.3469 | L12: =-年度版model!K23 -> 1579.5294 | M12: =-年度版model!L23 -> 1663.5218 | ... P12: =-年度版model!O23 -> 1945.0365
B13: R&I rate | F13: =F12/F6 -> 0.029758996 | G13: =G12/G6 -> 0.031297198 | H13: =H12/H6 -> 0.031151982 | I13: =I12/I6 -> 0.031340234 | J13: =J12/J6 -> 0.031 | K13: =K12/K6 -> 0.031 | L13: =L12/L6 -> 0.031 | M13: =M12/M6 -> 0.031 | ... P13: =P12/P6 -> 0.031
B14: Advertising and promotion expenses | F14: =-年度版model!E27 -> 12059 | G14: =-年度版model!F27 -> 13356.6 | H14: =-年度版model!G27 -> 14008.9 | I14: =-年度版model!H27 -> 14177.8 | J14: =-年度版model!I27 -> 14645.541 | K14: =-年度版model!J27 -> 15342.257 | L14: =-年度版model!K27 -> 16151.962 | M14: =-年度版model!L27 -> 17010.851 | ... P14: =-年度版model!O27 -> 19889.567
B15: Advertising rate | F15: =F14/F6 -> 0.31517981 | G15: =G14/G6 -> 0.32432629 | H15: =H14/H6 -> 0.32214143 | I15: =I14/I6 -> 0.32184237 | J15: =J14/J6 -> 0.318 | K15: =K14/K6 -> 0.317 | L15: =L14/L6 -> 0.317 | M15: =M14/M6 -> 0.317 | ... P15: =P14/P6 -> 0.317
B16: Selling, general and admnistrative expenses | F16: =-年度版model!E31 -> 7028.8 | G16: =-年度版model!F31 -> 7626.7 | H16: =-年度版model!G31 -> 8208.7 | I16: =-年度版model!H31 -> 8288.3 | J16: =-年度版model!I31 -> 8704.4251 | K16: =-年度版model!J31 -> 9098.8778 | L16: =-年度版model!K31 -> 9528.1292 | M16: =-年度版model!L31 -> 9981.1305 | ... P16: =-年度版model!O31 -> 11481.99
B17: Administrating rate | F17: =F16/F$6 -> 0.18370809 | G17: =G16/G$6 -> 0.18519229 | H17: =H16/H$6 -> 0.18876303 | I17: =I16/I$6 -> 0.1881481 | J17: =J16/J$6 -> 0.189 | K17: =K16/K$6 -> 0.188 | L17: =L16/L$6 -> 0.187 | M17: =M16/M$6 -> 0.186 | ... P17: =P16/P$6 -> 0.183
B18: Other Operating Income and Expense | F18: =-年度版model!E52 -> 241.5 | G18: =-年度版model!F52 -> 449.9 | H18: =-年度版model!G52 -> 437.7 | I18: =-年度版model!H52 -> 505.4 | J18: =-年度版model!I52 -> 471.55 | K18: =-年度版model!J52 -> 488.475 | L18: =-年度版model!K52 -> 480.0125 | M18: =-年度版model!L52 -> 484.24375 | ... P18: =-年度版model!O52 -> 482.65703
B19: Operating expenses | F19: =F12+F14+F16+F18 -> 20467.9 | G19: =G12+G14+G16+G18 -> 22722.1 | H19: =H12+H14+H16+H18 -> 24010 | I19: =I12+I14+I16+I18 -> 24352.1 | J19: =J12+J14+J16+J18 -> 25249.226 | K19: =K12+K14+K16+K18 -> 26429.956 | L19: =L12+L14+L16+L18 -> 27739.633 | M19: =M12+M14+M16+M18 -> 29139.748 | ... P19: =P12+P14+P16+P18 -> 33799.251
C20: YoY | G20: =G19/F19-1 -> 0.11013343 | H20: =H19/G19-1 -> 0.0566805 | I20: =I19/H19-1 -> 0.01424823 | J20: =J19/I19-1 -> 0.036839771 | K20: =K19/J19-1 -> 0.046763041 | L20: =L19/K19-1 -> 0.049552753 | M20: =M19/L19-1 -> 0.050473416 | N20: =N19/M19-1 -> 0.050437831 | ... P20: =P19/O19-1 -> 0.050882852
C21: % of revenue | F21: =F19/F6 -> 0.53495885 | G21: =G19/G6 -> 0.5517403 | H21: =H19/H6 -> 0.55212156 | I21: =I19/I6 -> 0.5528035 | J21: =J19/J6 -> 0.54823881 | K21: =K19/K6 -> 0.54609282 | L21: =L19/L6 -> 0.54442077 | M21: =M19/M6 -> 0.54302396 | ... P21: =P19/P6 -> 0.53869259
B22: Operating profit | F22: =年度版model!E54 -> 7215.3 | G22: =年度版model!F54 -> 7693.4 | H22: =年度版model!G54 -> 8249.8 | I22: =年度版model!H54 -> 8386.5 | J22: =年度版model!I54 -> 9024.139 | K22: =年度版model!J54 -> 9732.3131 | L22: =年度版model!K54 -> 10484 | M22: =年度版model!L54 -> 11277.434 | ... P22: =年度版model!O54 -> 14022.345
C23: YoY | G23: =G22/F22-1 -> 0.066261971 | H23: =H22/G22-1 -> 0.07232173 | I23: =I22/H22-1 -> 0.016570099 | J23: =J22/I22-1 -> 0.076031597 | K23: =K22/J22-1 -> 0.078475535 | L23: =L22/K22-1 -> 0.077236197 | M23: =M22/L22-1 -> 0.075680455 | N23: =N22/M22-1 -> 0.075862946 | ... P23: =P22/O22-1 -> 0.07492317
C24: Operating margin | F24: =F22/F6 -> 0.18858254 | G24: =G22/G6 -> 0.18681191 | H24: =H22/H$6 -> 0.18970814 | I24: =I22/I$6 -> 0.19037728 | J24: =J22/J$6 -> 0.19594198 | K24: =K22/K$6 -> 0.20108797 | L24: =L22/L$6 -> 0.20576001 | M24: =M22/M$6 -> 0.21015682 | N24: =N22/N$6 -> 0.21465119 | O24: =O22/O$6 -> 0.21906656 | P24: =P22/P$6 -> 0.2234882
B25: DD&A | F25: =F73 -> 1536.1 | G25: =G73 -> 1715 | H25: =H73 -> 1855.3 | I25: =AVERAGE(F25:H25)*1.05 -> 1787.24 | J25: =AVERAGE(G25:I25)*1.05 -> 1875.139 | K25: =AVERAGE(H25:J25)*1.05 -> 1931.1877 | L25: =AVERAGE(I25:K25)*1.1 -> 2050.9744 | M25: =AVERAGE(J25:L25)*1.1 -> 2147.6771 | N25: =AVERAGE(K25:M25)*1.1 -> 2247.6077 | O25: =AVERAGE(L25:N25)*1.1 -> 2363.6284 | P25: =AVERAGE(M25:O25)*1.1 -> 2478.2681
B26: EBITDA | F26: =F22+F25 -> 8751.4 | G26: =G22+G25 -> 9408.4 | H26: =H22+H25 -> 10105.1 | I26: =I22+I25 -> 10173.74 | J26: =J22+J25 -> 10899.278 | K26: =K22+K25 -> 11663.501 | L26: =L22+L25 -> 12534.974 | M26: =M22+M25 -> 13425.111 | ... P26: =P22+P25 -> 16500.614
C27: YoY | G27: =G26/F26-1 -> 0.075073702 | H27: =H26/G26-1 -> 0.074050848 | I27: =I26/H26-1 -> 0.0067926097 | J27: =J26/I26-1 -> 0.071314776 | K27: =K26/J26-1 -> 0.070116827 | L27: =L26/K26-1 -> 0.074718016 | M27: =M26/L26-1 -> 0.071012233 | N27: =N26/M26-1 -> 0.07117036 | ... P27: =P26/O26-1 -> 0.07087019
C28: EBITDA margin | F28: =F26/F$6 -> 0.22873079 | G28: =G26/G$6 -> 0.22845571 | H28: =H26/H$6 -> 0.23237166 | I28: =I26/I$6 -> 0.23094842 | J28: =J26/J$6 -> 0.23665705 | K28: =K26/K$6 -> 0.24098995 | L28: =L26/L$6 -> 0.24601264 | M28: =M26/M$6 -> 0.25017914 | ... P28: =P26/P$6 -> 0.26298684
C29: Finance cost, net | F29: =年度版model!E57 -> -0.6 | G29: =年度版model!F57 -> -64.6 | H29: =年度版model!G57 -> -224.7 | I29: =年度版model!H57 -> -198.1 | J29: =年度版model!I57 -> -136 | K29: =年度版model!J57 -> -59.04 | L29: =年度版model!K57 -> -89.04 | M29: =年度版model!L57 -> -89.04 | ... P29: =年度版model!O57 -> 714.34208
B30: + Interest Expense | F30: =年度版model!E58 -> -70.4 | G30: =年度版model!F58 -> -226.7 | H30: =年度版model!G58 -> -373.4 | I30: =年度版model!H58 -> -365.8 | J30: =年度版model!I58 -> -366 | K30: =年度版model!J58 -> -259.04 | L30: =年度版model!K58 -> -259.04 | M30: =年度版model!L58 -> -259.04 | ... P30: =年度版model!O58 -> -259.04
B31: - Interest Income | F31: =年度版model!E59 -> 69.8 | G31: =年度版model!F59 -> 162.1 | H31: =年度版model!G59 -> 148.7 | I31: =年度版model!H59 -> 167.7 | J31: =年度版model!I59 -> 230 | K31: =年度版model!J59 -> 200 | L31: =年度版model!K59 -> 170 | M31: =年度版model!L59 -> 170 | ... P31: =年度版model!O59 -> 170
B32: + Other Investment (Inc) Loss
B33: + Foreign Exch (Gain) Loss
B34: + (Income) Loss from Affiliates
B35: + Other Non-Op (Income) Loss
B36: Profit before taxation | F36: =年度版model!E64 -> 7610.6 | G36: =年度版model!F64 -> 8000.9 | H36: =年度版model!G64 -> 8432.9 | I36: =年度版model!H64 -> 8502.3 | J36: =年度版model!I64 -> 9207.3175 | K36: =年度版model!J64 -> 10003.167 | L36: =年度版model!K64 -> 10735.891 | M36: =年度版model!L64 -> 11540.692 | ... P36: =年度版model!O64 -> 15125.177
C37: YoY | G37: =G36/F36-1 -> 0.051283736 | H37: =H36/G36-1 -> 0.053993926 | I37: =I36/H36-1 -> 0.0082296719 | J37: =J36/I36-1 -> 0.082920797 | K37: =K36/J36-1 -> 0.086436629 | L37: =L36/K36-1 -> 0.073249169 | M37: =M36/L36-1 -> 0.074963675 | N37: =N36/M36-1 -> 0.075146991 | ... P37: =P36/O36-1 -> 0.13450155
C38: EBT margin | F38: =F36/F6 -> 0.19891429 | G38: =G36/G6 -> 0.19427865 | H38: =H36/H6 -> 0.19391861 | I38: =I36/I$6 -> 0.19300599 | J38: =J36/J$6 -> 0.19991935 | K38: =K36/K$6 -> 0.20668432 | L38: =L36/L$6 -> 0.21070364 | M38: =M36/M$6 -> 0.21506269 | N38: =N36/N$6 -> 0.21951579 | O38: =O36/O$6 -> 0.22388667 | P38: =P36/P$6 -> 0.24106514
B39: Abnormal (Losses) Gains
B40: Profit before taxation | F40: =F36-F39 -> 7610.6 | G40: =G36-G39 -> 8000.9 | H40: =H36-H39 -> 8432.9 | I40: =I36-I39 -> 8502.3 | J40: =J36-J39 -> 9207.3175 | K40: =K36-K39 -> 10003.167 | L40: =L36-L39 -> 10735.891 | M40: =M36-M39 -> 11540.692 | ... P40: =P36-P39 -> 15125.177
B41: Taxation | F41: =-年度版model!E67 -> 1899.4 | G41: =-年度版model!F67 -> 1810.6 | H41: =-年度版model!G67 -> 2015.1 | I41: =-年度版model!H67 -> 2363.1 | J41: =-年度版model!I67 -> 2409.2187 | K41: =-年度版model!J67 -> 2609.067 | L41: =-年度版model!K67 -> 2791.8224 | M41: =-年度版model!L67 -> 3001.1077 | ... P41: =-年度版model!O67 -> 3933.2376
C42: Effective tax rate | F42: =F41/F40 -> 0.24957296 | G42: =G41/G40 -> 0.22629954 | H42: =H41/H40 -> 0.23895694 | I42: =I41/I40 -> 0.27793656 | J42: =J41/J40 -> 0.26166348 | K42: =K41/K40 -> 0.2608241 | L42: =L41/L40 -> 0.26004572 | M42: =M41/M40 -> 0.26004572 | ... P42: =P41/P40 -> 0.26004572
B43: Share in profit/(loss) of associates | F43: =年度版model!E70 -> 1.4 | G43: =年度版model!F70 -> 0.2 | H43: =年度版model!G70 -> -1.3 | I43: =年度版model!H70 -> -5.5 | J43: =年度版model!I70 -> -5.5 | K43: =年度版model!J70 -> -5.5 | L43: =年度版model!K70 -> -5.5 | M43: =年度版model!L70 -> -5.5 | ... P43: =年度版model!O70 -> -5.5
B45: Net Profit for the year | F45: =F49-F47 -> 5712.6 | G45: =G49-G47 -> 6190.5 | H45: =H49-H47 -> 6416.5 | I45: =I49-I47 -> 6133.7 | J45: =J49-J47 -> 6792.5987 | K45: =K49-K47 -> 7388.5999 | L45: =L49-L47 -> 7938.5682 | M45: =M49-M47 -> 8534.0848 | ... P45: =P49-P47 -> 11186.44
C46: Loss from discontinued operations
C47: Minority interest | F47: =年度版model!E73 -> -6 | G47: =年度版model!F73 -> -6.5 | H47: =年度版model!G73 -> -7.8 | I47: =年度版model!H73 -> -6.5 | J47: =年度版model!I73 -> -6.5 | K47: =年度版model!J73 -> -6.5 | L47: =年度版model!K73 -> -6.5 | M47: =年度版model!L73 -> -6.5 | ... P47: =年度版model!O73 -> -6.5
C48: % of profit for the year | F48: =F47/F45 -> -0.0010503098 | G48: =G47/G45 -> -0.001049996 | H48: =G48 -> -0.001049996 | I48: =H48 -> -0.001049996 | J48: =I48 -> -0.001049996 | K48: =J48 -> -0.001049996 | L48: =K48 -> -0.001049996 | M48: =L48 -> -0.001049996 | N48: =M48 -> -0.001049996 | O48: =N48 -> -0.001049996 | P48: =O48 -> -0.001049996
B49: Net profit attributable to parent company | F49: =年度版model!E72 -> 5706.6 | G49: =年度版model!F72 -> 6184 | H49: =年度版model!G72 -> 6408.7 | I49: =年度版model!H72 -> 6127.2 | J49: =年度版model!I72 -> 6786.0987 | K49: =年度版model!J72 -> 7382.0999 | L49: =年度版model!K72 -> 7932.0682 | M49: =年度版model!L72 -> 8527.5848 | ... P49: =年度版model!O72 -> 11179.94
C50: YoY | G50: =G49/F49-1 -> 0.083657519 | H50: =H49/G49-1 -> 0.036335705 | I50: =I49/H49-1 -> -0.043924665 | J50: =J49/I49-1 -> 0.10753668 | K50: =K49/J49-1 -> 0.08782678 | L50: =L49/K49-1 -> 0.074500252 | M50: =M49/L49-1 -> 0.075077083 | N50: =N49/M49-1 -> 0.075252738 | ... P50: =P49/O49-1 -> 0.13466536
C51: Net margin | F51: =F49/F$6 -> 0.14915043 | G51: =G49/G$6 -> 0.1501605 | H51: =H49/H$6 -> 0.14737116 | I51: =I49/I$6 -> 0.13909017 | J51: =J49/J$6 -> 0.1473472 | K51: =K49/K$6 -> 0.15252813 | L51: =L49/L$6 -> 0.15567555 | M51: =M49/M$6 -> 0.15891294 | ... P51: =P49/P$6 -> 0.17818592
B52: Dividends | F52: =F45*F53 -> 3214.4956 | G52: =G45*G53 -> 3537.7159 | H52: =H45*H53 -> 3744.7363 | I52: =I45*I53 -> 3846.1224 | J52: =J45*J53 -> 3942.6012 | K52: =K45*K53 -> 4039.2945 | L52: =L45*L53 -> 4149.7658 | M52: =M45*M53 -> 4345.024 | ... P52: =P45*P53 -> 5429.3881
C53: Payout ratio | F53: =年度版model!E95 -> 0.56270273 | G53: =年度版model!F95 -> 0.57147499 | H53: =年度版model!G95 -> 0.58361043 | I53: =年度版model!H95 -> 0.62704768 | J53: =年度版model!I95 -> 0.58042605 | K53: =年度版model!J95 -> 0.54669281 | L53: =年度版model!K95 -> 0.52273479 | M53: =年度版model!L95 -> 0.50913767 | ... P53: =年度版model!O95 -> 0.48535443
B55: Basic shares outstanding | F55: =年度版model!E88 -> 535.18656 | G55: =年度版model!F88 -> 535.45475 | H55: =年度版model!G88 -> 534.31202 | I55: =年度版model!H88 -> 533.61758 | J55: =年度版model!I88 -> 532.27412 | K55: =年度版model!J88 -> 531.01855 | L55: =年度版model!K88 -> 529.84512 | M55: =年度版model!L88 -> 528.74846 | ... P55: =年度版model!O88 -> 525.87047
B56: Fully diluted shares outstanding | F56: =年度版model!E91 -> 537.65755 | G56: =年度版model!F91 -> 537.02104 | H56: =年度版model!G91 -> 536.07843 | I56: =年度版model!H91 -> 535.38399 | J56: =年度版model!I91 -> 534.54053 | K56: =年度版model!J91 -> 533.78496 | L56: =年度版model!K91 -> 533.11153 | M56: =年度版model!L91 -> 532.51487 | ... P56: =年度版model!O91 -> 531.13688
B58: Basic EPS (EUR) | F58: =F49/F55 -> 10.662824 | G58: =G49/G55 -> 11.549062 | H58: =H49/H55 -> 11.994302 | I58: =I49/I55 -> 11.48238 | J58: =J49/J55 -> 12.749256 | K58: =K49/K55 -> 13.901774 | L58: =L49/L55 -> 14.970541 | M58: =M49/M55 -> 16.127867 | ... P58: =P49/P55 -> 21.259873
C60: YoY | G60: =G58/F58-1 -> 0.083114758 | H60: =H58/G58-1 -> 0.038552108 | I60: =I58/H58-1 -> -0.042680438 | J60: =J58/I58-1 -> 0.1103321 | K60: =K58/J58-1 -> 0.090398895 | L60: =L58/K58-1 -> 0.076879908 | M60: =M58/L58-1 -> 0.077306869 | N60: =N58/M58-1 -> 0.077341039 | ... P60: =P58/O58-1 -> 0.13659693
B62: Diluted EPS (EUR) | F62: =F49/F56 -> 10.613819 | G62: =G49/G56 -> 11.515378 | H62: =H49/H56 -> 11.954781 | I62: =I49/I56 -> 11.444496 | J62: =J49/J56 -> 12.6952 | K62: =K49/K56 -> 13.829726 | L62: =L49/L56 -> 14.878816 | M62: =M49/M56 -> 16.013797 | ... P62: =P49/P56 -> 21.049074
C64: YoY | G64: =G62/F62-1 -> 0.084941934 | H64: =H62/G62-1 -> 0.038157935 | I64: =I62/H62-1 -> -0.042684543 | J64: =J62/I62-1 -> 0.10928427 | K64: =K62/J62-1 -> 0.08936659 | L64: =L62/K62-1 -> 0.075857564 | M64: =M62/L62-1 -> 0.076281665 | N64: =N62/M62-1 -> 0.076313696 | ... P64: =P62/O62-1 -> 0.13550963
B66: DPS (EUR) | F66: =F52/F55 -> 6.0063085 | G66: =G52/G55 -> 6.6069373 | H66: =H52/H55 -> 7.0085197 | I66: =I52/I55 -> 7.2076381 | J66: =J52/J55 -> 7.407088 | K66: =K52/K55 -> 7.6066919 | L66: =L52/L55 -> 7.8320355 | M66: =M52/M55 -> 8.2175635 | ... P66: =P52/P55 -> 10.324573
C68: YoY | G68: =G66/F66-1 -> 0.099999654 | H68: =H66/G66-1 -> 0.060781932 | I68: =I66/H66-1 -> 0.028410908 | J68: =J66/I66-1 -> 0.027672026 | K68: =K66/J66-1 -> 0.026947681 | L68: =L66/K66-1 -> 0.029624391 | M68: =M66/L66-1 -> 0.049224498 | N68: =N66/M66-1 -> 0.079944941 | ... P68: =P66/O66-1 -> 0.078266333
B70: Cashflow Statement
B71: Operating cashflow
B72: Net profit attributable to parent company | F72: =年度版model!E176 -> 5706.6 | G72: =年度版model!F176 -> 6184 | H72: =年度版model!G176 -> 6408.7 | I72: =年度版model!H176 -> 6127.2 | J72: =年度版model!I176 -> 6786.0987 | K72: =年度版model!J176 -> 7382.0999 | L72: =年度版model!K176 -> 7932.0682 | M72: =年度版model!L176 -> 8527.5848 | ... P72: =年度版model!O176 -> 11179.94
B73: D&A | F73: =年度版model!E178 -> 1536.1 | G73: =年度版model!F178 -> 1715 | H73: =年度版model!G178 -> 1855.3 | I73: =年度版model!H178 -> 1817.4 | J73: =年度版model!I178 -> 1900.0419 | K73: =年度版model!J178 -> 1996.7095 | L73: =年度版model!K178 -> 2102.0882 | M73: =年度版model!L178 -> 2213.8678 | ... P73: =年度版model!O178 -> 2588.5167
B74: Change in working capital | F74: =年度版model!E188 -> -1011.3 | G74: =年度版model!F188 -> -394.9 | H74: =年度版model!G188 -> -226.6 | I74: =年度版model!H188 -> 327.4 | J74: =年度版model!I188 -> -198.85467 | K74: =年度版model!J188 -> -314.99508 | L74: =年度版model!K188 -> -211.60712 | M74: =年度版model!L188 -> -117.9108 | ... P74: =年度版model!O188 -> -241.04194
B75: Others | F75: =年度版model!E177+SUM(年度版model!E181:E186)+年度版model!E189 -> 46.9 | G75: =年度版model!F177+SUM(年度版model!F181:F186)+年度版model!F189 -> 100.5 | H75: =年度版model!G177+SUM(年度版model!G181:G186)+年度版model!G189 -> 248.6 | I75: =年度版model!H177+SUM(年度版model!H181:H186)+年度版model!H189 -> 384.9 | J75: =年度版model!I177+SUM(年度版model!I181:I186)+年度版model!I189 -> 7.8 | K75: =年度版model!J177+SUM(年度版model!J181:J186)+年度版model!J189 -> 7.8 | L75: =年度版model!K177+SUM(年度版model!K181:K186)+年度版model!K189 -> 7.8 | M75: =年度版model!L177+SUM(年度版model!L181:L186)+年度版model!L189 -> 7.8 | ... P75: =年度版model!O177+SUM(年度版model!O181:O186)+年度版model!O189 -> 7.8
F76: =SUM(F72:F75) -> 6278.3 | G76: =SUM(G72:G75) -> 7604.6 | H76: =SUM(H72:H73,H74:H75) -> 8286 | I76: =SUM(I72:I73,I74:I75) -> 8656.9 | J76: =SUM(J72:J73,J74:J75) -> 8495.086 | K76: =SUM(K72:K73,K74:K75) -> 9071.6143 | L76: =SUM(L72:L73,L74:L75) -> 9830.3493 | M76: =SUM(M72:M73,M74:M75) -> 10631.342 | N76: =SUM(N72:N73,N74:N75) -> 11255.616 | O76: =SUM(O72:O73,O74:O75) -> 12055.432 | P76: =SUM(P72:P73,P74:P75) -> 13535.214
B78: Investment cashflow
B79: Purchases of PP&E and intangible assets | F79: =年度版model!E193 -> -1343.2 | G79: =年度版model!F193 -> -1488.7 | H79: =年度版model!G193 -> -1641.7 | I79: =年度版model!H193 -> -1495.3 | J79: =年度版model!I193 -> -1645.9071 | K79: =年度版model!J193 -> -1737.2826 | L79: =年度版model!K193 -> -1825.7441 | M79: =年度版model!L193 -> -1897.0787 | ... P79: =年度版model!O193 -> -2236.5603
B80: Disposals of PP&E and intangible assets | F80: =年度版model!E195 -> 9.2 | G80: =年度版model!F195 -> 12.8 | H80: =年度版model!G195 -> 13.6 | I80: =年度版model!H195 -> 5.7 | J80: =年度版model!I195 -> 10.7 | K80: =年度版model!J195 -> 10 | L80: =年度版model!K195 -> 8.8 | M80: =年度版model!L195 -> 9.8333333 | ... P80: =年度版model!O195 -> 9.5901235
B81: Changes in other financial assets | F81: =年度版model!E196 -> -142.8 | G81: =年度版model!F196 -> -170.7 | H81: =年度版model!G196 -> -1926.95 | I81: =年度版model!H196 -> 2509 | J81: =年度版model!I196 -> 137.11667 | K81: =年度版model!J196 -> 239.72222 | L81: =年度版model!K196 -> 961.9463 | M81: =年度版model!L196 -> 446.26173 | ... P81: =年度版model!O196 -> 549.35928
B82: Effect of changes in the scope of consolidation | F82: =年度版model!E197 -> -746.9 | G82: =年度版model!F197 -> -2497.2 | H82: =年度版model!G197 -> -148.85 | I82: =年度版model!H197 -> -2426.6 | J82: =年度版model!I197 -> -1690.8833 | K82: =年度版model!J197 -> -1422.1111 | L82: =年度版model!K197 -> -1846.5315 | M82: =年度版model!L197 -> -1653.1753 | ... P82: =年度版model!O197 -> -1669.073
B83: Net cash from discontinued operations | F83: =年度版model!E198 -> 0 | G83: =年度版model!F198 -> 0 | H83: =年度版model!G198 -> 0 | I83: =年度版model!H198 -> 0 | J83: =年度版model!I198 -> 0 | K83: =年度版model!J198 -> 0 | L83: =年度版model!K198 -> 0 | M83: =年度版model!L198 -> 0 | ... P83: =年度版model!O198 -> 0
F84: =SUM(F79:F83) -> -2223.7 | G84: =SUM(G79:G83) -> -4143.8 | H84: =SUM(H79:H83) -> -3703.9 | I84: =SUM(I79:I83) -> -1407.2 | J84: =SUM(J79:J83) -> -3188.9738 | K84: =SUM(K79:K83) -> -2909.6715 | L84: =SUM(L79:L83) -> -2701.5293 | M84: =SUM(M79:M83) -> -3094.1589 | ... P84: =SUM(P79:P83) -> -3346.6839
B86: Cashflow before financing | F86: =F76+F84 -> 4054.6 | G86: =G76+G84 -> 3460.8 | H86: =H76+H84 -> 4582.1 | I86: =I76+I84 -> 7249.7 | J86: =J76+J84 -> 5306.1122 | K86: =K76+K84 -> 6161.9428 | L86: =L76+L84 -> 7128.8199 | M86: =M76+M84 -> 7537.1829 | ... P86: =P76+P84 -> 10188.531
B88: Financing cashflow
B89: Dividends paid | F89: =年度版model!E202 -> -2689.9 | G89: =年度版model!F202 -> -3425.6 | H89: =年度版model!G202 -> -3614.9 | I89: =年度版model!H202 -> -3917 | J89: =年度版model!I202 -> -3938.8285 | K89: =年度版model!J202 -> -4035.741 | L89: =年度版model!K202 -> -4146.368 | M89: =年度版model!L202 -> -4341.7146 | ... P89: =年度版model!O202 -> -5426.2333
B90: Capital increase of the parent company | F90: =年度版model!E203 -> 103.2 | G90: =年度版model!F203 -> 1.5 | H90: =年度版model!G203 -> 69.9 | I90: =年度版model!H203 -> 65.6 | J90: =年度版model!I203 -> 45.666667 | K90: =年度版model!J203 -> 60.388889 | L90: =年度版model!K203 -> 57.218519 | M90: =年度版model!L203 -> 54.424691 | ... P90: =年度版model!O203 -> 56.032602
B91: Disposal (acquisition) of Treasury shares | F91: =年度版model!E204 -> -502.3 | G91: =年度版model!F204 -> -503.3 | H91: =年度版model!G204 -> -497.5 | I91: =年度版model!H204 -> -501.5 | J91: =年度版model!I204 -> -500 | K91: =年度版model!J204 -> -500 | L91: =年度版model!K204 -> -500 | M91: =年度版model!L204 -> -500 | ... P91: =年度版model!O204 -> -500
B92: Purchase of non-controlling interests | F92: =年度版model!E205 -> 0 | G92: =年度版model!F205 -> 0 | H92: =年度版model!G205 -> -13.9 | I92: =年度版model!H205 -> -16.3 | J92: =年度版model!I205 -> -10.066667 | K92: =年度版model!J205 -> -13.422222 | L92: =年度版model!K205 -> -13.262963 | M92: =年度版model!L205 -> -12.250617 | ... P92: =年度版model!O205 -> -12.686648
B93: Issuance (repayment) of short term loans | F93: =年度版model!E206 -> -3563.8 | G93: =年度版model!F206 -> -823.7 | H93: =年度版model!G206 -> -1775.9 | I93: =年度版model!H206 -> -609.7 | J93: =年度版model!I206 -> -1069.7667 | K93: =年度版model!J206 -> -1151.7889 | L93: =年度版model!K206 -> -943.75185 | M93: =年度版model!L206 -> -1055.1025 | ... P93: =年度版model!O206 -> -1040.5577
B94: Issuance of long term borrowings | F94: =年度版model!E207 -> 3019.9 | G94: =年度版model!F207 -> 3567.1 | H94: =年度版model!G207 -> 1529.4 | I94: =年度版model!H207 -> 4057.3 | J94: =年度版model!I207 -> 3051.2667 | K94: =年度版model!J207 -> 2879.3222 | L94: =年度版model!K207 -> 3329.2963 | M94: =年度版model!L207 -> 3086.6284 | ... P94: =年度版model!O207 -> 3118.8303
B95: Repayment of long term borrowings | F95: =年度版model!E208 -> 0 | G95: =年度版model!F208 -> 0 | H95: =年度版model!G208 -> -7.9 | I95: =年度版model!H208 -> -22.6 | J95: =年度版model!I208 -> -10.166667 | K95: =年度版model!J208 -> -13.555556 | L95: =年度版model!K208 -> -15.440741 | M95: =年度版model!L208 -> -13.054321 | ... P95: =年度版model!O208 -> -13.747279
B96: Repayment of lease debt | F96: =年度版model!E209 -> -446.9 | G96: =年度版model!F209 -> -430.6 | H96: =年度版model!G209 -> -474.25 | I96: =年度版model!H209 -> -453.6 | J96: =年度版model!I209 -> -452.81667 | K96: =年度版model!J209 -> -460.22222 | L96: =年度版model!K209 -> -455.5463 | M96: =年度版model!L209 -> -456.19506 | ... P96: =年度版model!O209 -> -456.62348
B97: Net cash from discontinued operations | F97: =年度版model!E210 -> 0 | G97: =年度版model!F210 -> 0 | H97: =年度版model!G210 -> 0 | I97: =年度版model!H210 -> 0 | J97: =年度版model!I210 -> 0 | K97: =年度版model!J210 -> 0 | L97: =年度版model!K210 -> 0 | M97: =年度版model!L210 -> 0 | ... P97: =年度版model!O210 -> 0
F98: =SUM(F89:F97) -> -4079.8 | G98: =SUM(G89:G97) -> -1614.6 | H98: =SUM(H89:H97) -> -4785.05 | I98: =SUM(I89:I97) -> -1397.8 | J98: =SUM(J89:J97) -> -2884.7118 | K98: =SUM(K89:K97) -> -3235.0188 | L98: =SUM(L89:L97) -> -2687.8551 | M98: =SUM(M89:M97) -> -3237.264 | ... P98: =SUM(P89:P97) -> -4274.9855
B99: Net effect of exchange rates and fair value | F99: =年度版model!E213 -> -70.7 | G99: =年度版model!F213 -> -175.9 | H99: =年度版model!G213 -> -32.75 | I99: =年度版model!H213 -> -39.2 | J99: =年度版model!I213 -> 0 | K99: =年度版model!J213 -> 0 | L99: =年度版model!K213 -> 0 | M99: =年度版model!L213 -> 0 | ... P99: =年度版model!O213 -> 0
B100: Increase in cash | F100: =F86+F98+F99 -> -95.9 | G100: =G86+G98+G99 -> 1670.3 | H100: =H86+H98+H99 -> -235.7 | I100: =I86+I98+I99 -> 5812.7 | J100: =J86+J98+J99 -> 2421.4004 | K100: =K86+K98+K99 -> 2926.9241 | L100: =L86+L98+L99 -> 4440.9649 | M100: =M86+M98+M99 -> 4299.9189 | ... P100: =P86+P98+P99 -> 5913.545
B101: Cash BB | F101: =年度版model!E215 -> 2713.6 | G101: =年度版model!F215 -> 2617.7 | H101: =年度版model!G215 -> 4288 | I101: =年度版model!H215 -> 4052.3 | J101: =年度版model!I215 -> 9865 | K101: =年度版model!J215 -> 12286.4 | L101: =年度版model!K215 -> 15213.324 | M101: =年度版model!L215 -> 19654.289 | ... P101: =年度版model!O215 -> 33616.945
B102: Net effect of discontinued operations | F102: =年度版model!E216 -> 0 | G102: =年度版model!F216 -> 0 | H102: =年度版model!G216 -> 0 | I102: =年度版model!H216 -> 0 | J102: =年度版model!I216 -> 0 | K102: =年度版model!J216 -> 0 | L102: =年度版model!K216 -> 0 | M102: =年度版model!L216 -> 0 | ... P102: =年度版model!O216 -> 0
B103: Cash EB | F103: =SUM(F100:F102) -> 2617.7 | G103: =SUM(G100:G102) -> 4288 | H103: =SUM(H100:H102) -> 4052.3 | I103: =SUM(I100:I102) -> 9865 | J103: =SUM(J100:J102) -> 12286.4 | K103: =SUM(K100:K102) -> 15213.324 | L103: =SUM(L100:L102) -> 19654.289 | M103: =SUM(M100:M102) -> 23954.208 | ... P103: =SUM(P100:P102) -> 39530.49
B105: Balance Sheet
B106: Current assets
B107: Inventories | F107: =年度版model!E232 -> 4079.4 | G107: =年度版model!F232 -> 4482.4 | H107: =年度版model!G232 -> 4630.1 | I107: =年度版model!H232 -> 4543.3 | J107: =年度版model!I232 -> 4894.1616 | K107: =年度版model!J232 -> 5138.8791 | L107: =年度版model!K232 -> 5376.1661 | M107: =年度版model!L232 -> 5649.1915 | ... P107: =年度版model!O232 -> 6623.9247
B108: Trade accounts receivable | F108: =年度版model!E234 -> 4755.5 | G108: =年度版model!F234 -> 5092.7 | H108: =年度版model!G234 -> 5601.8 | I108: =年度版model!H234 -> 5500.3 | J108: =年度版model!I234 -> 5775.649 | K108: =年度版model!J234 -> 6082.9872 | L108: =年度版model!K234 -> 6429.813 | M108: =年度版model!L234 -> 6736.5201 | ... P108: =年度版model!O234 -> 7893.297
B109: Other current assets | F109: =年度版model!E236 -> 2423.2 | G109: =年度版model!F236 -> 2270.6 | H109: =年度版model!G236 -> 1955.3 | I109: =年度版model!H236 -> 2063.8 | J109: =年度版model!I236 -> 2063.8 | K109: =年度版model!J236 -> 2063.8 | L109: =年度版model!K236 -> 2063.8 | M109: =年度版model!L236 -> 2063.8 | ... P109: =年度版model!O236 -> 2063.8
B110: Current tax assets | F110: =年度版model!E237 -> 173.9 | G110: =年度版model!F237 -> 191.6 | H110: =年度版model!G237 -> 234.1 | I110: =年度版model!H237 -> 226 | J110: =年度版model!I237 -> 226 | K110: =年度版model!J237 -> 226 | L110: =年度版model!K237 -> 226 | M110: =年度版model!L237 -> 226 | ... P110: =年度版model!O237 -> 226
B111: Cash and cash equivalents | F111: =年度版model!E238 -> 2617.7 | G111: =年度版model!F238 -> 4288 | H111: =年度版model!G238 -> 4052.3 | I111: =年度版model!H238 -> 9865 | J111: =年度版model!I238 -> 12286.4 | K111: =年度版model!J238 -> 15213.324 | L111: =年度版model!K238 -> 19654.289 | M111: =年度版model!L238 -> 23954.208 | ... P111: =年度版model!O238 -> 39530.49
F113: =SUM(F107:F111) -> 14049.7 | G113: =SUM(G107:G111) -> 16325.3 | H113: =SUM(H107:H111) -> 16473.6 | I113: =SUM(I107:I111) -> 22198.4 | J113: =SUM(J107:J111) -> 25246.011 | K113: =SUM(K107:K111) -> 28724.991 | L113: =SUM(L107:L111) -> 33750.069 | M113: =SUM(M107:M111) -> 38629.72 | ... P113: =SUM(P107:P111) -> 56337.512
B114: Non-current assets
B115: Goodwill | F115: =年度版model!E222 -> 11717.7 | G115: =年度版model!F222 -> 13102.6 | H115: =年度版model!G222 -> 13382 | I115: =年度版model!H222 -> 14469.7 | J115: =年度版model!I222 -> 16160.583 | K115: =年度版model!J222 -> 17582.694 | L115: =年度版model!K222 -> 19429.226 | M115: =年度版model!L222 -> 21082.401 | ... P115: =年度版model!O222 -> 26105.518
...

Sheet 年度版model
A1: L'OREAL | B1: FY19 | C1: FY20 | D1: FY21 | E1: FY22 | F1: FY23 | G1: FY24 | H1: FY25 | I1: FY26e | J1: FY27e | K1: FY28e | L1: FY29e | M1: FY30e | N1: FY31e | O1: FY32e
A2: NET SALES | B2: 29873.6 | C2: 27992.1 | D2: 32287.181 | E2: 38260.7 | F2: 41182.6 | G2: 43486.8 | H2: 44052 | I2: =I4+I6+I8+I10 -> 46055.159 | J2: =J4+J6+J8+J10 -> 48398.286 | K2: =K4+K6+K8+K10 -> 50952.563 | L2: =L4+L6+L8+L10 -> 53661.992 | M2: =M4+M6+M8+M10 -> 56524.137 | N2: =N4+N6+N8+N10 -> 59547.996 | O2: =O4+O6+O8+O10 -> 62743.114
A3: yoy | C3: =C2/B2-1 -> -0.062982031 | D3: =D2/C2-1 -> 0.15343905 | E3: =E2/D2-1 -> 0.18501209 | F3: =F2/E2-1 -> 0.076368179 | G3: =G2/F2-1 -> 0.055950814 | H3: =H2/G2-1 -> 0.012997047 | I3: =I2/H2-1 -> 0.045472611 | J3: =J2/I2-1 -> 0.05087653 | ... O3: =O2/N2-1 -> 0.053656185
A4: -Professional Products | B4: 3441.9 | C4: 3097.3 | D4: 3783.9 | E4: 4476.8 | F4: 4653.9 | G4: 4886 | H4: 5163 | I4: =H4*(1+I5) -> 5630.4745 | J4: =I4*(1+J5) -> 5954.4886 | K4: =J4*(1+K5) -> 6297.1486 | L4: =K4*(1+L5) -> 6659.5275 | M4: =L4*(1+M5) -> 7042.76 | N4: =M4*(1+N5) -> 7448.0463 | O4: =N4*(1+O5) -> 7876.6553
A5: yoy | C5: =C4/B4-1 -> -0.10011912 | D5: =D4/C4-1 -> 0.22167694 | E5: =E4/D4-1 -> 0.18311795 | F5: =F4/E4-1 -> 0.039559507 | G5: =G4/F4-1 -> 0.04987215 | H5: =H4/G4-1 -> 0.056692591 | I5: 0.090543197 | J5: 0.057546503 | K5: 0.057546503 | L5: 0.057546503 | M5: 0.057546503 | N5: 0.057546503 | O5: 0.057546503
A6: -Consumer Products | B6: 12748.2 | C6: 11703.8 | D6: 12233.5 | E6: 14021.3 | F6: 15172.7 | G6: 15982 | H6: 16089.7 | I6: =H6*(1+I7) -> 16536.879 | J6: =I6*(1+J7) -> 17135.652 | K6: =J6*(1+K7) -> 17756.106 | L6: =K6*(1+L7) -> 18399.026 | M6: =L6*(1+M7) -> 19065.224 | N6: =M6*(1+N7) -> 19755.544 | O6: =N6*(1+O7) -> 20470.86
A7: yoy | C7: =C6/B6-1 -> -0.081925291 | D7: =D6/C6-1 -> 0.045258805 | E7: =E6/D6-1 -> 0.1461397 | F7: =F6/E6-1 -> 0.082117921 | G7: =G6/F6-1 -> 0.053339221 | H7: =H6/G6-1 -> 0.0067388312 | I7: 0.027792879 | J7: 0.036208357 | K7: 0.036208357 | L7: 0.036208357 | M7: 0.036208357 | N7: 0.036208357 | O7: 0.036208357
A8: -Luxury Products | B8: 11019.8 | C8: 10179.9 | D8: 12346.2 | E8: 14638.1 | F8: 14924 | G8: 15591 | H8: 15595.1 | I8: =H8*(1+I9) -> 16260.645 | J8: =I8*(1+J9) -> 17251.712 | K8: =J8*(1+K9) -> 18389.441 | L8: =K8*(1+L9) -> 19614.619 | M8: =L8*(1+M9) -> 20921.424 | N8: =M8*(1+N9) -> 22315.293 | O8: =N8*(1+O9) -> 23802.027
A9: yoy | C9: =C8/B8-1 -> -0.076217354 | D9: =D8/C8-1 -> 0.2128017 | E9: =E8/D8-1 -> 0.18563607 | F9: =F8/E8-1 -> 0.019531223 | G9: =G8/F8-1 -> 0.044693112 | H9: =H8/G8-1 -> 0.00026297223 | I9: 0.042676532 | J9: 0.060948802 | K9: 0.065948802 | L9: 0.066624002 | M9: 0.066624002 | N9: 0.066624002 | O9: 0.066624002
A10: -Dermatological Beauty | B10: 2663.7 | C10: 3011.1 | D10: 3924 | E10: 5124.5 | F10: 6432 | G10: 7027 | H10: 7204.1 | I10: =H10*(1+I11) -> 7627.161 | J10: =I10*(1+J11) -> 8056.4336 | K10: =J10*(1+K11) -> 8509.8665 | L10: =K10*(1+L11) -> 8988.8195 | M10: =L10*(1+M11) -> 9494.729 | N10: =M10*(1+N11) -> 10029.112 | O10: =N10*(1+O11) -> 10593.572
A11: yoy | C11: =C10/B10-1 -> 0.13042009 | D11: =D10/C10-1 -> 0.30317824 | E11: =E10/D10-1 -> 0.30593782 | F11: =F10/E10-1 -> 0.25514684 | G11: =G10/F10-1 -> 0.092506219 | H11: =H10/G10-1 -> 0.025202789 | I11: 0.058725038 | J11: 0.056282087 | K11: 0.056282087 | L11: 0.056282087 | M11: 0.056282087 | N11: 0.056282087 | O11: 0.056282087
A12: -Other Cosmetics Sales
A13: The Body Shop
A14: Galderma
A16: Cost of good sold - NOT A DRIVER | B16: -8064.7 | C16: -7532.3 | D16: -8433.3 | E16: -10577.4 | F16: -10767 | G16: -11227 | H16: -11313.4 | I16: =-(I2-I19) -> -11781.795 | J16: =-(J2-J19) -> -12236.017 | K16: =-(K2-K19) -> -12728.929 | L16: =-(L2-L19) -> -13244.811 | M16: =-(M2-M19) -> -13781.671 | N16: =-(N2-N19) -> -14340.302 | O16: =-(O2-O19) -> -14921.518
A17: - as % of sales | B17: 0.26996077 | C17: 0.26908664 | D17: 0.26119654 | E17: 0.276456 | F17: 0.26144537 | G17: 0.2581703 | H17: 0.2581703 | I17: 0.2571703 | J17: 0.2541703 | K17: 0.2511703 | L17: 0.2481703 | M17: 0.2451703 | N17: 0.2421703 | O17: 0.2391703
A19: Gross profit | B19: =B2+B16 -> 21808.9 | C19: =C2+C16 -> 20459.8 | D19: =D2+D16 -> 23853.881 | E19: =E2+E16 -> 27683.3 | F19: =F2+F16 -> 30415.6 | G19: =G2+G16 -> 32259.8 | H19: =H2+H16 -> 32738.6 | I19: =I20*I2 -> 34273.365 | J19: =J20*J2 -> 36162.269 | K19: =K20*K2 -> 38223.633 | L19: =L20*L2 -> 40417.181 | M19: =M20*M2 -> 42742.466 | N19: =N20*N2 -> 45207.694 | O19: =O20*O2 -> 47821.596
A20: - gross margin | B20: =B19/B2 -> 0.73003923 | C20: =C19/C2 -> 0.73091336 | D20: =D19/D2 -> 0.73880346 | E20: =E19/E2 -> 0.723544 | F20: =F19/F2 -> 0.73855463 | G20: =G19/G2 -> 0.7418297 | H20: =H19/H2 -> 0.74318079 | I20: =H20+I21 -> 0.74418079 | J20: =I20+J21 -> 0.74718079 | K20: =J20+K21 -> 0.75018079 | L20: =K20+L21 -> 0.75318079 | M20: =L20+M21 -> 0.75618079 | N20: =M20+N21 -> 0.75918079 | O20: =N20+O21 -> 0.76218079
A21: - gross margin progression | C21: =C20-B20 -> 0.00087413288 | D21: =D20-C20 -> 0.0078900951 | E21: =E20-D20 -> -0.015259458 | F21: =F20-E20 -> 0.01501063 | G21: =G20-F20 -> 0.0032750723 | H21: 0 | I21: 0.001 | J21: 0.003 | K21: 0.003 | L21: 0.003 | M21: 0.003 | N21: 0.003 | O21: 0.003
A23: Research and innovation expenses | B23: -985.3 | C23: -964.4 | D23: -1028.7 | E23: -1138.6 | F23: -1288.9 | G23: -1354.7 | H23: -1380.6 | I23: =-(I2*I25) -> -1427.7099 | J23: =-(J2*J25) -> -1500.3469 | K23: =-(K2*K25) -> -1579.5294 | L23: =-(L2*L25) -> -1663.5218 | M23: =-(M2*M25) -> -1752.2482 | N23: =-(N2*N25) -> -1845.9879 | O23: =-(O2*O25) -> -1945.0365
A24: - reported growth | B24: 0.077537183 | C24: -0.021211814 | D24: 0.066673579 | E24: 0.10683387 | F24: 0.13200422 | G24: 0.051051284 | H24: 0.0075880703 | I24: =(-I23)/(-H23)-1 -> 0.034122804 | J24: =(-J23)/(-I23)-1 -> 0.05087653 | K24: =(-K23)/(-J23)-1 -> 0.052776175 | L24: =(-L23)/(-K23)-1 -> 0.05317553 | M24: =(-M23)/(-L23)-1 -> 0.05333654 | N24: =(-N23)/(-M23)-1 -> 0.053496771 | O24: =(-O23)/(-N23)-1 -> 0.053656185
A25: - as % of sales | B25: =-B23/B2 -> 0.032982299 | C25: =-C23/C2 -> 0.034452578 | D25: =-D23/D2 -> 0.031860942 | E25: =-E23/E2 -> 0.029758996 | F25: =-F23/F2 -> 0.031297198 | G25: =-G23/G2 -> 0.031151982 | H25: =-H23/H2 -> 0.031340234 | I25: 0.031 | J25: 0.031 | K25: 0.031 | L25: 0.031 | M25: 0.031 | N25: 0.031 | O25: 0.031
A27: Advertising and promotion expenses | B27: -9207.8 | C27: -8647.9 | D27: -10591 | E27: -12059 | F27: -13356.6 | G27: -14008.9 | H27: -14177.8 | I27: =-(I2*I29) -> -14645.541 | J27: =-(J2*J29) -> -15342.257 | K27: =-(K2*K29) -> -16151.962 | L27: =-(L2*L29) -> -17010.851 | M27: =-(M2*M29) -> -17918.151 | N27: =-(N2*N29) -> -18876.715 | O27: =-(O2*O29) -> -19889.567
A28: - reported growth | B28: 0.1305266 | C28: -0.060807142 | D28: 0.22469039 | E28: 0.13860825 | F28: 0.10760428 | G28: 0.048837279 | H28: 0.0057971415 | I28: =(-I27)/(-H27)-1 -> 0.032991064 | J28: =(-J27)/(-I27)-1 -> 0.047571887 | K28: =(-K27)/(-J27)-1 -> 0.052776175 | L28: =(-L27)/(-K27)-1 -> 0.05317553 | M28: =(-M27)/(-L27)-1 -> 0.05333654 | N28: =(-N27)/(-M27)-1 -> 0.053496771 | O28: =(-O27)/(-N27)-1 -> 0.053656185
A29: - as % of sales | B29: =-B27/B2 -> 0.30822532 | C29: =-C27/C2 -> 0.30894074 | D29: =-D27/D2 -> 0.32802492 | E29: =-E27/E2 -> 0.31517981 | F29: =-F27/F2 -> 0.32432629 | G29: =-G27/G2 -> 0.32214143 | H29: =-H27/H2 -> 0.32184237 | I29: 0.318 | J29: 0.317 | K29: 0.317 | L29: 0.317 | M29: 0.317 | N29: 0.317 | O29: 0.317
A31: Selling, general and admnistrative expenses | B31: -6068.3 | C31: -5638.5 | D31: -6074.2 | E31: -7028.8 | F31: -7626.7 | G31: -8208.7 | H31: -8288.3 | I31: =-I33*I2 -> -8704.4251 | J31: =-J33*J2 -> -9098.8778 | K31: =-K33*K2 -> -9528.1292 | L31: =-L33*L2 -> -9981.1305 | M31: =-M33*M2 -> -10456.965 | N31: =-N33*N2 -> -10956.831 | O31: =-O33*O2 -> -11481.99
A32: - reported growth | B32: 0.078866428 | C32: -0.070827085 | D32: 0.077272324 | E32: 0.1571565 | F32: 0.085064307 | G32: 0.076310855 | H32: 0.013799036 | I32: =(-I31)/(-H31)-1 -> 0.050206331 | J32: =(-J31)/(-I31)-1 -> 0.045316337 | K32: =(-K31)/(-J31)-1 -> 0.047176302 | L32: =(-L31)/(-K31)-1 -> 0.047543575 | M32: =(-M31)/(-L31)-1 -> 0.04767344 | N32: =(-N31)/(-M31)-1 -> 0.047802193 | O32: =(-O31)/(-N31)-1 -> 0.047929793
A33: - as % of sales | B33: =-B31/B2 -> 0.20313253 | C33: =-C31/C2 -> 0.20143183 | D33: =-D31/D2 -> 0.18813039 | E33: =-E31/E2 -> 0.18370809 | F33: =-F31/F2 -> 0.18519229 | G33: =-G31/G2 -> 0.18876303 | H33: =-H31/H2 -> 0.1881481 | I33: 0.189 | J33: 0.188 | K33: 0.187 | L33: 0.186 | M33: 0.185 | N33: 0.184 | O33: 0.183
A35: OPERATING PROFIT - DIVISIONS | B35: =B38+B40+B42+B44 -> 6380.7 | C35: =C38+C40+C42+C44 -> 6011.7 | D35: =D38+D40+D42+D44 -> 7079.7 | E35: =E38+E40+E42+E44 -> 8381.9 | F35: =F38+F40+F42+F44 -> 9122.7 | G35: =G38+G40+G42+G44 -> 9765 | H35: =H38+H40+H42+H44 -> 9993.8 | I35: =I38+I40+I42+I44 -> 10569.514 | ... O35: =O38+O40+O42+O44 -> 15437.757
A36: - Operating profit margin | B36: =B35/B2 -> 0.21358993 | C36: =C35/C2 -> 0.21476417 | D36: =D35/D2 -> 0.21927278 | E36: =E35/E2 -> 0.21907336 | F36: =F35/F2 -> 0.22151831 | G36: =G35/G2 -> 0.2245509 | H36: =H35/H2 -> 0.22686371 | I36: 0.22949685 | J36: 0.23253517 | K36: 0.23521854 | L36: 0.23791098 | M36: 0.24061329 | N36: 0.24332535 | O36: 0.24604704
A37: - Operating profit margin progression | B37: 29.162896 | C37: 11.735275 | D37: 45.086154 | E37: -1.9657919 | F37: 24.449539 | G37: 30.325871 | H37: 21.832873 | I37: 27.626683 | J37: 30.383166 | K37: 26.833693 | L37: 26.924428 | M37: 27.023096 | N37: 27.12059 | O37: 27.216867
A38: -Professional Products | B38: 691.6 | C38: 581.7 | D38: 806.9 | E38: 953.6 | F38: 1005.3 | G38: 1086.2 | H38: 1180.3 | I38: =I39*I2 -> 1324.1117 | J38: =J39*J2 -> 1424.3683 | K38: =K39*K2 -> 1531.7607 | L38: =L39*L2 -> 1646.7912 | M38: =M39*M2 -> 1769.9856 | N38: =N39*N2 -> 1901.9023 | O38: =O39*O2 -> 2043.1371
A39: - Professional Products OPM | B39: =B38/B2 -> 0.023150876 | C39: =C38/C2 -> 0.020780863 | D39: =D38/D2 -> 0.024991342 | E39: =E38/E2 -> 0.024923747 | F39: =F38/F2 -> 0.024410795 | G39: =G38/G2 -> 0.024977694 | H39: =H38/H2 -> 0.026793335 | I39: 0.028750562 | J39: 0.029430139 | K39: 0.030062485 | L39: 0.030688224 | M39: 0.031313802 | N39: 0.031938981 | O39: 0.032563527
A40: -Consumer Products | B40: 2574.6 | C40: 2388.1 | D40: 2466 | E40: 2774.9 | F40: 3114.7 | G40: 3376.4 | H40: 3443.3 | I40: =I41*I2 -> 3579.2379 | J40: =J41*J2 -> 3759.9083 | K40: =K41*K2 -> 3931.2363 | L40: =L41*L2 -> 4110.0324 | M40: =M41*M2 -> 4296.6185 | N40: =N41*N2 -> 4491.3243 | O40: =O41*O2 -> 4694.493
A41: - Consumer Products OPM | B41: =B40/B2 -> 0.086183118 | C41: =C40/C2 -> 0.085313356 | D41: =D40/D2 -> 0.076377061 | E41: =E40/E2 -> 0.072526117 | F41: =F40/F2 -> 0.075631456 | G41: =G40/G2 -> 0.077641951 | H41: =H40/H2 -> 0.078164442 | I41: 0.077716328 | J41: 0.077686807 | K41: 0.07715483 | L41: 0.076591127 | M41: 0.076013872 | N41: 0.075423601 | O41: 0.074820848
A42: -Luxury Products | B42: 2493.7 | C42: 2275.9 | D42: 2816.3 | E42: 3350.4 | F42: 3331.8 | G42: 3469.7 | H42: 3488.1 | I42: =I43*I2 -> 3690.8049 | J42: =J43*J2 -> 3967.6901 | K42: =K43*K2 -> 4284.6651 | L42: =L43*L2 -> 4629.1099 | M42: =M43*M2 -> 5000.4264 | N42: =N43*N2 -> 5400.666 | O42: =O43*O2 -> 5832.034
A43: - Luxury Products OPM | B43: =B42/B2 -> 0.083475042 | C43: =C42/C2 -> 0.081305083 | D43: =D42/D2 -> 0.087226568 | E43: =E42/E2 -> 0.087567661 | F43: =F42/F2 -> 0.0809031 | G43: =G42/G2 -> 0.07978743 | H43: =H42/H2 -> 0.079181422 | I43: 0.080138793 | J43: 0.08197997 | K43: 0.084091259 | L43: 0.086264221 | M43: 0.08846533 | N43: 0.090694337 | O43: 0.09295098
A44: -Dermatological Beauty | B44: 620.8 | C44: 766 | D44: 990.5 | E44: 1303 | F44: 1670.9 | G44: 1832.7 | H44: 1882.1 | I44: =I45*I2 -> 1975.3597 | J44: =J45*J2 -> 2102.337 | K44: =K45*K2 -> 2237.3253 | L44: =L45*L2 -> 2380.8437 | M44: =M45*M2 -> 2533.4281 | N44: =N45*N2 -> 2695.6444 | O44: =O45*O2 -> 2868.0933
A45: - Dermatological Beauty OPM | B45: =B44/B2 -> 0.02078089 | C45: =C44/C2 -> 0.027364864 | D45: =D44/D2 -> 0.03067781 | E45: =E44/E2 -> 0.034055833 | F45: =F44/F2 -> 0.04057296 | G45: =G44/G2 -> 0.042143823 | H45: =H44/H2 -> 0.042724507 | I45: 0.042891171 | J45: 0.043438254 | K45: 0.043909965 | L45: 0.044367411 | M45: 0.044820288 | N45: 0.045268432 | O45: 0.045711683
A46: Non-allocated operating profit | B46: -833.2 | C46: -802.6 | D46: -919.4 | E46: -925.1 | F46: -979.4 | G46: -1077.5 | H46: -1101.8 | I46: =I48-I35 -> -1073.8252 | J46: =J48-J35 -> -1033.5156 | K46: =K48-K35 -> -1020.9749 | L46: =L48-L35 -> -1005.0996 | M46: =M48-M35 -> -985.35735 | N46: =N48-N35 -> -961.37648 | O46: =O48-O35 -> -932.75491
A48: Adjusted group operating profit | B48: =B19+B23+B27+B31 -> 5547.5 | C48: =C19+C23+C27+C31 -> 5209 | D48: =D19+D23+D27+D31 -> 6159.9811 | E48: =E19+E23+E27+E31 -> 7456.9 | F48: =F19+F23+F27+F31 -> 8143.4 | G48: =G19+G23+G27+G31 -> 8687.5 | H48: =H19+H23+H27+H31 -> 8891.9 | I48: =I19+I23+I27+I31 -> 9495.689 | ... O48: =O19+O23+O27+O31 -> 14505.002
A49: - reported growth | B49: 0.12710539 | C49: =C48/B48-1 -> -0.061018477 | D49: =D48/C48-1 -> 0.18256501 | E49: =E48/D48-1 -> 0.21053942 | F49: =F48/E48-1 -> 0.092062385 | G49: =G48/F48-1 -> 0.066814844 | H49: =H48/G48-1 -> 0.023528058 | I49: =I48/H48-1 -> 0.067903259 | J49: =J48/I48-1 -> 0.076360877 | ... O49: =O48/N48-1 -> 0.072208039
A50: - Operating profit margin | B50: =B48/B2 -> 0.18569908 | C50: =C48/C2 -> 0.18608822 | D50: =D48/D2 -> 0.19078721 | E50: =E48/E2 -> 0.19489711 | F50: =F48/F2 -> 0.19773885 | G50: =G48/G2 -> 0.19977326 | H50: =H48/H2 -> 0.20185009 | I50: =I48/I2 -> 0.20618079 | ... O50: =O48/O2 -> 0.23118079
A52: Other income and expenses | B52: -436.5 | C52: -709 | D52: -432 | E52: -241.5 | F52: -449.9 | G52: -437.7 | H52: -505.4 | I52: =(H52+G52)/2 -> -471.55 | J52: =(I52+H52)/2 -> -488.475 | K52: =(J52+I52)/2 -> -480.0125 | L52: =(K52+J52)/2 -> -484.24375 | M52: =(L52+K52)/2 -> -482.12813 | N52: =(M52+L52)/2 -> -483.18594 | O52: =(N52+M52)/2 -> -482.65703
A54: Operational profit | B54: =B35+B46+B52 -> 5111 | C54: =C35+C46+C52 -> 4500.1 | D54: =D35+D46+D52 -> 5728.3 | E54: =E35+E46+E52 -> 7215.3 | F54: =F35+F46+F52 -> 7693.4 | G54: =G35+G46+G52 -> 8249.8 | H54: =H48+H52 -> 8386.5 | I54: =I48+I52 -> 9024.139 | J54: =J48+J52 -> 9732.3131 | K54: =K48+K52 -> 10484 | L54: =L48+L52 -> 11277.434 | M54: =M48+M52 -> 12132.973 | N54: =N48+N52 -> 13044.975 | O54: =O48+O52 -> 14022.345
A55: - reported growth | B55: 0.058791846 | C55: =C54/B54-1 -> -0.11952651 | D55: =D54/C54-1 -> 0.27292727 | E55: =E54/D54-1 -> 0.25958836 | F55: =F54/E54-1 -> 0.066261971 | G55: =G54/F54-1 -> 0.07232173 | H55: =H54/G54-1 -> 0.016570099 | I55: =I54/H54-1 -> 0.076031597 | J55: =J54/I54-1 -> 0.078475535 | ... O55: =O54/N54-1 -> 0.07492317
A57: Financial Cost On Net Debt | B57: =B58+B59 -> -46.7 | C57: =C58+C59 -> -59.4 | D57: =D58+D59 -> -19.5 | E57: =E58+E59 -> -0.6 | F57: =F58+F59 -> -64.6 | G57: =G58+G59 -> -224.7 | H57: -198.1 | I57: =I58+I59 -> -136 | J57: =J58+J59 -> -59.04 | K57: =K58+K59 -> -89.04 | L57: =L58+L59 -> -89.04 | M57: =M58+M59 -> -89.04 | N57: =N58+N59 -> -89.04 | O57: 714.34208
A58: -Finance costs on gross debt | B58: -75.4 | C58: -79.2 | D58: -38 | E58: -70.4 | F58: -226.7 | G58: -373.4 | H58: -365.8 | I58: -366 | J58: -259.04 | K58: -259.04 | L58: -259.04 | M58: -259.04 | N58: -259.04 | O58: -259.04
A59: -Finance income on cash and cash equivalents | B59: 28.7 | C59: 19.8 | D59: 18.5 | E59: 69.8 | F59: 162.1 | G59: 148.7 | H59: 167.7 | I59: 230 | J59: 200 | K59: 170 | L59: =K59 -> 170 | M59: =L59 -> 170 | N59: =M59 -> 170 | O59: =N59 -> 170
A60: Other financial income/expense | B60: -15.9 | C60: -36.5 | D60: -40.2 | E60: -72.3 | F60: -48.8 | G60: -36.7 | H60: -38 | I60: =H60 -> -38 | J60: =I60 -> -38 | K60: =J60 -> -38 | L60: =K60 -> -38 | M60: =L60 -> -38 | N60: =M60 -> -38 | O60: =N60 -> -38
A61: Dividends received | B61: 363 | C61: 372.4 | D61: 378.3 | E61: 468.2 | F61: 420.9 | G61: 444.5 | H61: 351.9 | I61: =H61*(1+I62) -> 357.1785 | J61: =I61*(1+J62) -> 367.89385 | K61: =J61*(1+K62) -> 378.93067 | L61: =K61*(1+L62) -> 390.29859 | M61: =L61*(1+M62) -> 402.00755 | N61: =M61*(1+N62) -> 414.06777 | O61: =N61*(1+O62) -> 426.48981
A62: - reported growth | H62: -0.21864567 | I62: 0.015 | J62: 0.03 | K62: 0.03 | L62: 0.03 | M62: 0.03 | N62: 0.03 | O62: 0.03
A64: Reported profit before tax | B64: =B54+B57+B60+B61 -> 5411.4 | C64: =C54+C57+C60+C61 -> 4776.6 | D64: =D54+D57+D60+D61 -> 6046.9 | E64: =E54+E57+E60+E61 -> 7610.6 | F64: =F54+F57+F60+F61 -> 8000.9 | G64: =G54+G57+G60+G61 -> 8432.9 | H64: =H54+H57+H60+H61 -> 8502.3 | I64: =I54+I57+I60+I61 -> 9207.3175 | ... O64: =O54+O57+O60+O61 -> 15125.177
A65: - reported growth | C65: =C64/B64-1 -> -0.11730791 | D65: =D64/C64-1 -> 0.2659423 | E65: =E64/D64-1 -> 0.25859531 | F65: =F64/E64-1 -> 0.051283736 | G65: =G64/F64-1 -> 0.053993926 | H65: =H64/G64-1 -> 0.0082296719 | I65: =I64/H64-1 -> 0.082920797 | J65: =J64/I64-1 -> 0.086436629 | ... O65: =O64/N64-1 -> 0.13450155
A67: Income tax | B67: -1657.2 | C67: -1209.8 | D67: -1445.4 | E67: -1899.4 | F67: -1810.6 | G67: -2015.1 | H67: -2363.1 | I67: =-I64*I68 -> -2409.2187 | J67: =-J64*J68 -> -2609.067 | K67: =-K64*K68 -> -2791.8224 | L67: =-L64*L68 -> -3001.1077 | M67: =-M64*M68 -> -3226.6319 | N67: =-N64*N68 -> -3466.9301 | O67: =-O64*O68 -> -3933.2376
A68: - effective tax rate | B68: 0.30624238 | C68: 0.25328169 | D68: 0.23903157 | E68: 0.24957296 | F68: 0.22629954 | G68: 0.23895694 | H68: 0.26252517 | I68: 0.26166348 | J68: 0.2608241 | K68: 0.26004572 | L68: =K68 -> 0.26004572 | M68: =L68 -> 0.26004572 | N68: =M68 -> 0.26004572 | O68: =N68 -> 0.26004572
A70: Share in profit/(loss) of associates | B70: 1 | C70: 0.9 | D70: 0.6 | E70: 1.4 | F70: 0.2 | G70: -1.3 | H70: -5.5 | I70: =H70 -> -5.5 | J70: =I70 -> -5.5 | K70: =J70 -> -5.5 | L70: =K70 -> -5.5 | M70: =L70 -> -5.5 | N70: =M70 -> -5.5 | O70: =N70 -> -5.5
A72: NET PROFIT Attributable to Owners of the Company | B72: =B64+B67+B70+B73 -> 3750 | C72: =C64+C67+C70+C73 -> 3563.5 | D72: =D64+D67+D70+D73 -> 4596.6 | E72: =E64+E67+E70+E73 -> 5706.6 | F72: =F64+F67+F70+F73 -> 6184 | G72: =G64+G67+G70+G73 -> 6408.7 | H72: =H64+H67+H70+H73 -> 6127.2 | I72: =I64+I67+I70+I73 -> 6786.0987 | ... O72: =O64+O67+O70+O73 -> 11179.94
A73: Non-controlling interests | B73: -5.2 | C73: -4.2 | D73: -5.5 | E73: -6 | F73: -6.5 | G73: -7.8 | H73: -6.5 | I73: =H73*(1+I74) -> -6.5 | J73: =I73*(1+J74) -> -6.5 | K73: =J73*(1+K74) -> -6.5 | L73: =K73*(1+L74) -> -6.5 | M73: =L73*(1+M74) -> -6.5 | N73: =M73*(1+N74) -> -6.5 | O73: =N73*(1+O74) -> -6.5
A74: - reported growth | B74: 0.26829268 | C74: -0.19230769 | D74: 0.30952381 | E74: 0.090909091 | F74: 0.083333333 | G74: 0.2 | H74: -0.025641026 | I74: 0 | J74: 0 | K74: 0 | L74: 0 | M74: 0 | N74: 0 | O74: 0
A75: Basic EPS | B75: =B72/B88 -> 6.6995424 | C75: =C72/C88 -> 6.3736211 | D75: =D72/D88 -> 8.2424741 | E75: =E72/E88 -> 10.662824 | F75: =F72/F88 -> 11.549062 | G75: =G72/G88 -> 11.994302 | H75: =H72/H88 -> 11.48238 | I75: =I72/I88 -> 12.749256 | ... O75: =O72/O88 -> 21.259873
A76: Diluted EPS | B76: =B72/B91 -> 6.6629576 | C76: =C72/C91 -> 6.3448572 | D76: =D72/D91 -> 8.2112709 | E76: =E72/E91 -> 10.613819 | F76: =F72/F91 -> 11.515378 | G76: =G72/G91 -> 11.954781 | H76: =H72/H91 -> 11.444496 | I76: =I72/I91 -> 12.6952 | ... O76: =O72/O91 -> 21.049074
A77: Basic EPS excluding non-recurring items | B77: 7.7836177 | C77: 7.331587 | D77: 8.8582479 | E77: 11.314559 | F77: 12.114002 | G77: 12.701006 | H77: 12.877539 | I77: 13.819497 | J77: 14.879731 | K77: 16.021474 | L77: 17.250413 | M77: 18.565871 | N77: 19.968615 | O77: 21.469482
A78: - reported growth | B78: 0.092391519 | C78: -0.058074629 | D78: 0.20823061 | E78: 0.27729087 | F78: 0.070656137 | G78: 0.048456611 | H78: 0.01389914 | I78: 0.073147365 | J78: 0.076720191 | K78: 0.07673144 | L78: 0.076705713 | M78: 0.076256591 | N78: 0.075555019 | O78: 0.075161268
A79: Diluted EPS excl. non-recurring items | B79: 7.7411129 | C79: 7.2984999 | D79: 8.8247135 | E79: 11.262559 | F79: 12.07867 | G79: 12.659155 | H79: 12.835051 | I79: 13.760903 | J79: 14.802615 | K79: 15.92331 | L79: 17.128403 | M79: 18.416978 | N79: 19.789551 | O79: 21.256604
A80: - reported growth | B80: 0.093168435 | C80: -0.057176931 | D80: 0.20911333 | E80: 0.27625212 | F80: 0.072462295 | G80: 0.048058679 | H80: 0.013894792 | I80: 0.072134633 | J80: 0.075700836 | K80: 0.075709237 | L80: 0.075681081 | M80: 0.075230282 | N80: 0.0745276 | O80: 0.074132739
A81: - Exceptional items above EBIT | B81: 436.5 | C81: 709 | D81: 432 | E81: 241.5 | F81: 449.9 | G81: 437.7 | H81: =-H52 -> 505.4 | I81: =-I52 -> 471.55 | J81: =-J52 -> 488.475 | K81: =-K52 -> 480.0125 | L81: =-L52 -> 484.24375 | M81: =-M52 -> 482.12813 | N81: =-N52 -> 483.18594 | O81: =-O52 -> 482.65703
A82: - Exceptional items in tax items | B82: 170.5 | C82: -173.3 | D82: -90.2 | E82: 106 | F82: -147.2 | G82: -60.3 | H82: 0 | I82: 0 | J82: 0 | K82: 0 | L82: 0 | M82: 0 | N82: 0 | O82: 0
A83: - Non-recurring share in profit/(loss) of associates | B83: 0 | C83: 0 | D83: 0.3 | E83: -0.5 | F83: 0 | G83: 0 | H83: 0 | I83: 0 | J83: 0 | K83: 0 | L83: 0 | M83: 0 | N83: 0 | O83: 0
A84: - Non-recurring non-controlling interests | B84: -0.2 | C84: 0 | D84: 1.3 | E84: 1.8 | F84: -0.2 | G84: 0.2 | H84: 0 | I84: 0 | J84: 0 | K84: 0 | L84: 0 | M84: 0 | N84: 0 | O84: 0
A85: - Profit from discontinued operations | B85: 0 | C85: 0 | D85: 0 | E85: 0 | F85: 0 | G85: 0 | H85: 0 | I85: 0 | J85: 0 | K85: 0 | L85: 0 | M85: 0 | N85: 0 | O85: 0
A86: ADJUSTED NET PROFIT | B86: =SUM(B81:B85)+B72 -> 4356.8 | C86: =SUM(C81:C85)+C72 -> 4099.2 | D86: =SUM(D81:D85)+D72 -> 4940 | E86: =SUM(E81:E85)+E72 -> 6055.4 | F86: =SUM(F81:F85)+F72 -> 6486.5 | G86: =SUM(G81:G85)+G72 -> 6786.3 | H86: =SUM(H81:H85)+H72 -> 6632.6 | I86: =SUM(I81:I85)+I72 -> 7257.6487 | ... O86: =SUM(O81:O85)+O72 -> 11662.597
A88: Basic number of shares | B88: 559.73972 | C88: 559.10132 | D88: 557.67236 | E88: 535.18656 | F88: 535.45475 | G88: 534.31202 | H88: 533.61758 | I88: 532.27412 | J88: 531.01855 | K88: 529.84512 | L88: 528.74846 | M88: 527.72354 | N88: 526.76568 | O88: 525.87047
A89: Dilution effect | B89: 3.073411 | C89: 2.534641 | D89: 2.119185 | E89: 2.470986 | F89: 1.566289 | G89: 1.76641 | H89: 1.76641 | I89: =H89+I90 -> 2.26641 | J89: =I89+J90 -> 2.76641 | K89: =J89+K90 -> 3.26641 | L89: =K89+L90 -> 3.76641 | M89: =L89+M90 -> 4.26641 | N89: =M89+N90 -> 4.76641 | O89: =N89+O90 -> 5.26641
A90: Dilution effect progression | C90: =C89-B89 -> -0.53877 | D90: =D89-C89 -> -0.415456 | E90: =E89-D89 -> 0.351801 | F90: =F89-E89 -> -0.904697 | G90: =G89-F89 -> 0.200121 | H90: =H89-G89 -> 0 | I90: 0.5 | J90: 0.5 | K90: 0.5 | L90: 0.5 | M90: 0.5 | N90: 0.5 | O90: 0.5
A91: Diluted number of shares | B91: =B88+B89 -> 562.81313 | C91: =C88+C89 -> 561.63596 | D91: =D88+D89 -> 559.79155 | E91: =E88+E89 -> 537.65755 | F91: =F88+F89 -> 537.02104 | G91: =G88+G89 -> 536.07843 | H91: =H88+H89 -> 535.38399 | I91: =I88+I89 -> 534.54053 | ... O91: =O88+O89 -> 531.13688
A93: Dividend per share | B93: 3.85 | C93: 4 | D93: 4.8 | E93: 6 | F93: 6.6 | G93: 7 | H93: 7.2 | I93: =I96/I88 -> 7.4 | J93: =J96/J88 -> 7.6 | K93: =K96/K88 -> 7.8256227 | L93: =L96/L88 -> 8.2113046 | M93: =M96/M88 -> 8.8682296 | N93: =N96/N88 -> 9.5688478 | O93: =O96/O88 -> 10.318574
A94: - reported growth | B94: 0 | C94: =C93/B93-1 -> 0.038961039 | D94: =D93/C93-1 -> 0.2 | E94: =E93/D93-1 -> 0.25 | F94: =F93/E93-1 -> 0.1 | G94: =G93/F93-1 -> 0.060606061 | H94: =H93/G93-1 -> 0.028571429 | I94: 0.027777778 | J94: 0.027027027 | K94: 0.029687198 | L94: 0.049284495 | M94: 0.080002511 | N94: 0.079003171 | O94: 0.078350706
A95: Payout ratio | B95: =B93/B75 -> 0.57466611 | C95: =C93/C75 -> 0.62758672 | D95: =D93/D75 -> 0.58234942 | E95: =E93/E75 -> 0.56270273 | F95: =F93/F75 -> 0.57147499 | G95: =G93/G75 -> 0.58361043 | H95: =H93/H75 -> 0.62704768 | I95: =I93/I75 -> 0.58042605 | ... O95: =O93/O75 -> 0.48535443
A96: Total dividend paid | B96: 2154.9979 | C96: 2236.4053 | D96: 2676.8273 | E96: 3211.1194 | F96: 3534.0014 | G96: 3740.1841 | H96: 3842.0466 | I96: =H96*(1+I97) -> 3938.8285 | J96: =I96*(1+J97) -> 4035.741 | K96: =J96*(1+K97) -> 4146.368 | L96: =K96*(1+L97) -> 4341.7146 | M96: =L96*(1+M97) -> 4679.9735 | N96: =M96*(1+N97) -> 5040.5406 | O96: =N96*(1+O97) -> 5426.2333
A97: - reported growth | C97: =C96/B96-1 -> 0.03777608 | D97: =D96/C96-1 -> 0.19693302 | E97: =E96/D96-1 -> 0.19959899 | F97: =F96/E96-1 -> 0.10055122 | G97: =G96/F96-1 -> 0.058342591 | H97: =H96/G96-1 -> 0.027234596 | I97: 0.025190201 | J97: 0.024604399 | K97: 0.027411827 | L97: 0.047112709 | M97: 0.077909051 | N97: 0.077044681 | O97: 0.076518122
A101: SALES BY GEOGRAPHIC ZONE (not a driver)
A103: Regional split
A104: Europe | E104: 0.29891507 | F104: 0.3158567 | G104: 0.32679727 | H104: 0.32510739 | I104: 0.3190465 | J104: 0.31213543 | K104: 0.30637761 | L104: 0.30078813 | M104: 0.29516299 | N104: 0.28950433 | O104: 0.28381452
A105: North America | E105: 0.26565118 | F105: 0.27067742 | G105: 0.27146566 | H105: 0.26849784 | I105: 0.26860866 | J105: 0.2661005 | K105: 0.26320685 | L105: 0.26039844 | M105: 0.25749993 | N105: 0.25451174 | O105: 0.25143452
A106: North Asia | E106: 0.29590154 | F106: 0.2589176 | G106: 0.23693112 | H106: 0.2320657 | I106: 0.23105595 | J106: 0.23327927 | K106: 0.23471704 | L106: 0.23554582 | M106: 0.23626735 | N106: 0.2368776 | O106: 0.23737263
A107: Latin America | E107: 0.062105503 | F107: 0.070828457 | G107: 0.075974604 | H107: 0.078791773 | I107: 0.080250637 | J107: 0.082164011 | K107: 0.083992518 | L107: 0.085879451 | M107: 0.08776785 | N107: 0.089654818 | O107: 0.091537317
A108: SAPMENA-SSA | E108: 0.077426707 | F108: 0.083717395 | G108: 0.088831349 | H108: 0.095537298 | I108: 0.10103826 | J108: 0.10632079 | K108: 0.11170597 | L108: 0.11738816 | M108: 0.12330188 | N108: 0.12945151 | O108: 0.135841
A110: Europe | B110: 10168.8 | C110: 9199.3 | D110: 10184.8 | E110: 11436.7 | F110: 13007.8 | G110: 14211.4 | H110: 14723.01
A111: - reported growth | D111: 0.101 | E111: 0.123 | F111: 0.137 | G111: 0.092529098 | H111: 0.036
A112: - organic growth | D112: 0.107 | E112: 0.116 | F112: 0.16 | G112: 0.0824 | H112: 0.036
A113: reference base | G113: 13007.8 | H113: 14211.4
A114: organic growth impact | G114: 1071.8427 | H114: 511.6104
A116: North America | B116: 7567 | C116: 6903.4 | D116: 8155.9 | E116: 10164 | F116: 11147.2 | G116: 11805.2 | H116: 12159.356
A117: - reported growth | D117: 0.181 | E117: 0.246 | F117: 0.097 | G117: 0.059028276 | H117: 0.03
A118: - organic growth | D118: 0.222 | E118: 0.104 | F118: 0.118 | G118: 0.05549 | H118: 0.03
A119: reference base | G119: 11147.2 | H119: 11805.2
A120: organic growth impact | G120: 618.55813 | H120: 354.156
A122: North Asia | B122: 7908.2 | C122: 8318.1 | D122: 9863.3 | E122: 11321.4 | F122: 10662.9 | G122: 10303.4 | H122: 10509.468
A123: - reported growth | D123: 0.186 | E123: 0.148 | F123: -0.058 | G123: -0.033715031 | H123: 0.02
...

Sheet 完整版model
A1: L'OREAL | B1: DEC YE | C1: FY05 | D1: FY06 | E1: FY07 | F1: FY08 | G1: FY09 | H1: FY10 | I1: FY11 | J1: FY12 | K1: FY13 | L1: FY14 | M1: H1 15 | N1: H2 15 | O1: FY15 | P1: H1 16 | Q1: H2 16 | R1: FY16 | S1: Q1 17 | T1: Q2 17 | U1: Q3 17 | V1: Q4 17 | W1: H1 17 | X1: H2 17 | Y1: FY17 | Z1: Q1 18 | AA1: Q2 18 | AB1: Q3 18 | AC1: Q4 18 | AD1: H1 18 | AE1: H2 18 | AF1: FY18 | AG1: Q1 19 | AH1: Q2 19 | AI1: Q3 19 | AJ1: Q4 19 | AK1: H1 19 | AL1: H2 19 | AM1: FY19 | AN1: Q1 20 | AO1: Q2 20 | AP1: Q3 20 | AQ1: Q4 20 | AR1: H1 20 | AS1: H2 20 | AT1: FY20 | AU1: Q1 21 | AV1: Q2 21 | AW1: Q3 21 | AX1: Q4 21 | AY1: H1 21 | AZ1: H2 21 | BA1: FY21 | BB1: Q1 22 | BC1: Q2 22 | BD1: Q3 22 | BE1: Q4 22 | BF1: H1 22 | BG1: H2 22 | BH1: FY22 | BI1: Q1 23 | BJ1: Q2 23 | BK1: Q3 23 | BL1: Q4 23 | BM1: H1 23 | BN1: H2 23 | BO1: FY23 | BP1: Q1 24 | BQ1: Q2 24 | BR1: Q3 24 | BS1: Q4 24 | BT1: H1 24 | BU1: H2 24 | BV1: FY24 | BW1: Q1 25 | BX1: Q2 25 | BY1: Q3 25 | BZ1: Q4 25e | CA1: H1 25 | CB1: H2 25e | CC1: FY25e | CD1: Q1 26e | CE1: Q2 26e | CF1: Q3 26e | CG1: Q4 26e | CH1: H1 26e | CI1: H2 26e | CJ1: FY26e | CK1: FY27e | CL1: FY28e | CM1: FY29e | CN1: FY30e | CO1: FY31e | CP1: FY32e | CQ1: FY33e | CR1: FY34e | CS1: FY35e
A2: =+A134 -> Diluted EPS excl. non-recurring items | B2: EUR/share | C2: =C134 -> 2.5986996 | D2: =D134 -> 2.9799104 | E2: =E134 -> 3.3629671 | F2: =F134 -> 3.492012 | G2: =G134 -> 3.419912 | H2: =H134 -> 4.0088439 | I2: =I134 -> 4.3218824 | J2: =J134 -> 4.9092569 | ... R2: =R134 -> 6.4608343 | W2: =W134 -> 3.8793185 | X2: =X134 -> 2.7737727 | Y2: =Y134 -> 6.6523698 | AD2: =AD134 -> 4.0845671 | AE2: =AE134 -> 2.9934599 | AF2: =AF134 -> 7.0813543 | AK2: =AK134 -> 4.3787172 | AL2: =AL134 -> 3.359019 | AM2: =AM134 -> 7.7411129 | AR2: =AR134 -> 3.8215806 | AS2: =AS134 -> 3.4796561 | AT2: =AT134 -> 7.2984999 | AY2: =AY134 -> 4.6280611 | AZ2: =AZ134 -> 4.1797702 | BA2: =BA134 -> 8.8247135 | BF2: =BF134 -> 6.0536717 | BG2: =BG134 -> 5.2101938 | BH2: =BH134 -> 11.262559 | BM2: =BM134 -> 6.7331122 | BN2: =BN134 -> 5.3441109 | BO2: =BO134 -> 12.07867 | BT2: =BT134 -> 6.9809545 | BU2: =BU134 -> 5.6741697 | BV2: =BV134 -> 12.659155 | CA2: =CA134 -> 7.0654226 | CB2: =CB134 -> 5.7689081 | CC2: =CC134 -> 12.835051 | CH2: =CH134 -> 7.6291171 | CI2: =CI134 -> 6.119748 | CJ2: =CJ134 -> 13.760903 | CK2: =CK134 -> 14.802615 | CL2: =CL134 -> 15.92331 | CM2: =CM134 -> 17.128403 | CN2: =CN134 -> 18.416978 | CO2: =CO134 -> 19.789551 | ... CS2: =CS134 -> 26.290376
A3: =+A135 -> - reported growth | B3: % | C3: - | D3: - | E3: - | F3: - | G3: - | H3: - | I3: =I135 -> 0.078086986 | J3: =J135 -> 0.1359071 | K3: =K135 -> 0.044446306 | L3: =L135 -> 0.041460781 | O3: =O135 -> 0.15688659 | R3: =R135 -> 0.045810555 | Y3: =Y135 -> 0.029645628 | AD3: =AD135 -> 0.052908416 | AE3: =AE135 -> 0.079201587 | AF3: =AF135 -> 0.064485957 | AK3: =AK135 -> 0.072014996 | AL3: =AL135 -> 0.12211924 | AM3: =AM135 -> 0.093168435 | AR3: =AR135 -> -0.1272374 | AS3: =AS135 -> 0.035914379 | AT3: =AT135 -> -0.057176931 | AY3: =AY135 -> 0.21103322 | AZ3: =AZ135 -> 0.20120209 | BA3: =BA135 -> 0.20911333 | BF3: =BF135 -> 0.30803626 | BG3: =BG135 -> 0.24652638 | BH3: =BH135 -> 0.27625212 | BM3: =BM135 -> 0.11223609 | BN3: =BN135 -> 0.025702915 | BO3: =BO135 -> 0.072462295 | BT3: =BT135 -> 0.036809475 | BU3: =BU135 -> 0.061761217 | BV3: =BV135 -> 0.048058679 | CA3: =CA135 -> 0.012099802 | CB3: =CB135 -> 0.016696424 | CC3: =CC135 -> 0.013894792 | CH3: =CH135 -> 0.07978213 | CI3: =CI135 -> 0.060815651 | CJ3: =CJ135 -> 0.072134633 | CK3: =CK135 -> 0.075700836 | CL3: =CL135 -> 0.075709237 | CM3: =CM135 -> 0.075681081 | CN3: =CN135 -> 0.075230282 | CO3: =CO135 -> 0.0745276 | ... CS3: =CS135 -> 0.073076594
A4: Organic sales growth | B4: % | C4: =C14 -> 0.049611728 | D4: =D14 -> 0.05839472 | E4: =E14 -> 0.082182298 | F4: =F14 -> 0.032390452 | G4: =G14 -> -0.0090106765 | H4: =H14 -> 0.056197012 | I4: =I14 -> 0.050929154 | J4: =J14 -> 0.054608511 | ... CS4: =CS14 -> 0.057626997
A5: Operating profit margin | B5: % | C5: =C74 -> 0.15582682 | D5: =D74 -> 0.16092147 | E5: =E74 -> 0.16591327 | F5: =F74 -> 0.15535425 | G5: =G74 -> 0.14753291 | H5: =H74 -> 0.156803 | I5: =I74 -> 0.1618534 | J5: =J74 -> 0.16459286 | ... Y5: =Y74 -> 0.17969389 | AD5: =AD74 -> 0.19237232 | AE5: =AE74 -> 0.17317133 | AF5: =AF74 -> 0.18271622 | AK5: =AK74 -> 0.19501063 | AL5: =AL74 -> 0.17654245 | AM5: =AM74 -> 0.18569908 | AR5: =AR74 -> 0.1802623 | AS5: =AS74 -> 0.19120092 | AT5: =AT74 -> 0.18608822 | AU5: =(1+AU4)*(1+AN4)-1 -> 0.049510615 | AV5: =(1+AV4)*(1+AO4)-1 -> 0.087595099 | AW5: =(1+AW4)*(1+AP4)-1 -> 0.15085822 | AX5: =(1+AX4)*(1+AQ4)-1 -> 0.16482556 | AY5: =AY74 -> 0.1966348 | AZ5: =AZ74 -> 0.18560624 | BA5: =BA74 -> 0.19079708 | BB5: =(1+BB4)*(1+AU4)-1 -> 0.25017574 | BC5: =(1+BC4)*(1+AV4)-1 -> 0.5176067 | BD5: =(1+BD4)*(1+AW4)-1 -> 0.23435555 | BE5: =(1+BE4)*(1+AX4)-1 -> 0.20153841 | BF5: =BF74 -> 0.20393329 | BG5: =BG74 -> 0.18655501 | BH5: =BH74 -> 0.1948945 | BI5: =(1+BI4)*(1+BB4)-1 -> 0.28149096 | BJ5: =(1+BJ4)*(1+BC4)-1 -> 0.28891193 | BK5: =(1+BK4)*(1+BD4)-1 -> 0.21181871 | BL5: =(1+BL4)*(1+BE4)-1 -> 0.15738059 | BM5: =BM74 -> 0.20699812 | BN5: =BN74 -> 0.18849019 | BO5: =BO74 -> 0.19773642 | BP5: =(1+BP4)*(1+BI4)-1 -> 0.23617465 | BQ5: =(1+BQ4)*(1+BJ4)-1 -> 0.19630049 | BR5: =(1+BR4)*(1+BK4)-1 -> 0.14757536 | BS5: =(1+BS4)*(1+BL4)-1 -> 0.096191964 | BT5: =BT74 -> 0.20790839 | BU5: =BU74 -> 0.19134985 | BV5: =BV74 -> 0.19977326 | BW5: =(1+BW4)*(1+BP4)-1 -> 0.1325207 | BX5: =(1+BX4)*(1+BQ4)-1 -> 0.078611716 | BY5: =(1+BY4)*(1+BR4)-1 -> 0.07635032 | BZ5: =(1+BZ4)*(1+BS4)-1 -> 0.090803324 | CA5: =CA74 -> 0.21092047 | CB5: =CB74 -> 0.19420038 | CC5: =CC74 -> 0.20273419 | CD5: =(1+CD4)*(1+BW4)-1 -> 0.078895371 | CE5: =(1+CE4)*(1+BX4)-1 -> 0.096095063 | CF5: =(1+CF4)*(1+BY4)-1 -> 0.097716688 | CG5: =(1+CG4)*(1+BZ4)-1 -> 0.1006786 | CH5: =CH74 -> 0.2123996 | CI5: =CI74 -> 0.19849784 | CJ5: =CJ74 -> 0.20549685 | CK5: =CK74 -> 0.20853517 | CL5: =CL74 -> 0.21121854 | CM5: =CM74 -> 0.21391098 | CN5: =CN74 -> 0.21661329 | CO5: =CO74 -> 0.21932535 | ... CS5: =CS74 -> 0.23026859
A6: Operating profit margin progression | B6: bps | C6: =C56 -> 20.843399 | D6: =D56 -> 44.034512 | E6: =E56 -> 43.718178 | F6: =F56 -> -106.7372 | G6: =G56 -> -96.304999 | H6: =H56 -> 79.840127 | I6: =I56 -> 55.855006 | J6: =J56 -> 15.859865 | ... R6: =R56 -> 18.199862 | W6: =W56 -> -24.088141 | X6: =X56 -> 41.298181 | Y6: =Y56 -> 10.007492 | AD6: =AD56 -> 63.584278 | AE6: =AE56 -> -7.6545836 | AF6: =AF56 -> 25.787071 | AK6: =AK56 -> 19.225172 | AL6: =AL56 -> 39.396709 | AM6: =AM56 -> 29.162896 | AR6: =AR56 -> -144.07823 | AS6: =AS56 -> 156.96577 | AT6: =AT56 -> 11.735275 | AY6: =AY56 -> 184.50491 | AZ6: =AZ56 -> -77.939341 | BA6: =BA56 -> 45.086154 | BB6: =(1+BB4)*(1+AU4)*(1+AN4)-1 -> 0.19071448 | BC6: =(1+BC4)*(1+AV4)*(1+AO4)-1 -> 0.23372002 | BD6: =(1+BD4)*(1+AW4)*(1+AP4)-1 -> 0.25584421 | BE6: =(1+BE4)*(1+AX4)*(1+AQ4)-1 -> 0.26006205 | BF6: =BF56 -> 13.865763 | BG6: =BG56 -> -18.703018 | BH6: =BH75 -> 40.974165 | BM6: =BM75 -> 30.648281 | BN6: =BN75 -> 19.351756 | BO6: =BO75 -> 28.419226 | BT6: =BT75 -> 9.1027492 | BU6: =BU75 -> 28.596625 | BV6: =BV75 -> 20.368419 | CA6: =CA75 -> 30.120721 | CB6: =CB75 -> 28.505277 | CC6: =CC75 -> 29.60921 | CH6: =CH75 -> 14.791319 | CI6: =CI75 -> 42.974685 | CJ6: =CJ75 -> 27.626683 | CK6: =CK75 -> 30.383166 | CL6: =CL75 -> 26.833693 | CM6: =CM75 -> 26.924428 | CN6: =CN75 -> 27.023096 | CO6: =CO75 -> 27.12059 | ... CS6: =CS75 -> 27.498013
A7: Net debt/(cash) to EBITDA | B7: x | C7: =+C791 -> 0.82374141 | D7: =+D791 -> 1.0669145 | E7: =+E791 -> 0.68020523 | F7: =+F791 -> 1.0788722 | G7: =+G791 -> 0.58300584 | H7: =+H791 -> 0.010814803 | I7: =+I791 -> 0.12491325 | J7: =+J791 -> 0.34706919 | ... L7: =+L791 -> 0.14097314 | O7: =+O791 -> -0.11550107 | R7: =+R791 -> -0.086453675 | Y7: =+Y791 -> -0.32146843 | AF7: =+AF791 -> -0.45718939 | AM7: =+AM791 -> -0.33552889 | AT7: =+AT791 -> -0.56534669 | BA7: =+BA791 -> 0.45156335 | BH7: =+BH791 -> 0.33726607 | BO7: =+BO791 -> 0.44673017 | BV7: =+BV791 -> 0.42139659 | CC7: =+CC791 -> 0.13251193 | CJ7: =+CJ791 -> -0.097885966 | CK7: =+CK791 -> -0.33872742 | CL7: =+CL791 -> -0.58813818 | CM7: =+CM791 -> -0.83524095 | CN7: =+CN791 -> -1.0742635 | CO7: =+CO791 -> -1.2975059 | CP7: =+CP791 -> -1.5130758 | CQ7: =+CQ791 -> -1.7211456 | ... CS7: =+CS791 -> -2.1154919
A8: Balance sheet check | BV8: SAVE | CC8: =CC906 -> 0 | CH8: =CH906 -> 0 | CJ8: =CJ906 -> 0 | CK8: =CK906 -> 0 | CL8: =CL906 -> 0 | CM8: =CM906 -> 0 | CN8: =CN906 -> 0 | CO8: =CO906 -> 0 | CP8: =CP906 -> 0 | CQ8: =CQ906 -> 0 | ... CS8: =CS906 -> 0
A10: NET SALES | B10: EURm | C10: =SUM(C23:C29) -> 14532.8 | D10: =SUM(D23:D29) -> 15790.31 | E10: =SUM(E23:E29) -> 17063.132 | F10: =SUM(F23:F29) -> 17541.2 | G10: =SUM(G23:G29) -> 17474.068 | H10: 19495.8 | I10: 20343.1 | J10: 22462.7 | K10: 22976.6 | L10: 22532 | M10: 12818.9 | N10: =+O10-M10 -> 12438.5 | O10: 25257.4 | P10: 12894.54 | Q10: =+R10-P10 -> 12942.56 | R10: 25837.1 | S10: 7045 | T10: 6564.2 | U10: 6097.9 | V10: =+X10-U10 -> 6513.9 | W10: 13411.9 | X10: =+Y10-W10 -> 12611.8 | Y10: 26023.7 | Z10: 6778.6 | AA10: 6612.1 | AB10: 6473.3 | AC10: =+AE10-AB10 -> 7073.4 | AD10: 13390.7 | AE10: =+AF10-AD10 -> 13546.7 | AF10: 26937.4 | AG10: 7550.5 | AH10: 7261 | AI10: 7182.8 | AJ10: =+AL10-AI10 -> 7879.3 | AK10: 14811.5 | AL10: =+AM10-AK10 -> 15062.1 | AM10: 29873.6 | AN10: 7225 | AO10: =+AO19+AO20+AO21+AO22 -> 5851.3 | AP10: 7036.8 | AQ10: =+AQ19+AQ20+AQ21+AQ22 -> 7878.4 | AR10: =+AR19+AR20+AR21+AR22 -> 13076.5 | AS10: =+AS19+AS20+AS21+AS22 -> 14915.2 | AT10: =+AT19+AT20+AT21+AT22 -> 27992.1 | AU10: 7614.5 | AV10: =+AV19+AV20+AV21+AV22 -> 7582.1 | AW10: 7996.6 | AX10: =+AX19+AX20+AX21+AX22 -> 9093.9811 | AY10: =+AY19+AY20+AY21+AY22 -> 15196.7 | AZ10: =+AZ19+AZ20+AZ21+AZ22 -> 17090.481 | BA10: =+BA19+BA20+BA21+BA22 -> 32287.181 | BB10: =+BB19+BB20+BB21+BB22 -> 9060.6 | BC10: =+BC19+BC20+BC21+BC22 -> 9305.7 | BD10: =+BD19+BD20+BD21+BD22 -> 9575.1 | BE10: =+BE19+BE20+BE21+BE22 -> 10319.3 | BF10: 18366.3 | BG10: =+BG19+BG20+BG21+BG22 -> 19894.4 | BH10: =+BH19+BH20+BH21+BH22 -> 38260.7 | BI10: =+BI19+BI20+BI21+BI22 -> 10380.4 | BJ10: =+BJ19+BJ20+BJ21+BJ22 -> 10193.7 | BK10: =+BK19+BK20+BK21+BK22 -> 10003.1 | BL10: =+BL19+BL20+BL21+BL22 -> 10605.4 | BM10: 20574.1 | BN10: =+BN19+BN20+BN21+BN22 -> 20608.5 | BO10: =+BO19+BO20+BO21+BO22 -> 41182.6 | BP10: 11245 | BQ10: =+BQ19+BQ20+BQ21+BQ22 -> 10875 | BR10: =+BR19+BR20+BR21+BR22 -> 10285 | BS10: =+BS19+BS20+BS21+BS22 -> 11080.8 | BT10: 22120.8 | BU10: =+BU19+BU20+BU21+BU22 -> 21366.1 | BV10: =+BV19+BV20+BV21+BV22 -> 43486.8 | BW10: =+BW19+BW20+BW21+BW22 -> 11734.7 | BX10: =+BX19+BX20+BX21+BX22 -> 10738.7 | BY10: =+BY19+BY20+BY21+BY22 -> 10333.7 | BZ10: =+BZ19+BZ20+BZ21+BZ22 -> 11224.499 | CA10: =+CA19+CA20+CA21+CA22 -> 22473.4 | CB10: =+CB19+CB20+CB21+CB22 -> 21558.199 | ... CS10: =+CS19+CS20+CS21+CS22 -> 73461.993
A11: Check | C11: =+C19+C20+C21+C22 -> 14445.7 | E11: =+E19+E20+E21+E22 -> 17003.132 | F11: =+F19+F20+F21+F22 -> 17468.2 | G11: =+G19+G20+G21+G22 -> 17474.068 | H11: =+H19+H20+H21+H22 -> 19495.7 | I11: =+I19+I20+I21+I22 -> 20343.1 | J11: =+J19+J20+J21+J22 -> 22462.7 | K11: =+K19+K20+K21+K22 -> 22976.7 | L11: =+L19+L20+L21+L22 -> 22532 | ... CS11: =+CS19+CS20+CS21+CS22 -> 73461.993
A12: Check | C12: =+C23+C24+C25+C26+C28+C29 -> 14445.7 | D12: =+D23+D24+D25+D26+D28+D29 -> 15709.31 | E12: =+E23+E24+E25+E26+E28+E29 -> 17003.132 | F12: =+F23+F24+F25+F26+F28+F29 -> 17468.2 | G12: =+G23+G24+G25+G26+G28+G29 -> 17474.068 | H12: =+H23+H24+H25+H26+H28+H29 -> 19495.7 | I12: =+I23+I24+I25+I26+I28+I29 -> 20343.1 | J12: =+J23+J24+J25+J26+J28+J29 -> 22462.7 | K12: =+K23+K24+K25+K26+K28+K29 -> 22976.7 | L12: =+L23+L24+L25+L26+L28 -> 22532 | M12: =+M23+M24+M25+M26+M28 -> 12819.2 | N12: =+N23+N24+N25+N26+N28 -> 12438.2 | O12: =+O23+O24+O25+O26+O28 -> 25257.4 | P12: =+P23+P24+P25+P26+P28 -> 12894.6 | Q12: =+Q23+Q24+Q25+Q26+Q28 -> 12942.4 | R12: =+R23+R24+R25+R26+R28 -> 25837 | S12: =+S23+S24+S25+S26+S28 -> 7044.9 | ... X12: =+X23+X24+X25+X26+X28 -> 12611.7 | Y12: =+Y23+Y24+Y25+Y26 -> 26023.7 | Z12: =+Z23+Z24+Z25+Z26+Z28 -> 6778.7 | AA12: =+AA23+AA24+AA25+AA26+AA28 -> 6612 | AB12: =+AB23+AB24+AB25+AB26+AB28 -> 6473.3 | AC12: =+AC23+AC24+AC25+AC26+AC28 -> 7073.4 | AD12: =+AD23+AD24+AD25+AD26+AD28 -> 13390.7 | AE12: =+AE23+AE24+AE25+AE26+AE28 -> 13546.7 | AF12: =+AF23+AF24+AF25+AF26 -> 26937.4 | AG12: =+AG23+AG24+AG25+AG26+AG28 -> 7550.4 | AH12: =+AH23+AH24+AH25+AH26+AH28 -> 7261.1 | AI12: =+AI23+AI24+AI25+AI26+AI28 -> 7182.8 | AJ12: =+AJ23+AJ24+AJ25+AJ26+AJ28 -> 7879.3 | AK12: =+AK23+AK24+AK25+AK26+AK28 -> 14811.5 | AL12: =+AL23+AL24+AL25+AL26+AL28 -> 15062.1 | AM12: =+AM23+AM24+AM25+AM26 -> 29873.6 | AN12: =+AN23+AN24+AN25+AN26+AN28 -> 7225.2 | AO12: =+AO23+AO24+AO25+AO26+AO28 -> 5851.3 | AP12: =+AP23+AP24+AP25+AP26+AP28 -> 7036.8 | AQ12: =+AQ23+AQ24+AQ25+AQ26+AQ28 -> 7878.8 | AR12: =+AR23+AR24+AR25+AR26+AR28 -> 13076.5 | AS12: =+AS23+AS24+AS25+AS26+AS28 -> 14915.6 | AT12: =+AT23+AT24+AT25+AT26 -> 27992.1 | AU12: =+AU23+AU24+AU25+AU26 -> 7614.6 | AV12: =+AV23+AV24+AV25+AV26+AV28 -> 7582.1 | AW12: =+AW23+AW24+AW25+AW26 -> 7996.5 | AX12: =+AX23+AX24+AX25+AX26+AX28 -> 9094.4 | AY12: =+AY23+AY24+AY25+AY26 -> 15196.7 | AZ12: =+AZ23+AZ24+AZ25+AZ26+AZ28 -> 17090.9 | BA12: =+BA23+BA24+BA25+BA26 -> 32287.6 | BB12: =+BB23+BB24+BB25+BB26 -> 9060.6 | BC12: =+BC23+BC24+BC25+BC26+BC28 -> 9305.7 | BD12: =+BD23+BD24+BD25+BD26 -> 9575.1 | BE12: =+BE23+BE24+BE25+BE26+BE28 -> 10319.3 | BF12: =+BF23+BF24+BF25+BF26 -> 18366.3 | BG12: =+BG23+BG24+BG25+BG26+BG28 -> 19894.4 | BH12: =+BH23+BH24+BH25+BH26 -> 38260.7 | BI12: =+BI23+BI24+BI25+BI26 -> 10380.4 | BJ12: =+BJ23+BJ24+BJ25+BJ26+BJ28 -> 10193 | BK12: =+BK23+BK24+BK25+BK26 -> 10003.1 | BL12: =+BL23+BL24+BL25+BL26+BL28 -> 10605.4 | BM12: =+BM23+BM24+BM25+BM26 -> 20574.1 | BN12: =+BN23+BN24+BN25+BN26+BN28 -> 20608.5 | BO12: =+BO23+BO24+BO25+BO26 -> 41182.6 | BP12: =+BP23+BP24+BP25+BP26 -> 11245 | BQ12: =+BQ23+BQ24+BQ25+BQ26+BQ28 -> 10875.7 | BR12: =+BR23+BR24+BR25+BR26 -> 10285 | BS12: =+BS23+BS24+BS25+BS26+BS28 -> 11081.1 | BT12: =+BT23+BT24+BT25+BT26 -> 22120.7 | BU12: =+BU23+BU24+BU25+BU26+BU28 -> 21366.1 | BV12: =+BV23+BV24+BV25+BV26 -> 43486.8 | BW12: =+BW23+BW24+BW25+BW26 -> 11734.7 | BX12: =+BX23+BX24+BX25+BX26+BX28 -> 10738.7 | BY12: =+BY23+BY24+BY25+BY26 -> 10333.7 | BZ12: =+BZ23+BZ24+BZ25+BZ26+BZ28 -> 11224.499 | CA12: =+CA23+CA24+CA25+CA26 -> 22473.4 | CB12: =+CB23+CB24+CB25+CB26+CB28 -> 21558.199 | CC12: =+CC23+CC24+CC25+CC26 -> 44031.599 | CD12: =+CD23+CD24+CD25+CD26 -> 11670.603 | CE12: =+CE23+CE24+CE25+CE26+CE28 -> 11506.897 | CF12: =+CF23+CF24+CF25+CF26 -> 11073.529 | CG12: =+CG23+CG24+CG25+CG26+CG28 -> 11785.186 | CH12: =+CH23+CH24+CH25+CH26 -> 23177.501 | CI12: =+CI23+CI24+CI25+CI26+CI28 -> 22858.715 | CJ12: =+CJ23+CJ24+CJ25+CJ26 -> 46036.216 | CK12: =+CK23+CK24+CK25+CK26 -> 48380.198 | CL12: =+CL23+CL24+CL25+CL26 -> 50935.973 | CM12: =+CM23+CM24+CM25+CM26 -> 53647.182 | CN12: =+CN23+CN24+CN25+CN26 -> 56511.341 | CO12: =+CO23+CO24+CO25+CO26 -> 59537.469 | CP12: =+CP23+CP24+CP25+CP26 -> 62735.134 | CQ12: =+CQ23+CQ24+CQ25+CQ26 -> 66114.487 | ... CS12: =+CS23+CS24+CS25+CS26 -> 73461.993
A13: - reported growth | B13: % | C13: =+C10/C19-1 -> 0.072183203 | D13: =+D10/D19-1 -> 0.093080328 | E13: =+E10/E19-1 -> 0.086179573 | F13: =+F10/F19-1 -> 0.031645218 | G13: =+G10/G19-1 -> 0.00033589648 | H13: =+H10/H19-1 -> 0.11579911 | I13: =+I10/I19-1 -> 0.043465995 | J13: =+J10/J19-1 -> 0.10419258 | ... AD13: =+AD10/AD19-1 -> -0.00158813 | AE13: =+'[56]L''OREAL'!BO99/[56]Valuation!AJ11 -> 0.096315525 | AF13: =+AF10/AF19-1 -> 0.035110303 | AG13: =+AG10/AG19-1 -> 0.11385664 | AH13: =+AH10/AH19-1 -> 0.09815487 | AI13: =+AI10/AI19-1 -> 0.10960407 | AJ13: =+AJ10/AJ19-1 -> 0.11393389 | AK13: =+AK10/AK19-1 -> 0.10610349 | AL13: =+AL10/AL19-1 -> 0.11186488 | AM13: =+AM10/AM19-1 -> 0.10900087 | ... CS13: =+CS10/CS19-1 -> 0.054181326
A14: - organic growth | B14: % | C14: =+C20/C19 -> 0.049611728 | D14: =+D20/D19 -> 0.05839472 | E14: =+E20/E19 -> 0.082182298 | F14: =+F20/F19 -> 0.032390452 | G14: =+G20/G19 -> -0.0090106765 | H14: =+H20/H19 -> 0.056197012 | I14: =+I20/I19 -> 0.050929154 | J14: =+J20/J19 -> 0.054608511 | ... CS14: =+CS20/CS19 -> 0.057626997
A15: - price/mix growth | B15: % | H15: 0.006 | I15: 0.008 | K15: 0.016 | O15: 0.01 | R15: 0.007 | AF15: 0.06 | BH15: 0.072 | BO15: 0.069 | BP15: 0.062 | BT15: 0.047 | BV15: 0.036 | CA15: 0.017 | CC15: =(1+CC14)/(1+CC16)-1 -> 0.022011218 | CJ15: =(1+CJ14)/(1+CJ16)-1 -> 0.029097493 | CK15: =(1+CK14)/(1+CK16)-1 -> 0.033943392 | CL15: =(1+CL14)/(1+CL16)-1 -> 0.035816545 | CM15: =(1+CM14)/(1+CM16)-1 -> 0.03596954 | CN15: =(1+CN14)/(1+CN16)-1 -> 0.036124819 | CO15: =(1+CO14)/(1+CO16)-1 -> 0.036279346 | CP15: =(1+CP14)/(1+CP16)-1 -> 0.036433084 | CQ15: =(1+CQ14)/(1+CQ16)-1 -> 0.036585997 | ... CS15: =(1+CS14)/(1+CS16)-1 -> 0.036889213
A16: - volume growth | B16: % | H16: 0.05 | I16: 0.043 | K16: 0.034 | O16: 0.029 | R16: 0.04 | AF16: 0.01 | BH16: 0.037 | BM16: 0.049 | BO16: 0.041 | BP16: 0.032 | BT16: 0.026 | BV16: 0.014 | CA16: 0.012 | CC16: 0.019 | CJ16: 0.02 | CK16: 0.02 | CL16: 0.02 | CM16: 0.02 | CN16: 0.02 | CO16: =CN16 -> 0.02 | CP16: =CO16 -> 0.02 | CQ16: =CP16 -> 0.02 | CR16: =CQ16 -> 0.02 | CS16: =CR16 -> 0.02
A17: - forex impact | B17: % | C17: =+C21/C19 -> 0.016145517 | D17: =+D21/D19 -> -0.0010343632 | E17: =+E21/E19 -> -0.033543896 | F17: =+F21/F19 -> -0.039045359 | G17: =+G21/G19 -> -0.006884796 | H17: =+H21/H19 -> 0.055495361 | I17: =+I21/I19 -> -0.014756905 | J17: =+J21/J19 -> 0.041379264 | ... CS17: =+CS21/CS19 -> -0.003445671
A18: - scope impact | B18: % | C18: =+C22/C19 -> 0 | D18: =+D22/D19 -> 0 | E18: =+E22/E19 -> 0.03372178 | F18: =+F22/F19 -> 0.034006799 | G18: =+G22/G19 -> 0.016231369 | H18: =+H22/H19 -> 0.0041010159 | I18: =+I22/I19 -> 0.0072937468 | J18: =+J22/J19 -> 0.0082048016 | ... CS18: =+CS22/CS19 -> 0
A19: reference base | B19: EURm | C19: =+C245+C358+C471+C584+C611+C638 -> 13554.4 | D19: =+D245+D358+D471+D584+D611+D638 -> 14445.7 | E19: =+E245+E358+E471+E584+E611+E638 -> 15709.31 | F19: =+F245+F358+F471+F584+F611+F638 -> 17003.132 | G19: =+G245+G358+G471+G584+G611+G638 -> 17468.2 | H19: =+H245+H358+H471+H584+H611+H638 -> 17472.5 | I19: =+I245+I358+I471+I584+I611+I638 -> 19495.7 | J19: =+J245+J358+J471+J584+J611+J638 -> 20343.1 | K19: =+K245+K358+K471+K584+K611+K638 -> 22462.7 | L19: =+L245+L358+L471+L584+L611 -> 22150.4 | M19: =+M245+M358+M471+M584+M611 -> 11174.9 | N19: =+N245+N358+N471+N584+N611 -> 11357.1 | O19: =+O245+O358+O471+O584+O611 -> 22532 | P19: =+P245+P358+P471+P584+P611 -> 12818.7 | Q19: =+Q245+Q358+Q471+Q584+Q611 -> 12438.7 | R19: =+R245+R358+R471+R584+R611 -> 25257.4 | S19: =+S245+S358+S471+S584+S611 -> 6552.5 | ... X19: =+X245+X358+X471+X584+X611 -> 12421.2 | Y19: =+Y245+Y358+Y471+Y584 -> 24916.2 | Z19: =+Z245+Z358+Z471+Z584+Z611 -> 6847.7 | AA19: =+AA245+AA358+AA471+AA584+AA611 -> 6564.3 | AB19: =+AB245+AB358+AB471+AB584+AB611 -> 6097.9 | AC19: =+AC245+AC358+AC471+AC584+AC611 -> 6513.8 | AD19: =+AD245+AD358+AD471+AD584+AD611 -> 13412 | AE19: =+AE245+AE358+AE471+AE584+AE611 -> 12611.7 | AF19: =+AF245+AF358+AF471+AF584 -> 26023.7 | AG19: =+AG245+AG358+AG471+AG584+AG611 -> 6778.7 | AH19: =+AH245+AH358+AH471+AH584+AH611 -> 6612 | AI19: =+AI245+AI358+AI471+AI584+AI611 -> 6473.3 | AJ19: =+AJ245+AJ358+AJ471+AJ584+AJ611 -> 7073.4 | AK19: =+AK245+AK358+AK471+AK584+AK611 -> 13390.7 | AL19: =+AL245+AL358+AL471+AL584+AL611 -> 13546.7 | AM19: =+AM245+AM358+AM471+AM584 -> 26937.4 | AN19: =+AN245+AN358+AN471+AN584+AN611 -> 7550.4 | AO19: =+AO245+AO358+AO471+AO584+AO611 -> 7261.1 | AP19: =+AP245+AP358+AP471+AP584+AP611 -> 7182.8 | AQ19: =+AQ245+AQ358+AQ471+AQ584+AQ611 -> 7879.3 | AR19: =+AR245+AR358+AR471+AR584+AR611 -> 14811.5 | AS19: =+AS245+AS358+AS471+AS584+AS611 -> 15062.1 | AT19: =+AT245+AT358+AT471+AT584 -> 29874 | AU19: =+AU245+AU358+AU471+AU584 -> 7225.2 | AV19: =+AV245+AV358+AV471+AV584+AV611 -> 5851.3 | AW19: =+AW245+AW358+AW471+AW584 -> 7036.8 | AX19: =+AX245+AX358+AX471+AX584+AX611 -> 7878.8 | AY19: =+AY245+AY358+AY471+AY584 -> 13076.5 | AZ19: =+AZ245+AZ358+AZ471+AZ584+AZ611 -> 14915.6 | BA19: =+BA245+BA358+BA471+BA584 -> 27992.1 | BB19: =+BB245+BB358+BB471+BB584 -> 7614.6 | BC19: =+BC245+BC358+BC471+BC584+BC611 -> 7582.1 | BD19: =+BD245+BD358+BD471+BD584 -> 7996.5 | BE19: =+BE245+BE358+BE471+BE584+BE611 -> 9094.4 | BF19: =+BF245+BF358+BF471+BF584 -> 15196.7 | BG19: =+BG245+BG358+BG471+BG584+BG611 -> 17090.9 | BH19: =+BH245+BH358+BH471+BH584 -> 32287.6 | BI19: =+BI245+BI358+BI471+BI584 -> 9060.6 | BJ19: =+BJ245+BJ358+BJ471+BJ584+BJ611 -> 9305.7 | BK19: =+BK245+BK358+BK471+BK584 -> 9575.1 | BL19: =+BL245+BL358+BL471+BL584+BL611 -> 10319.3 | BM19: =+BM245+BM358+BM471+BM584 -> 18366.3 | BN19: =+BN245+BN358+BN471+BN584+BN611 -> 19894.4 | BO19: =+BO245+BO358+BO471+BO584 -> 38260.7 | BP19: =+BP245+BP358+BP471+BP584 -> 10380.4 | BQ19: =+BQ245+BQ358+BQ471+BQ584 -> 10193 | BR19: =+BR245+BR358+BR471+BR584 -> 10002.8 | BS19: =+BS245+BS358+BS471+BS584+BS611 -> 10605.4 | BT19: =+BT245+BT358+BT471+BT584 -> 20574.1 | BU19: =+BU245+BU358+BU471+BU584+BU611 -> 20608.5 | BV19: =+BV245+BV358+BV471+BV584 -> 41182.6 | BW19: =+BW245+BW358+BW471+BW584 -> 11245 | BX19: =+BX245+BX358+BX471+BX584 -> 10875.7 | BY19: =+BY245+BY358+BY471+BY584 -> 10285.5 | BZ19: =+BZ245+BZ358+BZ471+BZ584+BZ611 -> 11080.6 | CA19: =+CA245+CA358+CA471+CA584 -> 22120.7 | CB19: =+CB245+CB358+CB471+CB584+CB611 -> 21366.1 | CC19: =+CC245+CC358+CC471+CC584 -> 43486.8 | CD19: =+CD245+CD358+CD471+CD584 -> 11734.7 | CE19: =+CE245+CE358+CE471+CE584 -> 10738.7 | CF19: =+CF245+CF358+CF471+CF584 -> 10333.7 | CG19: =+CG245+CG358+CG471+CG584+CG611 -> 11224.499 | CH19: =+CH245+CH358+CH471+CH584 -> 22473.4 | CI19: =+CI245+CI358+CI471+CI584+CI611 -> 21558.199 | CJ19: =+CJ245+CJ358+CJ471+CJ584 -> 44031.599 | CK19: =+CK245+CK358+CK471+CK584 -> 46036.216 | CL19: =+CL245+CL358+CL471+CL584 -> 48380.198 | CM19: =+CM245+CM358+CM471+CM584 -> 50935.973 | CN19: =+CN245+CN358+CN471+CN584 -> 53647.182 | CO19: =+CO245+CO358+CO471+CO584 -> 56511.341 | CP19: =+CP245+CP358+CP471+CP584 -> 59537.469 | CQ19: =+CQ245+CQ358+CQ471+CQ584 -> 62735.134 | ... CS19: =+CS245+CS358+CS471+CS584 -> 69686.297
A20: organic growth impact | B20: EURm | C20: =+C246+C359+C472+C585+C612+C639 -> 672.4572 | D20: =+D246+D359+D472+D585+D612+D639 -> 843.5526 | E20: =+E246+E359+E472+E585+E612+E639 -> 1291.0272 | F20: =+F246+F359+F472+F585+F612+F639 -> 550.73913 | G20: =+G246+G359+G472+G585+G612+G639 -> -157.4003 | H20: =+H246+H359+H472+H585+H612+H639 -> 981.9023 | I20: =+I246+I359+I472+I585+I612+I639 -> 992.8995 | J20: =+J246+J359+J472+J585+J612+J639 -> 1110.9064 | K20: =+K246+K359+K472+K585+K612+K639 -> 1127.1043 | L20: =+L246+L359+L472+L585+L612 -> 820.5008 | M20: =+M246+M359+M472+M585+M612 -> 422.2339 | N20: =+N246+N359+N472+N585+N612 -> 449.7741 | O20: =+O246+O359+O472+O585+O612 -> 872.008 | P20: =+P246+P359+P472+P585+P612 -> 541.2919 | Q20: =+Q246+Q359+Q472+Q585+Q612 -> 649.2498 | R20: =+R246+R359+R472+R585+R612 -> 1190.5417 | S20: =+S246+S359+S472+S585+S612 -> 271.8393 | ... X20: =+X246+X359+X472+X585+X612 -> 654.48874 | Y20: =+Y246+Y359+Y472+Y585 -> 1183.8067 | Z20: =+Z246+Z359+Z472+Z585+Z612 -> 463.7854 | AA20: =+AA246+AA359+AA472+AA585+AA612 -> 413.202 | AB20: =+AB246+AB359+AB472+AB585+AB612 -> 454.6115 | AC20: =+AC246+AC359+AC472+AC585+AC612 -> 506.1665 | AD20: =+AD246+AD359+AD472+AD585+AD612 -> 876.9874 | AE20: =+AE246+AE359+AE472+AE585+AE612 -> 960.778 | AF20: =+AF246+AF359+AF472+AF585 -> 1837.7654 | AG20: =+AG246+AG359+AG472+AG585+AG612 -> 524.3141 | AH20: =+AH246+AH359+AH472+AH585+AH612 -> 453.795 | AI20: =+AI246+AI359+AI472+AI585+AI612 -> 502.0448 | AJ20: =+AJ246+AJ359+AJ472+AJ585+AJ612 -> 666.6848 | AK20: =+AK246+AK359+AK472+AK585+AK612 -> 978.1091 | AL20: =+AL246+AL359+AL472+AL585+AL612 -> 1168.7296 | AM20: =+AM246+AM359+AM472+AM585 -> 2146.8387 | AN20: =+AN246+AN359+AN472+AN585+AN612 -> -359.11456 | AO20: =+AO246+AO359+AO472+AO585+AO612 -> -1358.2765 | AP20: =+AP246+AP359+AP472+AP585+AP612 -> 125.044 | AQ20: =+AQ246+AQ359+AQ472+AQ585+AQ612 -> 383.77908 | AR20: =+AR246+AR359+AR472+AR585+AR612 -> -1717.3911 | AS20: =+AS246+AS359+AS472+AS585+AS612 -> 508.82308 | AT20: =+AT246+AT359+AT472+AT585 -> -1208.568 | AU20: =+AU246+AU359+AU472+AU585 -> 736.3961 | AV20: =+AV246+AV359+AV472+AV585+AV612 -> 1976.9057 | AW20: =+AW246+AW359+AW472+AW585 -> 922.9887 | AX20: =+AX246+AX359+AX472+AX585+AX612 -> 872.3816 | AY20: =+AY246+AY359+AY472+AY585 -> 2713.3018 | AZ20: =+AZ246+AZ359+AZ472+AZ585+AZ612 -> 1795.3703 | BA20: =+BA246+BA359+BA472+BA585 -> 4508.6721 | BB20: =+BB246+BB359+BB472+BB585 -> 1024.4879 | BC20: =+BC246+BC359+BC472+BC585+BC612 -> 1018.7006 | BD20: =+BD246+BD359+BD472+BD585 -> 729.4734 | BE20: =+BE246+BE359+BE472+BE585+BE612 -> 743.5609 | BF20: =+BF246+BF359+BF472+BF585 -> 2043.1885 | BG20: =+BG246+BG359+BG472+BG585+BG612 -> 1473.0343 | BH20: =+BH246+BH359+BH472+BH585 -> 3516.2228 | BI20: =+BI246+BI359+BI472+BI585 -> 1173.5483 | BJ20: =+BJ246+BJ359+BJ472+BJ585+BJ612 -> 1267.9011 | BK20: =+BK246+BK359+BK472+BK585 -> 1058.1746 | BL20: =+BL246+BL359+BL472+BL585+BL612 -> 721.36908 | BM20: =+BM246+BM359+BM472+BM585 -> 2441.4494 | BN20: =+BN246+BN359+BN472+BN585+BN612 -> 1779.5437 | BO20: =+BO246+BO359+BO472+BO585 -> 4220.9931 | BP20: =+BP246+BP359+BP472+BP585 -> 980.14515 | BQ20: =+BQ246+BQ359+BQ472+BQ585 -> 538.69771 | BR20: =+BR246+BR359+BR472+BR585 -> 333.83275 | BS20: =+BS246+BS359+BS472+BS585+BS612 -> 260.57027 | BT20: =+BT246+BT359+BT472+BT585 -> 1518.8429 | BU20: =+BU246+BU359+BU472+BU585+BU612 -> 594.40302 | BV20: =+BV246+BV359+BV472+BV585 -> 2113.2459 | BW20: =+BW246+BW359+BW472+BW585 -> 391.4505 | BX20: =+BX246+BX359+BX472+BX585 -> 266.11507 | BY20: =+BY246+BY359+BY472+BY585 -> 427.7577 | BZ20: =+BZ246+BZ359+BZ472+BZ585+BZ612 -> 716.31013 | CA20: =+CA246+CA359+CA472+CA585 -> 657.56557 | CB20: =+CB246+CB359+CB472+CB585+CB612 -> 1144.0678 | CC20: =+CC246+CC359+CC472+CC585 -> 1801.6334 | CD20: =+CD246+CD359+CD472+CD585 -> 499.9135 | CE20: =+CE246+CE359+CE472+CE585 -> 750.802 | CF20: =+CF246+CF359+CF472+CF585 -> 556.854 | CG20: =+CG246+CG359+CG472+CG585+CG612 -> 379.89578 | CH20: =+CH246+CH359+CH472+CH585 -> 1250.7155 | CI20: =+CI246+CI359+CI472+CI585+CI612 -> 936.74978 | CJ20: =+CJ246+CJ359+CJ472+CJ585 -> 2187.4653 | CK20: =+CK246+CK359+CK472+CK585 -> 2514.6021 | CL20: =+CL246+CL359+CL472+CL585 -> 2735.0717 | CM20: =+CM246+CM359+CM472+CM585 -> 2887.5058 | CN20: =+CN246+CN359+CN472+CN585 -> 3049.6983 | CO20: =+CO246+CO359+CO472+CO585 -> 3221.4252 | CP20: =+CP246+CP359+CP472+CP585 -> 3403.2656 | CQ20: =+CQ246+CQ359+CQ472+CQ585 -> 3595.8346 | ... CS20: =+CS246+CS359+CS472+CS585 -> 4015.8121
A21: forex impact | B21: EURm | C21: =+C247+C360+C473+C586+C613+C640 -> 218.8428 | D21: =+D247+D360+D473+D586+D613+D640 -> -14.9421 | E21: =+E247+E360+E473+E586+E613+E640 -> -526.95148 | F21: =+F247+F360+F473+F586+F613+F640 -> -663.8934 | G21: =+G247+G360+G473+G586+G613+G640 -> -120.26499 | H21: =+H247+H360+H473+H586+H613+H640 -> 969.6427 | I21: =+I247+I360+I473+I586+I613+I640 -> -287.6962 | J21: =+J247+J360+J473+J586+J613+J640 -> 841.7825 | K21: =+K247+K360+K473+K586+K613+K640 -> -863.7379 | L21: =+L247+L360+L473+L586+L613 -> -491.315 | M21: =+M247+M360+M473+M586+M613 -> 1091.2471 | N21: =+N247+N360+N473+N586+N613 -> 570.77867 | O21: =+O247+O360+O473+O586+O613 -> 1662.0258 | P21: =+P247+P360+P473+P586+P613 -> -493.5237 | Q21: =+Q247+Q360+Q473+Q586+Q613 -> -65.624038 | R21: =+R247+R360+R473+R586+R613 -> -559.14774 | S21: =+S247+S360+S473+S586+S613 -> 220.5607 | ... X21: =+X247+X360+X473+X586+X613 -> -691.1573 | Y21: =+Y247+Y360+Y473+Y586 -> -303.4753 | Z21: =+Z247+Z360+Z473+Z586+Z613 -> -532.7854 | AA21: =+AA247+AA360+AA473+AA586+AA613 -> -365.502 | AB21: =+AB247+AB360+AB473+AB586+AB613 -> -79.2115 | AC21: =+AC247+AC360+AC473+AC586+AC613 -> -72.88997 | AD21: =+AD247+AD360+AD473+AD586+AD613 -> -898.2874 | AE21: =+AE247+AE360+AE473+AE586+AE613 -> -152.10147 | AF21: =+AF247+AF360+AF473+AF586 -> -1050.3889 | AG21: =+AG247+AG360+AG473+AG586+AG613 -> 247.3859 | AH21: =+AH247+AH360+AH473+AH586+AH613 -> 195.305 | AI21: =+AI247+AI360+AI473+AI586+AI613 -> 207.4552 | AJ21: =+AJ247+AJ360+AJ473+AJ586+AJ613 -> -32.54574 | AK21: =+AK247+AK360+AK473+AK586+AK613 -> 442.6909 | AL21: =+AL247+AL360+AL473+AL586+AL613 -> 174.90946 | AM21: =+AM247+AM360+AM473+AM586 -> 617.60036 | AN21: =+AN247+AN360+AN473+AN586+AN613 -> 47.31256 | AO21: =+AO247+AO360+AO473+AO586+AO613 -> -116.42248 | AP21: =+AP247+AP360+AP473+AP586+AP613 -> -260.0364 | AQ21: =+AQ247+AQ360+AQ473+AQ586+AQ613 -> -487.44568 | AR21: =+AR247+AR360+AR473+AR586+AR613 -> -69.10992 | AS21: =+AS247+AS360+AS473+AS586+AS613 -> -747.48208 | AT21: =+AT247+AT360+AT473+AT586 -> -816.592 | AU21: =+AU247+AU360+AU473+AU586 -> -438.1789 | AV21: =+AV247+AV360+AV473+AV586+AV613 -> -291.9229 | AW21: =+AW247+AW360+AW473+AW586 -> 12.7113 | AX21: =+AX247+AX360+AX473+AX586+AX613 -> 342.79954 | AY21: =+AY247+AY360+AY473+AY586 -> -730.1018 | AZ21: =+AZ247+AZ360+AZ473+AZ586+AZ613 -> 355.51084 | BA21: =+BA247+BA360+BA473+BA586 -> -374.59096 | BB21: =+BB247+BB360+BB473+BB586 -> 391.5121 | BC21: =+BC247+BC360+BC473+BC586+BC613 -> 684.8994 | BD21: =+BD247+BD360+BD473+BD586 -> 819.1266 | BE21: =+BE247+BE360+BE473+BE586+BE613 -> 436.3391 | BF21: =+BF247+BF360+BF473+BF586 -> 1076.4115 | BG21: =+BG247+BG360+BG473+BG586+BG613 -> 1255.4657 | BH21: =+BH247+BH360+BH473+BH586 -> 2331.8772 | BI21: =+BI247+BI360+BI473+BI586 -> 116.25168 | BJ21: =+BJ247+BJ360+BJ473+BJ586+BJ613 -> -409.90108 | BK21: =+BK247+BK360+BK473+BK586 -> -765.17462 | BL21: =+BL247+BL360+BL473+BL586+BL613 -> -852.26908 | BM21: =+BM247+BM360+BM473+BM586 -> -293.6494 | BN21: =+BN247+BN360+BN473+BN586+BN613 -> -1617.4437 | BO21: =+BO247+BO360+BO473+BO586 -> -1911.0931 | BP21: =+BP247+BP360+BP473+BP586 -> -365.54515 | BQ21: =+BQ247+BQ360+BQ473+BQ586 -> -126.69771 | BR21: =+BR247+BR360+BR473+BR586 -> -163.63275 | BS21: =+BS247+BS360+BS473+BS586+BS613 -> 166.82973 | BT21: =+BT247+BT360+BT473+BT586 -> -492.24286 | BU21: =+BU247+BU360+BU473+BU586+BU613 -> 3.196977 | BV21: =+BV247+BV360+BV473+BV586 -> -489.04588 | BW21: =+BW247+BW360+BW473+BW586 -> 43.2495 | BX21: =+BX247+BX360+BX473+BX586 -> -448.11507 | BY21: =+BY247+BY360+BY473+BY586 -> -488.5577 | BZ21: =+BZ247+BZ360+BZ473+BZ586+BZ613 -> -703.41146 | CA21: =+CA247+CA360+CA473+CA586 -> -404.86557 | CB21: =+CB247+CB360+CB473+CB586+CB613 -> -1191.9692 | CC21: =+CC247+CC360+CC473+CC586 -> -1596.8347 | CD21: =+CD247+CD360+CD473+CD586 -> -639.01017 | CE21: =+CE247+CE360+CE473+CE586 -> -57.604712 | CF21: =+CF247+CF360+CF473+CF586 -> 107.975 | CG21: =+CG247+CG360+CG473+CG586+CG613 -> 125.79165 | CH21: =+CH247+CH360+CH473+CH586 -> -696.61488 | CI21: =+CI247+CI360+CI473+CI586+CI613 -> 233.76665 | CJ21: =+CJ247+CJ360+CJ473+CJ586 -> -462.84823 | CK21: =+CK247+CK360+CK473+CK586 -> -170.62024 | CL21: =+CL247+CL360+CL473+CL586 -> -179.29662 | CM21: =+CM247+CM360+CM473+CM586 -> -176.29697 | CN21: =+CN247+CN360+CN473+CN586 -> -185.53915 | CO21: =+CO247+CO360+CO473+CO586 -> -195.29694 | CP21: =+CP247+CP360+CP473+CP586 -> -205.60053 | CQ21: =+CQ247+CQ360+CQ473+CQ586 -> -216.48192 | ... CS21: =+CS247+CS360+CS473+CS586 -> -240.11605
A22: group structure impact | B22: EURm | C22: =+C248+C361+C474+C587+C614+C641 -> 0 | D22: =+D248+D361+D474+D587+D614+D641 -> 0 | E22: =+E248+E361+E474+E587+E614+E641 -> 529.74592 | F22: =+F248+F361+F474+F587+F614+F641 -> 578.2221 | G22: =+G248+G361+G474+G587+G614+G641 -> 283.5328 | H22: =+H248+H361+H474+H587+H614+H641 -> 71.655 | I22: =+I248+I361+I474+I587+I614+I641 -> 142.1967 | J22: =+J248+J361+J474+J587+J614+J641 -> 166.9111 | K22: =+K248+K361+K474+K587+K614+K641 -> 250.6336 | L22: =+L248+L361+L474+L587+L614 -> 52.4142 | M22: =+M248+M361+M474+M587+M614 -> 130.819 | N22: =+N248+N361+N474+N587+N614 -> 60.54723 | O22: =+O248+O361+O474+O587+O614 -> 191.36623 | P22: =+P248+P361+P474+P587+P614 -> 28.1318 | Q22: =+Q248+Q361+Q474+Q587+Q614 -> -79.925762 | R22: =+R248+R361+R474+R587+R614 -> -51.793962 | S22: =+S248+S361+S474+S587+S614 -> 0 | ... X22: =+X248+X361+X474+X587+X614 -> 227.16856 | Y22: =+Y248+Y361+Y474+Y587 -> 227.16856 | Z22: =+Z248+Z361+Z474+Z587+Z614 -> 0 | AA22: =+AA248+AA361+AA474+AA587+AA614 -> 0 | AB22: =+AB248+AB361+AB474+AB587+AB614 -> 0 | AC22: =+AC248+AC361+AC474+AC587+AC614 -> 126.32347 | AD22: =+AD248+AD361+AD474+AD587+AD614 -> 0 | AE22: =+AE248+AE361+AE474+AE587+AE614 -> 126.32347 | AF22: =+AF248+AF361+AF474+AF587 -> 126.32347 | AG22: =+AG248+AG361+AG474+AG587+AG614 -> 0 | AH22: =+AH248+AH361+AH474+AH587+AH614 -> 0 | AI22: =+AI248+AI361+AI474+AI587+AI614 -> 0 | AJ22: =+AJ248+AJ361+AJ474+AJ587+AJ614 -> 171.76094 | AK22: =+AK248+AK361+AK474+AK587+AK614 -> 0 | AL22: =+AL248+AL361+AL474+AL587+AL614 -> 171.76094 | AM22: =+AM248+AM361+AM474+AM587 -> 171.76094 | AN22: =+AN248+AN361+AN474+AN587+AN614 -> -13.398 | AO22: =+AO248+AO361+AO474+AO587+AO614 -> 64.899 | AP22: =+AP248+AP361+AP474+AP587+AP614 -> -11.0076 | AQ22: =+AQ248+AQ361+AQ474+AQ587+AQ614 -> 102.7666 | AR22: =+AR248+AR361+AR474+AR587+AR614 -> 51.501 | AS22: =+AS248+AS361+AS474+AS587+AS614 -> 91.759 | AT22: =+AT248+AT361+AT474+AT587 -> 143.26 | AU22: =+AU248+AU361+AU474+AU587 -> 91.1828 | AV22: =+AV248+AV361+AV474+AV587+AV614 -> 45.8172 | AW22: =+AW248+AW361+AW474+AW587 -> 24 | AX22: =+AX248+AX361+AX474+AX587+AX614 -> 0 | AY22: =+AY248+AY361+AY474+AY587 -> 137 | AZ22: =+AZ248+AZ361+AZ474+AZ587+AZ614 -> 24 | BA22: =+BA248+BA361+BA474+BA587 -> 161 | BB22: =+BB248+BB361+BB474+BB587 -> 30 | BC22: =+BC248+BC361+BC474+BC587+BC614 -> 20 | BD22: =+BD248+BD361+BD474+BD587 -> 30 | BE22: =+BE248+BE361+BE474+BE587+BE614 -> 45 | BF22: =+BF248+BF361+BF474+BF587 -> 50 | BG22: =+BG248+BG361+BG474+BG587+BG614 -> 75 | BH22: =+BH248+BH361+BH474+BH587 -> 125 | BI22: =+BI248+BI361+BI474+BI587 -> 30 | BJ22: =+BJ248+BJ361+BJ474+BJ587+BJ614 -> 30 | BK22: =+BK248+BK361+BK474+BK587 -> 135 | BL22: =+BL248+BL361+BL474+BL587+BL614 -> 417 | BM22: =+BM248+BM361+BM474+BM587 -> 60 | BN22: =+BN248+BN361+BN474+BN587+BN614 -> 552 | BO22: =+BO248+BO361+BO474+BO587 -> 612 | BP22: =+BP248+BP361+BP474+BP587 -> 250 | BQ22: =+BQ248+BQ361+BQ474+BQ587 -> 270 | BR22: =+BR248+BR361+BR474+BR587 -> 112 | BS22: =+BS248+BS361+BS474+BS587+BS614 -> 48 | BT22: =+BT248+BT361+BT474+BT587 -> 520 | BU22: =+BU248+BU361+BU474+BU587+BU614 -> 160 | BV22: =+BV248+BV361+BV474+BV587 -> 680 | BW22: =+BW248+BW361+BW474+BW587 -> 55 | BX22: =+BX248+BX361+BX474+BX587 -> 45 | BY22: =+BY248+BY361+BY474+BY587 -> 109 | BZ22: =+BZ248+BZ361+BZ474+BZ587+BZ614 -> 131 | CA22: =+CA248+CA361+CA474+CA587 -> 100 | CB22: =+CB248+CB361+CB474+CB587+CB614 -> 240 | CC22: =+CC248+CC361+CC474+CC587 -> 340 | CD22: =+CD248+CD361+CD474+CD587 -> 75 | CE22: =+CE248+CE361+CE474+CE587 -> 75 | CF22: =+CF248+CF361+CF474+CF587 -> 75 | CG22: =+CG248+CG361+CG474+CG587+CG614 -> 55 | CH22: =+CH248+CH361+CH474+CH587 -> 150 | CI22: =+CI248+CI361+CI474+CI587+CI614 -> 130 | CJ22: =+CJ248+CJ361+CJ474+CJ587 -> 280 | CK22: =+CK248+CK361+CK474+CK587 -> 0 | CL22: =+CL248+CL361+CL474+CL587 -> 0 | CM22: =+CM248+CM361+CM474+CM587 -> 0 | CN22: =+CN248+CN361+CN474+CN587 -> 0 | CO22: =+CO248+CO361+CO474+CO587 -> 0 | CP22: =+CP248+CP361+CP474+CP587 -> 0 | CQ22: =+CQ248+CQ361+CQ474+CQ587 -> 0 | ... CS22: =+CS248+CS361+CS474+CS587 -> 0
A23: Professional Products | B23: EURm | C23: =+C238 -> 2061 | D23: =+D238 -> 2126.952 | E23: =+E238 -> 2392.821 | F23: =+F238 -> 2471.7 | G23: =+G238 -> 2388.5 | H23: =+H238 -> 2717 | I23: =+I238 -> 2813.8 | J23: =+J238 -> 3002.6 | ... CS23: =+CS238 -> 9427.4202
A24: Consumer Products | B24: EURm | C24: =+C351 -> 7499 | D24: =+D351 -> 7903.1961 | E24: =+E351 -> 8280.5737 | F24: =+F351 -> 8354.9 | G24: =+G351 -> 8555.2 | H24: =+H351 -> 9529.9 | I24: =+I351 -> 9835.2 | J24: =+J351 -> 10713.2 | ... CS24: =+CS351 -> 22680.946
A25: Luxury Products | B25: EURm | C25: =+C464 -> 3582 | D25: =+D464 -> 3772.5624 | E25: =+E464 -> 3927.2375 | F25: =+F464 -> 4169.6 | G25: 4080 | H25: =+H464 -> 4506.6 | I25: =+I464 -> 4800.1 | J25: =+J464 -> 5568.1 | K25: =+K464 -> 5865.2 | L25: =+L464 -> 6197.9 | M25: =+M464 -> 3486.6 | N25: =+N464 -> 3743.4 | O25: =+O464 -> 7230 | ... CS25: =+CS464 -> 29055.081
A26: Dermatological Beauty | B26: EURm | C26: =+C577 -> 985.9 | D26: =+D577 -> 1127.9 | E26: =+E577 -> 1248.1 | F26: =+F577 -> 1289 | G26: =+G577 -> 1233.8601 | H26: =+H577 -> 1385.6 | I26: =+I577 -> 1421.7 | J26: =+J577 -> 1528 | ... CS26: =+CS577 -> 12298.547
A27: Other Cosmetics Sales | B27: EURm | C27: =14215-SUM(C23:C26) -> 87.1 | D27: 81 | E27: 60 | F27: 73
A28: The Body Shop | B28: EURm | C28: =+C604 -> 0 | D28: =+D604 -> 435 | E28: =+E604 -> 786.9 | F28: =+F604 -> 756 | G28: =+G604 -> 726.81103 | H28: =+H604 -> 754.9 | I28: =+I604 -> 767.6 | J28: =+J604 -> 855.3 | ... S28: =+S604 -> 197.2
A29: Galderma | B29: EURm | C29: =+C631 -> 317.8 | D29: =+D631 -> 343.7 | E29: =+E631 -> 367.5 | F29: =+F631 -> 427 | G29: =+G631 -> 489.69638 | H29: =+H631 -> 601.7 | I29: =+I631 -> 704.7 | J29: =+J631 -> 795.5 | K29: =+K631 -> 826.3
A31: Cost of good sold - NOT A DRIVER | B31: EURm | C31: -4347 | D31: -4569 | E31: -4941 | F31: -5240 | G31: -5162 | H31: -5696.5 | I31: -5851.5 | J31: -6587.7 | K31: -6601.8 | L31: -6500.7 | M31: -3630.3 | N31: =+O31-M31 -> -3647.1 | O31: -7277.4 | P31: -3561.2 | Q31: =+R31-P31 -> -3780.5 | R31: -7341.7 | W31: -3780.5 | X31: =+Y31-W31 -> -3578.7 | Y31: -7359.2 | AD31: -3598.3 | AE31: =+AF31-AD31 -> -3733.3 | AF31: -7331.6 | AK31: -3988.5 | AL31: =+AM31-AK31 -> -4076.2 | AM31: -8064.7 | AR31: -3512.3 | AS31: =AT31-AR31 -> -4020 | AT31: -7532.3 | AY31: -3869.5 | AZ31: =BA31-AY31 -> -4563.8 | BA31: -8433.3 | BF31: -4935.8 | BG31: =BH31-BF31 -> -5641.6 | BH31: -10577.4 | BM31: -5291.5 | BN31: =BO31-BM31 -> -5475.5 | BO31: -10767 | BT31: -5568.7 | BU31: =BV31-BT31 -> -5658.3 | BV31: -11227 | CA31: -5692.6 | CB31: =CC31-CA31 -> -5675.0508 | CC31: =CC33-CC10 -> -11367.651 | CH31: -5692.6 | CI31: =CJ31-CH31 -> -6146.5472 | CJ31: =CJ33-CJ10 -> -11839.147 | CK31: =CK33-CK10 -> -12296.809 | CL31: =CL33-CL10 -> -12793.603 | CM31: =CM33-CM10 -> -13313.637 | CN31: =CN33-CN10 -> -13854.902 | CO31: =CO33-CO10 -> -14418.206 | CP31: =CP33-CP10 -> -15004.381 | CQ31: =CQ33-CQ10 -> -15614.278 | ... CS31: =CS33-CS10 -> -16908.769
A32: - as % of sales | B32: % | C32: =-C31/C10 -> 0.29911648 | D32: =-D31/D10 -> 0.28935466 | E32: =-E31/E10 -> 0.28957169 | F32: =-F31/F10 -> 0.29872529 | G32: =-G31/G10 -> 0.29540918 | H32: =-H31/H10 -> 0.29219114 | I32: =-I31/I10 -> 0.28764053 | J32: =-J31/J10 -> 0.29327285 | ... R32: =-R31/R10 -> 0.28415341 | W32: =-W31/W10 -> 0.28187654 | X32: =-X31/X10 -> 0.28375807 | Y32: =-Y31/Y10 -> 0.28278838 | AD32: =-AD31/AD10 -> 0.26871635 | AE32: =-AE31/AE10 -> 0.27558741 | AF32: =-AF31/AF10 -> 0.27217178 | AK32: =-AK31/AK10 -> 0.269284 | AL32: =-AL31/AL10 -> 0.27062627 | AM32: =-AM31/AM10 -> 0.26996077 | AR32: =-AR31/AR10 -> 0.26859634 | AS32: =-AS31/AS10 -> 0.26952371 | AT32: =-AT31/AT10 -> 0.26908664 | AY32: =-AY31/AY10 -> 0.25462765 | AZ32: =-AZ31/AZ10 -> 0.26703754 | BA32: =-BA31/BA10 -> 0.26119654 | BF32: =-BF31/BF10 -> 0.26874221 | BG32: =-BG31/BG10 -> 0.28357729 | BH32: =-BH31/BH10 -> 0.276456 | BM32: =-BM31/BM10 -> 0.2571923 | BN32: =-BN31/BN10 -> 0.26569134 | BO32: =-BO31/BO10 -> 0.26144537 | BT32: =-BT31/BT10 -> 0.25174044 | BU32: =-BU31/BU10 -> 0.26482606 | BV32: =-BV31/BV10 -> 0.2581703 | CA32: =-CA31/CA10 -> 0.25330391 | CB32: =-CB31/CB10 -> 0.26324328 | CC32: =-CC31/CC10 -> 0.2581703 | CH32: =-CH31/CH10 -> 0.24560888 | CI32: =-CI31/CI10 -> 0.26889294 | CJ32: =-CJ31/CJ10 -> 0.2571703 | CK32: =-CK31/CK10 -> 0.2541703 | CL32: =-CL31/CL10 -> 0.2511703 | CM32: =-CM31/CM10 -> 0.2481703 | CN32: =-CN31/CN10 -> 0.2451703 | CO32: =-CO31/CO10 -> 0.2421703 | ... CS32: =-CS31/CS10 -> 0.2301703
A33: Gross profit | B33: EURm | C33: =+C10+C31 -> 10185.8 | D33: =+D10+D31 -> 11221.31 | E33: =+E10+E31 -> 12122.132 | F33: =+F10+F31 -> 12301.2 | G33: =+G10+G31 -> 12312.068 | H33: =+H10+H31 -> 13799.3 | I33: =+I10+I31 -> 14491.6 | J33: =+J10+J31 -> 15875 | ... R33: =+R10+R31 -> 18495.4 | W33: =+W10+W31 -> 9631.4 | X33: =+X10+X31 -> 9033.1 | Y33: =+Y10+Y31 -> 18664.5 | AD33: =+AD10+AD31 -> 9792.4 | AE33: =+AE10+AE31 -> 9813.4 | AF33: =+AF10+AF31 -> 19605.8 | AK33: =+AK10+AK31 -> 10823 | AL33: =+AL10+AL31 -> 10985.9 | AM33: =+AM10+AM31 -> 21808.9 | AR33: =+AR10+AR31 -> 9564.2 | AS33: =AS10+AS31 -> 10895.2 | AT33: =+AT10+AT31 -> 20459.8 | AY33: =+AY10+AY31 -> 11327.2 | AZ33: =BA33-AY33 -> 12526.681 | BA33: =+BA10+BA31 -> 23853.881 | BF33: =+BF10+BF31 -> 13430.5 | BG33: =BH33-BF33 -> 14252.8 | BH33: =+BH10+BH31 -> 27683.3 | BM33: =+BM10+BM31 -> 15282.6 | BN33: =BO33-BM33 -> 15133 | BO33: =+BO10+BO31 -> 30415.6 | BT33: =+BT10+BT31 -> 16552.1 | BU33: =BV33-BT33 -> 15707.7 | BV33: =+BV10+BV31 -> 32259.8 | CA33: =+CA10+CA31 -> 16780.8 | CB33: =CC33-CA33 -> 15883.148 | CC33: =CC34*CC10 -> 32663.948 | CH33: =+CH10+CH31 -> 17484.901 | CI33: =CJ33-CH33 -> 16712.168 | CJ33: =CJ34*CJ10 -> 34197.069 | CK33: =CK34*CK10 -> 36083.389 | CL33: =CL34*CL10 -> 38142.369 | CM33: =CM34*CM10 -> 40333.545 | CN33: =CN34*CN10 -> 42656.439 | CO33: =CO34*CO10 -> 45119.262 | CP33: =CP34*CP10 -> 47730.753 | CQ33: =CQ34*CQ10 -> 50500.209 | ... CS33: =CS34*CS10 -> 56553.224
A34: - gross margin | B34: % | C34: =+C33/C10 -> 0.70088352 | D34: =+D33/D10 -> 0.71064534 | E34: =+E33/E10 -> 0.71042831 | F34: =+F33/F10 -> 0.70127471 | G34: =+G33/G10 -> 0.70459082 | H34: =+H33/H10 -> 0.70780886 | I34: =+I33/I10 -> 0.71235947 | J34: =+J33/J10 -> 0.70672715 | ... R34: =+R33/R10 -> 0.71584659 | W34: =+W33/W10 -> 0.71812346 | X34: =+X33/X10 -> 0.71624193 | Y34: =+Y33/Y10 -> 0.71721162 | AD34: =+AD33/AD10 -> 0.73128365 | AE34: =+AE33/AE10 -> 0.72441259 | AF34: =+AF33/AF10 -> 0.72782822 | AK34: =+AK33/AK10 -> 0.730716 | AL34: =+AL33/AL10 -> 0.72937373 | AM34: =+AM33/AM10 -> 0.73003923 | AR34: =+AR33/AR10 -> 0.73140366 | AS34: =+AS33/AS10 -> 0.73047629 | AT34: =+AT33/AT10 -> 0.73091336 | AY34: =+AY33/AY10 -> 0.74537235 | AZ34: =+AZ33/AZ10 -> 0.73296246 | BA34: =+BA33/BA10 -> 0.73880346 | BF34: =+BF33/BF10 -> 0.73125779 | BG34: =+BG33/BG10 -> 0.71642271 | BH34: =+BH33/BH10 -> 0.723544 | BM34: =+BM33/BM10 -> 0.7428077 | BN34: =+BN33/BN10 -> 0.73430866 | BO34: =+BO33/BO10 -> 0.73855463 | BT34: =+BT33/BT10 -> 0.74825956 | BU34: =+BU33/BU10 -> 0.73516926 | BV34: =+BV33/BV10 -> 0.7418297 | CA34: =+CA33/CA10 -> 0.74669609 | CB34: =+CB33/CB10 -> 0.73675672 | CC34: =BV34+CC35/10000 -> 0.7418297 | CH34: =+CH33/CH10 -> 0.75439112 | CI34: =+CI33/CI10 -> 0.73110706 | CJ34: =CC34+CJ35/10000 -> 0.7428297 | CK34: =CJ34+CK35/10000 -> 0.7458297 | CL34: =CK34+CL35/10000 -> 0.7488297 | CM34: =CL34+CM35/10000 -> 0.7518297 | CN34: =CM34+CN35/10000 -> 0.7548297 | CO34: =CN34+CO35/10000 -> 0.7578297 | CP34: =CO34+CP35/10000 -> 0.7608297 | CQ34: =CP34+CQ35/10000 -> 0.7638297 | CR34: =CQ34+CR35/10000 -> 0.7668297 | CS34: =CR34+CS35/10000 -> 0.7698297
A35: - gross margin progression | B35: bps | C35: - | D35: =(D34-C34)*10000 -> 97.618167 | E35: =(E34-D34)*10000 -> -2.1702416 | F35: =(F34-E34)*10000 -> -91.535979 | G35: =(G34-F34)*10000 -> 33.161041 | H35: =(H34-G34)*10000 -> 32.180441 | I35: =(I34-H34)*10000 -> 45.506118 | J35: =(J34-I34)*10000 -> -56.323211 | K35: =(K34-J34)*10000 -> 59.457412 | L35: =(L34-K34)*10000 -> -11.825684 | M35: =(M34-(9333/12895))*10000 -> -69.679291 | N35: - | O35: =(O34-L34)*10000 -> 3.8025563 | P35: =(P34-(9333/12895))*10000 -> 0.52187491 | Q35: - | R35: =(R34-O34)*10000 -> 39.760122 | W35: =(W34-(9333/12895))*10000 -> -56.454451 | X35: - | Y35: =(Y34-R34)*10000 -> 13.650259 | AD35: =(AD34-W34)*10000 -> 131.60195 | AE35: =(AE34-X34)*10000 -> 81.706554 | AF35: =(AF34-Y34)*10000 -> 106.16605 | AK35: =(AK34-AD34)*10000 -> -5.6765438 | AL35: =(AL34-AE34)*10000 -> 49.611385 | AM35: =(AM34-AF34)*10000 -> 22.11008 | AR35: =(AR34-AK34)*10000 -> 6.8766536 | AS35: =(AS34-AL34)*10000 -> 11.025665 | AT35: =(AT34-AM34)*10000 -> 8.7413288 | AY35: =(AY34-AR34)*10000 -> 139.68688 | AZ35: =(AZ34-AS34)*10000 -> 24.861697 | BA35: =(BA34-AT34)*10000 -> 78.900951 | BF35: =(BF34-AY34)*10000 -> -141.14558 | BG35: =(BG34-AZ34)*10000 -> -165.3975 | BH35: =(BH34-BA34)*10000 -> -152.59458 | BM35: =(BM34-BF34)*10000 -> 115.49912 | BN35: =(BN34-BG34)*10000 -> 178.85947 | BO35: =(BO34-BH34)*10000 -> 150.1063 | BT35: =(BT34-BM34)*10000 -> 54.518518 | BU35: =(BU34-BN34)*10000 -> 8.6060441 | BV35: =(BV34-BO34)*10000 -> 32.750723 | CA35: =(CA34-BT34)*10000 -> -15.634626 | CB35: =(CB34-BU34)*10000 -> 15.87461 | CC35: 0 | CH35: =(CH34-CA34)*10000 -> 76.950245 | CI35: =(CI34-CB34)*10000 -> -56.496681 | CJ35: 10 | CK35: 30 | CL35: =CK35 -> 30 | CM35: =CL35 -> 30 | CN35: =CM35 -> 30 | CO35: =CN35 -> 30 | CP35: =CO35 -> 30 | CQ35: =CP35 -> 30 | CR35: =CQ35 -> 30 | CS35: =CR35 -> 30
A37: Research and innovation expenses | B37: EURm | C37: -496 | D37: -533 | E37: -560 | F37: -581 | G37: -609 | H37: -664.7 | I37: -720.5 | J37: -790.5 | K37: -857 | L37: -760.6 | M37: -379.7 | N37: =+O37-M37 -> -414.4 | O37: -794.1 | P37: -414.2 | Q37: =+R37-P37 -> -435.6 | R37: -849.8 | W37: -425.1 | X37: =+Y37-W37 -> -452 | Y37: -877.1 | AD37: -447.2 | AE37: =+AF37-AD37 -> -467.2 | AF37: -914.4 | AK37: -459.7 | AL37: =+AM37-AK37 -> -525.6 | AM37: -985.3 | AR37: -455.3 | AS37: =AT37-AR37 -> -509.1 | AT37: -964.4 | AY37: -489.1 | AZ37: =BA37-AY37 -> -539.6 | BA37: -1028.7 | BF37: -539.6 | BG37: =BH37-BF37 -> -599 | BH37: -1138.6 | BM37: -622.8 | BN37: =BO37-BM37 -> -666.1 | BO37: -1288.9 | BT37: -667.3 | BU37: =BV37-BT37 -> -687.4 | BV37: -1354.7 | CA37: -671.7 | CB37: =CC37-CA37 -> -693.27956 | CC37: =-CC39*CC10 -> -1364.9796 | CH37: -671.7 | CI37: =CJ37-CH37 -> -755.42269 | CJ37: =-CJ39*CJ10 -> -1427.1227 | CK37: =-CK39*CK10 -> -1499.7861 | CL37: =-CL39*CL10 -> -1579.0152 | CM37: =-CM39*CM10 -> -1663.0626 | CN37: =-CN39*CN10 -> -1751.8516 | CO37: =-CO39*CO10 -> -1845.6615 | CP37: =-CP39*CP10 -> -1944.7892 | CQ37: =-CQ39*CQ10 -> -2049.5491 | ... CS37: =-CS39*CS10 -> -2277.3218
A38: - reported growth | B38: % | C38: - | D38: =+D37/C37-1 -> 0.074596774 | E38: =+E37/D37-1 -> 0.05065666 | F38: =+F37/E37-1 -> 0.0375 | G38: =+G37/F37-1 -> 0.048192771 | H38: =+H37/G37-1 -> 0.091461412 | I38: =+I37/H37-1 -> 0.083947646 | J38: =+J37/I37-1 -> 0.097154754 | K38: =+K37/J37-1 -> 0.084123972 | L38: =+L37/K37-1 -> -0.11248541 | M38: =+M37/-414.2-1 -> -0.083293095 | N38: - | O38: =+O37/L37-1 -> 0.044044176 | P38: =+P37/-414.2-1 -> 0 | Q38: - | R38: =+R37/O37-1 -> 0.070142299 | W38: =+W37/-414.2-1 -> 0.026315789 | X38: - | Y38: =+Y37/R37-1 -> 0.032125206 | AD38: =+AD37/W37-1 -> 0.051987768 | AE38: =+AE37/X37-1 -> 0.033628319 | AF38: =+AF37/Y37-1 -> 0.042526508 | AK38: =+AK37/AD37-1 -> 0.027951699 | AL38: =+AL37/AE37-1 -> 0.125 | AM38: =+AM37/AF37-1 -> 0.077537183 | AR38: =+AR37/AK37-1 -> -0.0095714596 | AS38: =+AS37/AL37-1 -> -0.031392694 | AT38: =+AT37/AM37-1 -> -0.021211814 | AY38: =+AY37/AR37-1 -> 0.074236767 | AZ38: =+AZ37/AS37-1 -> 0.059909644 | BA38: =+BA37/AT37-1 -> 0.066673579 | BF38: =+BF37/AY37-1 -> 0.10325087 | BG38: =+BG37/AZ37-1 -> 0.11008154 | BH38: =+BH37/BA37-1 -> 0.10683387 | BM38: =+BM37/BF37-1 -> 0.15418829 | BN38: =+BN37/BG37-1 -> 0.11202003 | BO38: =+BO37/BH37-1 -> 0.13200422 | BT38: =+BT37/BM37-1 -> 0.071451509 | BU38: =+BU37/BN37-1 -> 0.031977181 | BV38: =+BV37/BO37-1 -> 0.051051284 | CA38: =+CA37/BT37-1 -> 0.006593736 | CB38: =+CB37/BU37-1 -> 0.0085533297 | CC38: =+CC37/BV37-1 -> 0.0075880703 | CH38: =+CH37/CA37-1 -> 0 | CI38: =+CI37/CB37-1 -> 0.089636464 | CJ38: =+CJ37/CC37-1 -> 0.045526783 | CK38: =+CK37/CJ37-1 -> 0.050916042 | CL38: =+CL37/CK37-1 -> 0.052826884 | CM38: =+CM37/CL37-1 -> 0.053227782 | CN38: =+CN37/CM37-1 -> 0.053388809 | CO38: =+CO37/CN37-1 -> 0.053549043 | CP38: =+CP37/CO37-1 -> 0.053708449 | CQ38: =+CQ37/CP37-1 -> 0.053866988 | CR38: =+CR37/CQ37-1 -> 0.054024626 | CS38: =+CS37/CR37-1 -> 0.054181326
A39: - as % of sales | B39: % | C39: =-C37/C$10 -> 0.034129693 | D39: =-D37/D$10 -> 0.033754878 | E39: =-E37/E$10 -> 0.032819297 | F39: =-F37/F$10 -> 0.033122021 | G39: =-G37/G$10 -> 0.034851645 | H39: =-H37/H$10 -> 0.034094523 | I39: =-I37/I$10 -> 0.035417414 | J39: =-J37/J$10 -> 0.035191673 | ... R39: =-R37/R$10 -> 0.032890688 | W39: =-W37/W$10 -> 0.031695733 | X39: =-X37/X$10 -> 0.035839452 | Y39: =-Y37/Y$10 -> 0.033703893 | AD39: =-AD37/AD$10 -> 0.033396312 | AE39: =-AE37/AE$10 -> 0.034488104 | AF39: =-AF37/AF$10 -> 0.03394537 | AK39: =-AK37/AK$10 -> 0.031036694 | AL39: =-AL37/AL$10 -> 0.034895532 | AM39: =-AM37/AM$10 -> 0.032982299 | AR39: =-AR37/AR$10 -> 0.034818185 | AS39: =-AS37/AS$10 -> 0.034132965 | AT39: =-AT37/AT$10 -> 0.034452578 | AY39: =-AY37/AY$10 -> 0.032184619 | AZ39: =-AZ37/AZ$10 -> 0.031573131 | BA39: =-BA37/BA$10 -> 0.031860942 | BF39: =-BF37/BF$10 -> 0.029379897 | BG39: =-BG37/BG$10 -> 0.030108975 | BH39: =-BH37/BH$10 -> 0.029758996 | BM39: =-BM37/BM$10 -> 0.030271069 | BN39: =-BN37/BN$10 -> 0.032321615 | BO39: =-BO37/BO$10 -> 0.031297198 | BT39: =-BT37/BT$10 -> 0.030166178 | BU39: =-BU37/BU$10 -> 0.03217246 | BV39: =-BV37/BV$10 -> 0.031151982 | CA39: =-CA37/CA$10 -> 0.029888668 | CB39: =-CB37/CB$10 -> 0.032158511 | CC39: 0.031 | CH39: =-CH37/CH$10 -> 0.028980692 | CI39: =-CI37/CI$10 -> 0.033047469 | CJ39: 0.031 | CK39: 0.031 | CL39: =CK39 -> 0.031 | CM39: =CL39 -> 0.031 | CN39: =CM39 -> 0.031 | CO39: =CN39 -> 0.031 | CP39: =CO39 -> 0.031 | CQ39: =CP39 -> 0.031 | CR39: =CQ39 -> 0.031 | CS39: =CR39 -> 0.031
A41: Advertising and promotion expenses | B41: EURm | C41: -4367 | D41: -4783 | E41: -5127 | F41: -5275 | G41: -5389 | H41: -6029.1 | I41: -6291.6 | J41: -6776.3 | K41: -6886.2 | L41: -6558.9 | M41: -3753.3 | N41: =+O41-M41 -> -3606.3 | O41: -7359.6 | P41: -3790.9 | Q41: =+R41-P41 -> -3707.8 | R41: -7498.7 | W41: -3913.5 | X41: =+Y41-W41 -> -3737.1 | Y41: -7650.6 | AD41: -4018.3 | AE41: =+AF41-AD41 -> -4126.4 | AF41: -8144.7 | AK41: -4471.7 | AL41: =+AM41-AK41 -> -4736.1 | AM41: -9207.8 | AR41: -3986.5 | AS41: =AT41-AR41 -> -4661.4 | AT41: -8647.9 | AY41: -4951.6 | AZ41: =BA41-AY41 -> -5639.4 | BA41: -10591 | BF41: -5793.3 | BG41: =BH41-BF41 -> -6265.7 | BH41: -12059 | BM41: -6682.6 | BN41: =BO41-BM41 -> -6674 | BO41: -13356.6 | BT41: -7109.1 | BU41: =BV41-BT41 -> -6899.8 | BV41: -14008.9 | CA41: -7177 | CB41: =CC41-CA41 -> -6913.1116 | CC41: =-CC43*CC10 -> -14090.112 | CH41: -7177 | CI41: =CJ41-CH41 -> -7462.5166 | CJ41: =-CJ43*CJ10 -> -14639.517 | CK41: =-CK43*CK10 -> -15336.523 | CL41: =-CL43*CL10 -> -16146.703 | CM41: =-CM43*CM10 -> -17006.157 | CN41: =-CN43*CN10 -> -17914.095 | CO41: =-CO43*CO10 -> -18873.378 | CP41: =-CP43*CP10 -> -19887.037 | CQ41: =-CQ43*CQ10 -> -20958.292 | ... CS41: =-CS43*CS10 -> -23287.452
A42: - reported growth | B42: % | C42: - | D42: - | E42: - | F42: - | G42: - | H42: - | I42: =+I41/H41-1 -> 0.043538837 | J42: =+J41/I41-1 -> 0.077039227 | K42: =+K41/J41-1 -> 0.01621829 | L42: =+L41/K41-1 -> -0.047529842 | M42: =+M41/-3791-1 -> -0.0099446056 | N42: - | O42: =+O41/L41-1 -> 0.1220784 | P42: =+P41/-3791-1 -> -2.6378264e-05 | Q42: - | R42: =+R41/O41-1 -> 0.018900484 | W42: =+W41/-3791-1 -> 0.032313374 | X42: - | Y42: =+Y41/R41-1 -> 0.020256845 | AD42: =+AD41/W41-1 -> 0.026779098 | AE42: =+AE41/X41-1 -> 0.10417168 | AF42: =+AF41/Y41-1 -> 0.06458317 | AK42: =+AK41/AD41-1 -> 0.11283379 | AL42: =+AL41/AE41-1 -> 0.14775591 | AM42: =+AM41/AF41-1 -> 0.1305266 | AR42: =+AR41/AK41-1 -> -0.1085046 | AS42: =+AS41/AL41-1 -> -0.015772471 | AT42: =+AT41/AM41-1 -> -0.060807142 | AY42: =+AY41/AR41-1 -> 0.24209206 | AZ42: =+AZ41/AS41-1 -> 0.20980821 | BA42: =+BA41/AT41-1 -> 0.22469039 | BF42: =+BF41/AY41-1 -> 0.16998546 | BG42: =+BG41/AZ41-1 -> 0.11105791 | BH42: =+BH41/BA41-1 -> 0.13860825 | BM42: =+BM41/BF41-1 -> 0.15350491 | BN42: =+BN41/BG41-1 -> 0.065164307 | BO42: =+BO41/BH41-1 -> 0.10760428 | BT42: =+BT41/BM41-1 -> 0.063822464 | BU42: =+BU41/BN41-1 -> 0.033832784 | BV42: =+BV41/BO41-1 -> 0.048837279 | CA42: =+CA41/BT41-1 -> 0.0095511387 | CB42: =+CB41/BU41-1 -> 0.0019292697 | CC42: =+CC41/BV41-1 -> 0.0057971415 | CH42: =+CH41/CA41-1 -> 0 | CI42: =+CI41/CB41-1 -> 0.0794729 | CJ42: =+CJ41/CC41-1 -> 0.038992241 | CK42: =+CK41/CJ41-1 -> 0.047611275 | CL42: =+CL41/CK41-1 -> 0.052826884 | CM42: =+CM41/CL41-1 -> 0.053227782 | CN42: =+CN41/CM41-1 -> 0.053388809 | CO42: =+CO41/CN41-1 -> 0.053549043 | CP42: =+CP41/CO41-1 -> 0.053708449 | CQ42: =+CQ41/CP41-1 -> 0.053866988 | CR42: =+CR41/CQ41-1 -> 0.054024626 | CS42: =+CS41/CR41-1 -> 0.054181326
A43: - as % of sales | B43: % | C43: =-C41/C$10 -> 0.30049268 | D43: =-D41/D$10 -> 0.30290728 | E43: =-E41/E$10 -> 0.30047238 | F43: =-F41/F$10 -> 0.30072059 | G43: =-G41/G$10 -> 0.30839986 | H43: =-H41/H$10 -> 0.30925122 | I43: =-I41/I$10 -> 0.3092744 | J43: =-J41/J$10 -> 0.30166899 | ... R43: =-R41/R$10 -> 0.29022994 | W43: =-W41/W$10 -> 0.29179311 | X43: =-X41/X$10 -> 0.29631773 | Y43: =-Y41/Y$10 -> 0.29398587 | AD43: =-AD41/AD$10 -> 0.3000814 | AE43: =-AE41/AE$10 -> 0.30460555 | AF43: =-AF41/AF$10 -> 0.30235657 | AK43: =-AK41/AK$10 -> 0.3019073 | AL43: =-AL41/AL$10 -> 0.31443823 | AM43: =-AM41/AM$10 -> 0.30822532 | AR43: =-AR41/AR$10 -> 0.30485986 | AS43: =-AS41/AS$10 -> 0.31252682 | AT43: =-AT41/AT$10 -> 0.30894074 | AY43: =-AY41/AY$10 -> 0.3258339 | AZ43: =-AZ41/AZ$10 -> 0.32997316 | BA43: =-BA41/BA$10 -> 0.32802492 | BF43: =-BF41/BF$10 -> 0.31543098 | BG43: =-BG41/BG$10 -> 0.31494793 | BH43: =-BH41/BH$10 -> 0.31517981 | BM43: =-BM41/BM$10 -> 0.32480643 | BN43: =-BN41/BN$10 -> 0.32384696 | BO43: =-BO41/BO$10 -> 0.32432629 | BT43: =-BT41/BT$10 -> 0.32137626 | BU43: =-BU41/BU$10 -> 0.32293212 | BV43: =-BV41/BV$10 -> 0.32214143 | CA43: =-CA41/CA$10 -> 0.31935533 | CB43: =-CB41/CB$10 -> 0.32067204 | CC43: 0.32 | CH43: =-CH41/CH$10 -> 0.30965375 | CI43: =-CI41/CI$10 -> 0.32646265 | CJ43: 0.318 | CK43: 0.317 | CL43: =CK43 -> 0.317 | CM43: =CL43 -> 0.317 | CN43: =CM43 -> 0.317 | CO43: =CN43 -> 0.317 | CP43: =CO43 -> 0.317 | CQ43: =CP43 -> 0.317 | CR43: =CQ43 -> 0.317 | CS43: =CR43 -> 0.317
A45: Selling, general and admnistrative expenses | B45: EURm | C45: -3009 | D45: -3309 | E45: -3618 | F45: -3779 | G45: -3736 | H45: -4048.6 | I45: -4186.9 | J45: -4610.9 | K45: -4756.8 | L45: -4821.1 | M45: -2732.6 | N45: =+O45-M45 -> -2706 | O45: -5438.6 | P45: -2764.7 | Q45: =+R45-P45 -> -2842.3 | R45: -5607 | W45: -2762.4 | X45: =+Y45-W45 -> -2698.1 | Y45: -5460.5 | AD45: -2751 | AE45: =+AF45-AD45 -> -2873.7 | AF45: -5624.7 | AK45: -3003.3 | AL45: =+AM45-AK45 -> -3065 | AM45: -6068.3 | AR45: -2765.2 | AS45: =AT45-AR45 -> -2873.3 | AT45: -5638.5 | AY45: -2898.2 | AZ45: =BA45-AY45 -> -3176 | BA45: -6074.2 | BF45: -3352.2 | BG45: =BH45-BF45 -> -3676.6 | BH45: -7028.8 | BM45: -3718.5 | BN45: =BO45-BM45 -> -3908.2 | BO45: -7626.7 | BT45: -4176.6 | BU45: =BV45-BT45 -> -4032.1 | BV45: -8208.7 | CA45: -4191.9 | CB45: =CC45-CA45 -> -4130.0721 | CC45: =-CC47*CC10 -> -8321.9721 | CH45: -4191.9 | CI45: =CJ45-CH45 -> -4508.9448 | CJ45: =-CJ47*CJ10 -> -8700.8448 | CK45: =-CK47*CK10 -> -9095.4772 | CL45: =-CL47*CL10 -> -9525.0269 | CM45: =-CM47*CM10 -> -9978.3758 | CN45: =-CN47*CN10 -> -10454.598 | CO45: =-CO47*CO10 -> -10954.894 | CP45: =-CP47*CP10 -> -11480.53 | CQ45: =-CQ47*CQ10 -> -12032.837 | ... CS45: =-CS47*CS10 -> -13223.159
A46: - reported growth | B46: % | AK46: =+AK45/AD45-1 -> 0.091712105 | AL46: =+AL45/AE45-1 -> 0.066569231 | AM46: =+AM45/AF45-1 -> 0.078866428 | AR46: =+AR45/AK45-1 -> -0.079279459 | AS46: =+AS45/AL45-1 -> -0.062544861 | AT46: =+AT45/AM45-1 -> -0.070827085 | AY46: =+AY45/AR45-1 -> 0.048097787 | AZ46: =+AZ45/AS45-1 -> 0.10534925 | BA46: =+BA45/AT45-1 -> 0.077272324 | BF46: =+BF45/AY45-1 -> 0.15664895 | BG46: =+BG45/AZ45-1 -> 0.15761965 | BH46: =+BH45/BA45-1 -> 0.1571565 | BM46: =+BM45/BF45-1 -> 0.10927152 | BN46: =+BN45/BG45-1 -> 0.062992983 | BO46: =+BO45/BH45-1 -> 0.085064307 | BT46: =+BT45/BM45-1 -> 0.12319484 | BU46: =+BU45/BN45-1 -> 0.031702574 | BV46: =+BV45/BO45-1 -> 0.076310855 | CA46: =+CA45/BT45-1 -> 0.0036632668 | CB46: =+CB45/BU45-1 -> 0.024298045 | CC46: =+CC45/BV45-1 -> 0.013799036 | CH46: =+CH45/CA45-1 -> 0 | CI46: =+CI45/CB45-1 -> 0.09173511 | CJ46: =+CJ45/CC45-1 -> 0.045526783 | CK46: =+CK45/CJ45-1 -> 0.04535564 | CL46: =+CL45/CK45-1 -> 0.047226741 | CM46: =+CM45/CL45-1 -> 0.047595548 | CN46: =+CN45/CM45-1 -> 0.047725428 | CO46: =+CO45/CN45-1 -> 0.047854184 | CP46: =+CP45/CO45-1 -> 0.047981772 | CQ46: =+CQ45/CP45-1 -> 0.048108152 | CR46: =+CR45/CQ45-1 -> 0.048233282 | CS46: =+CS45/CR45-1 -> 0.04835712
A47: - as % of sales | B47: % | C47: =-C45/C$10 -> 0.20704888 | D47: =-D45/D$10 -> 0.20955889 | E47: =-E45/E$10 -> 0.2120361 | F47: =-F45/F$10 -> 0.21543566 | G47: =-G45/G$10 -> 0.21380254 | H47: =-H45/H$10 -> 0.20766524 | I47: =-I45/I$10 -> 0.20581426 | J47: =-J45/J$10 -> 0.20526918 | ... R47: =-R45/R$10 -> 0.21701352 | W47: =-W45/W$10 -> 0.20596634 | X47: =-X45/X$10 -> 0.21393457 | Y47: =-Y45/Y$10 -> 0.20982796 | AD47: =-AD45/AD$10 -> 0.20544109 | AE47: =-AE45/AE$10 -> 0.21213284 | AF47: =-AF45/AF$10 -> 0.20880634 | AK47: =-AK45/AK$10 -> 0.20276812 | AL47: =-AL45/AL$10 -> 0.20349088 | AM47: =-AM45/AM$10 -> 0.20313253 | AR47: =-AR45/AR$10 -> 0.21146331 | AS47: =-AS45/AS10 -> 0.19264241 | AT47: =-AT45/AT$10 -> 0.20143183 | AY47: =-AY45/AY$10 -> 0.19071246 | AZ47: =-AZ45/AZ$10 -> 0.18583444 | BA47: =-BA45/BA$10 -> 0.18813039 | BF47: =-BF45/BF$10 -> 0.18251907 | BG47: =-BG45/BG$10 -> 0.18480577 | BH47: =-BH45/BH$10 -> 0.18370809 | BM47: =-BM45/BM$10 -> 0.18073695 | BN47: =-BN45/BN$10 -> 0.1896402 | BO47: =-BO45/BO$10 -> 0.18519229 | BT47: =-BT45/BT$10 -> 0.18880872 | BU47: =-BU45/BU$10 -> 0.18871483 | BV47: =-BV45/BV$10 -> 0.18876303 | CA47: =-CA45/CA$10 -> 0.18652718 | CB47: =-CB45/CB$10 -> 0.19157779 | CC47: 0.189 | CH47: =-CH45/CH$10 -> 0.18086074 | CI47: =-CI45/CI$10 -> 0.19725277 | CJ47: =CC47 -> 0.189 | CK47: =CJ47-0.1% -> 0.188 | CL47: =CK47-0.1% -> 0.187 | CM47: =CL47-0.1% -> 0.186 | CN47: =CM47-0.1% -> 0.185 | CO47: =CN47-0.1% -> 0.184 | CP47: =CO47-0.1% -> 0.183 | CQ47: =CP47-0.1% -> 0.182 | CR47: =CQ47-0.1% -> 0.181 | CS47: =CR47-0.1% -> 0.18
A49: Theoritical EBIT | B49: EURm | AR49: =AR50 -> 2357.2 | AS49: =AS33+AS37+AS41+AS45 -> 2851.4 | AT49: =AT33+AT37+AT41+AT45 -> 5209 | AY49: =AY33+AY37+AY41+AY45 -> 2988.3 | AZ49: =AZ33+AZ37+AZ41+AZ45 -> 3171.6811 | BA49: =BA33+BA37+BA41+BA45 -> 6159.9811 | BF49: =BF33+BF37+BF41+BF45 -> 3745.4 | BG49: =BH49-BF49 -> 3711.5 | BH49: =BH33+BH37+BH41+BH45 -> 7456.9 | BM49: =BM33+BM37+BM41+BM45 -> 4258.7 | BN49: =BO49-BM49 -> 3884.7 | BO49: =BO33+BO37+BO41+BO45 -> 8143.4 | BT49: =BT33+BT37+BT41+BT45 -> 4599.1 | BU49: =BV49-BT49 -> 4088.4 | BV49: =BV33+BV37+BV41+BV45 -> 8687.5 | CA49: =CA33+CA37+CA41+CA45 -> 4740.2 | CB49: =CC49-CA49 -> 4146.6846 | CC49: =CC33+CC37+CC41+CC45 -> 8886.8846 | CH49: =CH33+CH37+CH41+CH45 -> 5444.3006 | CI49: =CJ49-CH49 -> 3985.2839 | CJ49: =CJ33+CJ37+CJ41+CJ45 -> 9429.5845 | CK49: =CK33+CK37+CK41+CK45 -> 10151.603 | CL49: =CL33+CL37+CL41+CL45 -> 10891.624 | CM49: =CM33+CM37+CM41+CM45 -> 11685.95 | CN49: =CN33+CN37+CN41+CN45 -> 12535.894 | CO49: =CO33+CO37+CO41+CO45 -> 13445.329 | CP49: =CP33+CP37+CP41+CP45 -> 14418.397 | CQ49: =CQ33+CQ37+CQ41+CQ45 -> 15459.531 | ... CS49: =CS33+CS37+CS41+CS45 -> 17765.292
A50: =A72 -> Adjusted group operating profit | B50: EURm | Y50: =Y72 -> 4676.3 | AF50: =AF72 -> 4921.9 | AM50: =AM72 -> 5547.5 | AR50: =AR72 -> 2357.2 | AS50: =AS72 -> 2851.8 | AT50: =AT72 -> 5209 | AY50: =AY72 -> 2988.2 | AZ50: =BA50-AY50 -> 3172.1 | BA50: =BA72 -> 6160.3 | BF50: =BF72 -> 3745.5 | BG50: =BH50-BF50 -> 3711.3 | BH50: =BH72 -> 7456.8 | BM50: =BM72 -> 4258.8 | BN50: =BO50-BM50 -> 3884.5 | BO50: =BO72 -> 8143.3 | BT50: =BT72 -> 4599.1 | BU50: =BV50-BT50 -> 4088.4 | BV50: =BV72 -> 8687.5 | CA50: =CA72 -> 4740.1 | CB50: =CC50-CA50 -> 4186.6103 | CC50: =CC72 -> 8926.7103 | CH50: =CH72 -> 4922.8918 | CI50: =CJ50-CH50 -> 4537.4057 | CJ50: =CJ72 -> 9460.2975 | CK50: =CK72 -> 10088.973 | CL50: =CL72 -> 10758.622 | CM50: =CM72 -> 11475.721 | CN50: =CN72 -> 12241.108 | CO50: =CO72 -> 13058.076 | CP50: =CP72 -> 13930.151 | CQ50: =CQ72 -> 14861.097 | ... CS50: =CS72 -> 16915.99
A52: OPERATING PROFIT - DIVISIONS | B52: EURm | C52: =2607+54 -> 2661 | D52: =2861+58+59 -> 2978 | E52: =3184+64+62 -> 3310 | F52: =3111+36+80 -> 3227 | G52: =2921+54+85 -> 3060 | H52: =3386+65+119 -> 3570 | I52: =3650.6+68.1+120.1 -> 3838.8 | J52: =4054.3+77.5+142.6 -> 4274.4 | K52: =4290.6+71.9+116.8 -> 4479.3 | L52: =4440.6+65.3 -> 4505.9 | M52: =2641-7 -> 2634 | N52: =+O52-M52 -> 2397.2 | O52: =4976.4+54.8 -> 5031.2 | P52: =2695.6-22.2 -> 2673.4 | Q52: =+R52-P52 -> 2520.4 | R52: =5160+33.8 -> 5193.8 | W52: 2861.1 | X52: =+Y52-W52 -> 2554.3 | Y52: 5415.4 | AD52: 2941.7 | AE52: =+AF52-AD52 -> 2733.3 | AF52: 5675 | AK52: 3282.3 | AL52: =+AM52-AK52 -> 3098.4 | AM52: 6380.7 | AR52: =+AR61+AR62+AR63+AR64 -> 2709.5 | AS52: =+AS61+AS62+AS63+AS64 -> 3302.2 | AT52: 6011.6 | AY52: =+AY61+AY62+AY63+AY64 -> 3429.2 | AZ52: =+AZ61+AZ62+AZ63+AZ64 -> 3650.5 | BA52: 7079.7 | BF52: 4169.9 | BG52: =+BG61+BG62+BG63+BG64 -> 4212.1 | BH52: =+BH61+BH62+BH63+BH64 -> 8381.9 | BM52: 4729.3 | BN52: =+BN61+BN62+BN63+BN64 -> 4393.4 | BO52: =+BO61+BO62+BO63+BO64 -> 9122.7 | BT52: =+BT61+BT62+BT63+BT64 -> 5128.5 | BU52: =+BU61+BU62+BU63+BU64 -> 4636.5 | BV52: =+BV61+BV62+BV63+BV64 -> 9765 | CA52: =+CA61+CA62+CA63+CA64 -> 5261 | CB52: =+CB61+CB62+CB63+CB64 -> 4722.4687 | CC52: =+CC61+CC62+CC63+CC64 -> 9983.4687 | CH52: =+CH61+CH62+CH63+CH64 -> 5479.1518 | CI52: =+CI61+CI62+CI63+CI64 -> 5086.0148 | CJ52: =+CJ61+CJ62+CJ63+CJ64 -> 10565.167 | CK52: =+CK61+CK62+CK63+CK64 -> 11250.098 | CL52: =+CL61+CL62+CL63+CL64 -> 11981.085 | CM52: =+CM61+CM62+CM63+CM64 -> 12763.254 | CN52: =+CN61+CN62+CN63+CN64 -> 13597.38 | CO52: =+CO61+CO62+CO63+CO64 -> 14486.976 | ... CS52: =+CS61+CS62+CS63+CS64 -> 18679.077
A53: Check | B53: EURm | C53: =+C61+C62+C63+C64 -> 2660.8 | E53: =+E61+E62+E63+E64 -> 3309.5 | F53: =+F61+F62+F63+F64 -> 3227.2 | G53: =+G61+G62+G63+G64 -> 3060 | H53: =+H61+H62+H63+H64 -> 3570 | I53: =+I61+I62+I63+I64 -> 3838.8 | J53: =+J61+J62+J63+J64 -> 4274.3 | K53: =+K61+K62+K63+K64 -> 4479.3 | L53: =+L61+L62+L63+L64 -> 4505.9 | ... R53: =+R61+R62+R63+R64 -> 5193.8 | W53: =+W61+W62+W63+W64 -> 2861.1 | X53: =+X61+X62+X63+X64 -> 2554.3 | Y53: =+Y61+Y62+Y63+Y64 -> 5415.4 | AD53: =+AD61+AD62+AD63+AD64 -> 2941.7 | AE53: =+AE61+AE62+AE63+AE64 -> 2733.3 | AF53: =+AF61+AF62+AF63+AF64 -> 5675 | AK53: =+AK61+AK62+AK63+AK64 -> 3282.4 | AL53: =+AL61+AL62+AL63+AL64 -> 3098.3 | AM53: =+AM61+AM62+AM63+AM64 -> 6380.7 | AR53: =+AR61+AR62+AR63+AR64 -> 2709.5 | AS53: =+AS61+AS62+AS63+AS64 -> 3302.2 | AT53: =+AT61+AT62+AT63+AT64 -> 6011.7 | AY53: =+AY61+AY62+AY63+AY64 -> 3429.2 | AZ53: =+AZ61+AZ62+AZ63+AZ64 -> 3650.5 | BA53: =+BA61+BA62+BA63+BA64 -> 7079.7 | BF53: =+BF61+BF62+BF63+BF64 -> 4169.8 | BG53: =+BG61+BG62+BG63+BG64 -> 4212.1 | BH53: =+BH61+BH62+BH63+BH64 -> 8381.9 | BM53: =+BM61+BM62+BM63+BM64 -> 4729.3 | BN53: =+BN61+BN62+BN63+BN64 -> 4393.4 | BO53: =+BO61+BO62+BO63+BO64 -> 9122.7 | BT53: =+BT61+BT62+BT63+BT64 -> 5128.5 | BU53: =+BU61+BU62+BU63+BU64 -> 4636.5 | BV53: =+BV61+BV62+BV63+BV64 -> 9765 | CA53: =+CA61+CA62+CA63+CA64 -> 5261 | CB53: =+CB61+CB62+CB63+CB64 -> 4722.4687 | CC53: =+CC61+CC62+CC63+CC64 -> 9983.4687 | CH53: =+CH61+CH62+CH63+CH64 -> 5479.1518 | CI53: =+CI61+CI62+CI63+CI64 -> 5086.0148 | CJ53: =+CJ61+CJ62+CJ63+CJ64 -> 10565.167 | CK53: =+CK61+CK62+CK63+CK64 -> 11250.098 | CL53: =+CL61+CL62+CL63+CL64 -> 11981.085 | CM53: =+CM61+CM62+CM63+CM64 -> 12763.254 | CN53: =+CN61+CN62+CN63+CN64 -> 13597.38 | CO53: =+CO61+CO62+CO63+CO64 -> 14486.976 | ... CS53: =+CS61+CS62+CS63+CS64 -> 18679.077
A54: Check | B54: EURm | C54: =+C65+C66+C67+C68+C69+C70 -> 2660.8 | D54: =+D65+D66+D67+D68+D69+D70 -> 2978.7 | E54: =+E65+E66+E67+E68+E69+E70 -> 3309.5 | F54: =+F65+F66+F67+F68+F69+F70 -> 3227.2 | G54: =+G65+G66+G67+G68+G69+G70 -> 3060 | H54: =+H65+H66+H67+H68+H69+H70 -> 3570 | I54: =+I65+I66+I67+I68+I69+I70 -> 3838.8 | J54: =+J65+J66+J67+J68+J69+J70 -> 4274.3 | K54: =+K65+K66+K67+K68+K69+K70 -> 4479.3 | L54: =+L65+L66+L67+L68+L69 -> 4505.9 | M54: =+M65+M66+M67+M68+M69 -> 2634.1 | N54: =+N65+N66+N67+N68+N69 -> 2397.2 | O54: =+O65+O66+O67+O68+O69 -> 5031.3 | P54: =+P65+P66+P67+P68+P69 -> 2673.4 | Q54: =+Q65+Q66+Q67+Q68+Q69 -> 2520.4 | R54: =+R65+R66+R67+R68+R69 -> 5193.8 | W54: =+W65+W66+W67+W68 -> 2861.1 | X54: =+X65+X66+X67+X68 -> 2554.3 | Y54: =+Y65+Y66+Y67+Y68 -> 5415.4 | AD54: =+AD65+AD66+AD67+AD68 -> 2941.7 | AE54: =+AE65+AE66+AE67+AE68 -> 2733.3 | AF54: =+AF65+AF66+AF67+AF68 -> 5675 | AK54: =+AK65+AK66+AK67+AK68 -> 3282.4 | AL54: =+AL65+AL66+AL67+AL68 -> 3098.3 | AM54: =+AM65+AM66+AM67+AM68 -> 6380.7 | AR54: =+AR65+AR66+AR67+AR68 -> 2709.5 | AS54: =+AS65+AS66+AS67+AS68 -> 3302.2 | AT54: =+AT65+AT66+AT67+AT68 -> 6011.7 | AY54: =+AY65+AY66+AY67+AY68 -> 3429.2 | AZ54: =+AZ65+AZ66+AZ67+AZ68 -> 3650.5 | BA54: =+BA65+BA66+BA67+BA68 -> 7079.7 | BF54: =+BF65+BF66+BF67+BF68 -> 4169.8 | BG54: =+BG65+BG66+BG67+BG68 -> 4212.1 | BH54: =+BH65+BH66+BH67+BH68 -> 8381.9 | BM54: =+BM65+BM66+BM67+BM68 -> 4729.3 | BN54: =+BN65+BN66+BN67+BN68 -> 4393.4 | BO54: =+BO65+BO66+BO67+BO68 -> 9122.7 | BT54: =+BT65+BT66+BT67+BT68 -> 5128.5 | BU54: =+BU65+BU66+BU67+BU68 -> 4636.5 | BV54: =+BV65+BV66+BV67+BV68 -> 9765 | CA54: =+CA65+CA66+CA67+CA68 -> 5261 | CB54: =+CB65+CB66+CB67+CB68 -> 4722.4687 | CC54: =+CC65+CC66+CC67+CC68 -> 9983.4687 | CH54: =+CH65+CH66+CH67+CH68 -> 5479.1518 | CI54: =+CI65+CI66+CI67+CI68 -> 5086.0148 | CJ54: =+CJ65+CJ66+CJ67+CJ68 -> 10565.167 | CK54: =+CK65+CK66+CK67+CK68 -> 11250.098 | CL54: =+CL65+CL66+CL67+CL68 -> 11981.085 | CM54: =+CM65+CM66+CM67+CM68 -> 12763.254 | CN54: =+CN65+CN66+CN67+CN68 -> 13597.38 | CO54: =+CO65+CO66+CO67+CO68 -> 14486.976 | ... CS54: =+CS65+CS66+CS67+CS68 -> 18679.077
A55: - Operating profit margin | B55: % | C55: =+C52/C10 -> 0.18310305 | D55: =+D52/D10 -> 0.18859667 | E55: =+E52/E10 -> 0.19398549 | F55: =+F52/F10 -> 0.18396689 | G55: =+G52/G10 -> 0.17511664 | H55: =+H52/H10 -> 0.18311636 | I55: =+I52/I10 -> 0.1887028 | J55: =+J52/J10 -> 0.19028879 | ... R55: =+R52/R10 -> 0.20102101 | W55: =+W52/W10 -> 0.21332548 | X55: =+X52/X10 -> 0.20253255 | Y55: =+Y52/Y10 -> 0.20809493 | AD55: =+AD52/AD10 -> 0.21968232 | AE55: =+AE52/AE10 -> 0.2017687 | AF55: =+AF52/AF10 -> 0.21067364 | AK55: =+AK52/AK10 -> 0.22160483 | AL55: =+AL52/AL10 -> 0.20570837 | AM55: =+AM52/AM10 -> 0.21358993 | AR55: =+AR52/AR10 -> 0.20720376 | AS55: =+AS52/AS10 -> 0.22139831 | AT55: =+AT52/AT10 -> 0.21476059 | AY55: =+AY52/AY10 -> 0.22565425 | AZ55: =+AZ52/AZ10 -> 0.21359843 | BA55: =+BA52/BA10 -> 0.21927278 | BF55: =+BF52/BF10 -> 0.22704083 | BG55: =+BG52/BG10 -> 0.2117229 | BH55: =+BH52/BH10 -> 0.21907336 | BM55: =+BM52/BM10 -> 0.22986668 | BN55: =+BN52/BN10 -> 0.21318388 | BO55: =+BO52/BO10 -> 0.22151831 | BT55: =+BT52/BT10 -> 0.23184062 | BU55: =+BU52/BU10 -> 0.21700264 | BV55: =+BV52/BV10 -> 0.2245509 | CA55: =+CA52/CA10 -> 0.23409898 | CB55: =+CB52/CB10 -> 0.21905674 | CC55: =+CC52/CC10 -> 0.22673419 | CH55: =+CH52/CH10 -> 0.2363996 | CI55: =+CI52/CI10 -> 0.22249784 | CJ55: =+CJ52/CJ10 -> 0.22949685 | CK55: =+CK52/CK10 -> 0.23253517 | CL55: =+CL52/CL10 -> 0.23521854 | CM55: =+CM52/CM10 -> 0.23791098 | CN55: =+CN52/CN10 -> 0.24061329 | CO55: =+CO52/CO10 -> 0.24332535 | ... CS55: =+CS52/CS10 -> 0.25426859
A56: - Operating profit margin progression | B56: bps | C56: =(C55-(C61/C19))*10000 -> 20.843399 | D56: =(D55-(D61/D19))*10000 -> 44.034512 | E56: =(E55-(E61/E19))*10000 -> 43.718178 | F56: =(F55-(F61/F19))*10000 -> -106.7372 | G56: =(G55-(G61/G19))*10000 -> -96.304999 | H56: =(H55-(H61/H19))*10000 -> 79.840127 | I56: =(I55-(I61/I19))*10000 -> 55.855006 | J56: =(J55-(J61/J19))*10000 -> 15.859865 | ... R56: =(R55-(R61/R19))*10000 -> 18.199862 | W56: =(W55-(W61/W19))*10000 -> -24.088141 | X56: =(X55-(X61/X19))*10000 -> 41.298181 | Y56: =(Y55-(Y61/Y19))*10000 -> 10.007492 | AD56: =(AD55-(AD61/AD19))*10000 -> 63.584278 | AE56: =(AE55-(AE61/AE19))*10000 -> -7.6545836 | AF56: =(AF55-(AF61/AF19))*10000 -> 25.787071 | AK56: =(AK55-(AK61/AK19))*10000 -> 19.225172 | AL56: =(AL55-(AL61/AL19))*10000 -> 39.396709 | AM56: =(AM55-(AM61/AM19))*10000 -> 29.162896 | AR56: =(AR55-(AR61/AR19))*10000 -> -144.07823 | AS56: =(AS55-(AS61/AS19))*10000 -> 156.96577 | AT56: =(AT55-(AT61/AT19))*10000 -> 11.735275 | AY56: =(AY55-(AY61/AY19))*10000 -> 184.50491 | AZ56: =(AZ55-(AZ61/AZ19))*10000 -> -77.939341 | BA56: =(BA55-(BA61/BA19))*10000 -> 45.086154 | BF56: =(BF55-(BF61/BF19))*10000 -> 13.865763 | BG56: =(BG55-(BG61/BG19))*10000 -> -18.703018 | BH56: =(BH55-(BH61/BH19))*10000 -> -1.9657919 | BM56: =(BM55-(BM61/BM19))*10000 -> 28.312916 | BN56: =(BN55-(BN61/BN19))*10000 -> 14.609835 | BO56: =(BO55-(BO61/BO19))*10000 -> 24.449539 | BT56: =(BT55-(BT61/BT19))*10000 -> 19.739436 | BU56: =(BU55-(BU61/BU19))*10000 -> 38.187546 | BV56: =(BV55-(BV61/BV19))*10000 -> 30.325871 | CA56: =(CA55-(CA61/CA19))*10000 -> 22.573106 | CB56: =(CB55-(CB61/CB19))*10000 -> 20.541023 | CC56: =(CC55-(CC61/CC19))*10000 -> 21.832873 | CH56: =(CH55-(CH61/CH19))*10000 -> 23.006187 | CI56: =(CI55-(CI61/CI19))*10000 -> 34.411075 | CJ56: =(CJ55-(CJ61/CJ19))*10000 -> 27.626683 | CK56: =(CK55-(CK61/CK19))*10000 -> 30.383166 | CL56: =(CL55-(CL61/CL19))*10000 -> 26.833693 | CM56: =(CM55-(CM61/CM19))*10000 -> 26.924428 | CN56: =(CN55-(CN61/CN19))*10000 -> 27.023096 | CO56: =(CO55-(CO61/CO19))*10000 -> 27.12059 | ... CS56: =(CS55-(CS61/CS19))*10000 -> 27.498013
A57: - reported growth | B57: % | C57: =+C52/C61-1 -> 0.084528856 | D57: =+D52/D61-1 -> 0.11921227 | E57: =+E52/E61-1 -> 0.11122302 | F57: =+F52/F61-1 -> -0.024928237 | G57: =+G52/G61-1 -> -0.051809618 | H57: =+H52/H61-1 -> 0.16666667 | I57: =+I52/I61-1 -> 0.075294118 | J57: =+J52/J61-1 -> 0.11347296 | ... R57: =+R52/R61-1 -> 0.032297816 | W57: =+W52/W61-1 -> 0.06139635 | X57: =+X52/X61-1 -> 0.036479468 | Y57: =+Y52/Y61-1 -> 0.049496124 | AD57: =+AD52/AD61-1 -> 0.028170983 | AE57: =+AE52/AE61-1 -> 0.070077908 | AF57: =+AF52/AF61-1 -> 0.047937364 | AK57: =+AK52/AK61-1 -> 0.11578339 | AL57: =+AL52/AL61-1 -> 0.1335748 | AM57: =+AM52/AM61-1 -> 0.12435242 | AR57: =+AR52/AR61-1 -> -0.17453692 | AS57: =+AS52/AS61-1 -> 0.065810283 | AT57: =+AT52/AT61-1 -> -0.057846318 | AY57: =+AY52/AY61-1 -> 0.26562096 | AZ57: =+AZ52/AZ61-1 -> 0.10547514 | BA57: =+BA52/BA61-1 -> 0.17765358 | BF57: =+BF52/BF61-1 -> 0.2159979 | BG57: =+BG52/BG61-1 -> 0.15384194 | BH57: =+BH52/BH61-1 -> 0.18393435 | BM57: =+BM52/BM61-1 -> 0.1341791 | BN57: =+BN52/BN61-1 -> 0.043042663 | BO57: =+BO52/BO61-1 -> 0.088380916 | BT57: =+BT52/BT61-1 -> 0.084409955 | BU57: =+BU52/BU61-1 -> 0.055332999 | BV57: =+BV52/BV61-1 -> 0.070406787 | CA57: =+CA52/CA61-1 -> 0.025836014 | CB57: =+CB52/CB61-1 -> 0.018541715 | CC57: =+CC52/CC61-1 -> 0.022372623 | CH57: =+CH52/CH61-1 -> 0.041465848 | CI57: =+CI52/CI61-1 -> 0.076982233 | CJ57: =+CJ52/CJ61-1 -> 0.058266123 | CK57: =+CK52/CK61-1 -> 0.064829155 | CL57: =+CL52/CL61-1 -> 0.064976114 | CM57: =+CM52/CM61-1 -> 0.065283616 | CN57: =+CN52/CN61-1 -> 0.065353715 | CO57: =+CO52/CO61-1 -> 0.065424061 | ... CS57: =+CS52/CS61-1 -> 0.065706466
A58: - estimated organic growth | B58: % | C58: =+C62/C61 -> 0.068465169 | D58: =+D62/D61 -> 0.098414369 | E58: =+E62/E61 -> 0.11626928 | F58: =+F62/F61 -> -0.023928197 | G58: =+G62/G61 -> -0.062313205 | H58: =+H62/H61 -> 0.10588447 | I58: =+I62/I61 -> 0.081814216 | J58: =+J62/J61 -> 0.064306606 | ... R58: =+R62/R61 -> 0.055623837 | W58: =+W62/W61 -> 0.029333947 | X58: =+X62/X61 -> 0.076385524 | Y58: =+Y62/Y61 -> 0.051805635 | AD58: =+AD62/AD61 -> 0.09450687 | AE58: =+AE62/AE61 -> 0.071044142 | AF58: =+AF62/AF61 -> 0.083440126 | AK58: =+AK62/AK61 -> 0.082830082 | AL58: =+AL62/AL61 -> 0.10789567 | AM58: =+AM62/AM61 -> 0.094902642 | AR58: =+AR62/AR61 -> -0.1736352 | AS58: =+AS62/AS61 -> 0.10986043 | AT58: =+AT62/AT61 -> -0.035977182 | AY58: =+AY62/AY61 -> 0.30949222 | AZ58: =+AZ62/AZ61 -> 0.082734915 | BA58: =+BA62/BA61 -> 0.18493544 | BF58: =+BF62/BF61 -> 0.14096626 | BG58: =+BG62/BG61 -> 0.075381149 | BH58: =+BH62/BH61 -> 0.10714866 | BM58: =+BM62/BM61 -> 0.1462048 | BN58: =+BN62/BN61 -> 0.097480948 | BO58: =+BO62/BO61 -> 0.12171993 | BT58: =+BT62/BT61 -> 0.083116901 | BU58: =+BU62/BU61 -> 0.047207332 | BV58: =+BV62/BV61 -> 0.065823216 | CA58: =+CA62/CA61 -> 0.039652735 | CB58: =+CB62/CB61 -> 0.064141128 | CC58: =+CC62/CC61 -> 0.05128002 | CH58: =+CH62/CH61 -> 0.065903944 | CI58: =+CI62/CI61 -> 0.058593182 | CJ58: =+CJ62/CJ61 -> 0.062445743 | CK58: =+CK62/CK61 -> 0.068530015 | CL58: =+CL62/CL61 -> 0.068676131 | CM58: =+CM62/CM61 -> 0.068741877 | CN58: =+CN62/CN61 -> 0.068808292 | CO58: =+CO62/CO61 -> 0.068875003 | ... CS58: =+CS62/CS61 -> 0.069143378
A59: - forex impact | B59: % | C59: =+C63/C61 -> 0.015982173 | D59: =+D63/D61 -> -0.00084972655 | E59: =+E63/E61 -> -0.033556351 | F59: =+F63/F61 -> -0.037718596 | G59: =+G63/G61 -> -0.005657791 | H59: =+H63/H61 -> 0.056105722 | I59: =+I63/I61 -> -0.014543348 | J59: =+J63/J61 -> 0.041109852 | ... R59: =+R63/R61 -> -0.021161943 | W59: =+W63/W61 -> 0.032062402 | X59: =+X63/X61 -> -0.060388462 | Y59: =+Y63/Y61 -> -0.012091844 | AD59: =+AD63/AD61 -> -0.066335887 | AE59: =+AE63/AE61 -> -0.011181377 | AF59: =+AF63/AF61 -> -0.040320973 | AK59: =+AK63/AK61 -> 0.032987303 | AL59: =+AL63/AL61 -> 0.012604148 | AM59: =+AM63/AM61 -> 0.023169985 | AR59: =+AR63/AR61 -> -0.004640757 | AS59: =+AS63/AS61 -> -0.050552133 | AT59: =+AT63/AT61 -> -0.026934113 | AY59: =+AY63/AY61 -> -0.05515993 | AZ59: =+AZ63/AZ61 -> 0.020699108 | BA59: =+BA63/BA61 -> -0.013490899 | BF59: =+BF63/BF61 -> 0.071533575 | BG59: =+BG63/BG61 -> 0.074054747 | BH59: =+BH63/BH61 -> 0.072833565 | BM59: =+BM63/BM61 -> -0.016016397 | BN59: =+BN63/BN61 -> -0.084309806 | BO59: =+BO63/BO61 -> -0.050335426 | BT59: =+BT63/BT61 -> -0.024170615 | BU59: =+BU63/BU61 -> 0.00098189747 | BV59: =+BV63/BV61 -> -0.01205742 | CA59: =+CA63/CA61 -> -0.018090687 | CB59: =+CB63/CB61 -> -0.057186037 | CC59: =+CC63/CC61 -> -0.036653472 | CH59: =+CH63/CH61 -> -0.030829406 | CI59: =+CI63/CI61 -> 0.012033511 | CJ59: =+CJ63/CJ61 -> -0.010554009 | CK59: =+CK63/CK61 -> -0.0037008602 | CL59: =+CL63/CL61 -> -0.0037000174 | CM59: =+CM63/CM61 -> -0.0034582614 | CN59: =+CN63/CN61 -> -0.0034545767 | CO59: =+CO63/CO61 -> -0.0034509422 | ... CS59: =+CS63/CS61 -> -0.0034369122
A60: - scope impact | B60: % | C60: =+C64/C61 -> 0 | D60: =+D64/D61 -> 0 | E60: =+E64/E61 -> 0.028342227 | F60: =+F64/F61 -> 0.036778988 | G60: =+G64/G61 -> 0.016161378 | H60: =+H64/H61 -> 0.0046764706 | I60: =+I64/I61 -> 0.0080232493 | J60: =+J64/J61 -> 0.0080304522 | ... R60: =+R64/R61 -> -0.0021640785 | W60: =+W64/W61 -> 0 | X60: =+X64/X61 -> 0.020482405 | Y60: =+Y64/Y61 -> 0.0097823333 | AD60: =+AD64/AD61 -> 0 | AE60: =+AE64/AE61 -> 0.010215143 | AF60: =+AF64/AF61 -> 0.004818211 | AK60: =+AK64/AK61 -> 0 | AL60: =+AL64/AL61 -> 0.013038393 | AM60: =+AM64/AM61 -> 0.0062797956 | AR60: =+AR64/AR61 -> 0.0037390324 | AS60: =+AS64/AS61 -> 0.006501985 | AT60: =+AT64/AT61 -> 0.0050806495 | AY60: =+AY64/AY61 -> 0.011288672 | AZ60: =+AZ64/AZ61 -> 0.0020411144 | BA60: =+BA64/BA61 -> 0.00620903 | BF60: =+BF64/BF61 -> 0.0034689086 | BG60: =+BG64/BG61 -> 0.0044060428 | BH60: =+BH64/BH61 -> 0.0039521224 | BM60: =+BM64/BM61 -> 0.0039906913 | BN60: =+BN64/BN61 -> 0.029871521 | BO60: =+BO64/BO61 -> 0.016996411 | BT60: =+BT64/BT61 -> 0.02546367 | BU60: =+BU64/BU61 -> 0.0071437705 | BV60: =+BV64/BV61 -> 0.016640992 | CA60: =+CA64/CA61 -> 0.0042739665 | CB60: =+CB64/CB61 -> 0.011586625 | CC60: =+CC64/CC61 -> 0.0077460753 | CH60: =+CH64/CH61 -> 0.0063913095 | CI60: =+CI64/CI61 -> 0.0063555396 | CJ60: =+CJ64/CJ61 -> 0.0063743893 | CK60: =+CK64/CK61 -> 0 | CL60: =+CL64/CL61 -> 0 | CM60: =+CM64/CM61 -> 0 | CN60: =+CN64/CN61 -> 0 | CO60: =+CO64/CO61 -> 0 | ... CS60: =+CS64/CS61 -> 0
A61: reference base | B61: EURm | C61: =+C258+C371+C484+C597+C624+C651 -> 2453.6 | D61: =+D258+D371+D484+D597+D624+D651 -> 2660.8 | E61: =+E258+E371+E484+E597+E624+E651 -> 2978.7 | F61: =+F258+F371+F484+F597+F624+F651 -> 3309.5 | G61: =+G258+G371+G484+G597+G624+G651 -> 3227.2 | H61: =+H258+H371+H484+H597+H624+H651 -> 3060 | I61: =+I258+I371+I484+I597+I624+I651 -> 3570 | J61: =+J258+J371+J484+J597+J624+J651 -> 3838.8 | K61: =+K258+K371+K484+K597+K624+K651 -> 4274.3 | L61: =+L258+L371+L484+L597+L624 -> 4364.9 | M61: =+M258+M371+M484+M597+M624 -> 2234 | N61: =+N258+N371+N484+N597+N624 -> 2271.9 | O61: =+O258+O371+O484+O597+O624 -> 4505.9 | P61: =+P258+P371+P484+P597+P624 -> 2634.1 | Q61: =+Q258+Q371+Q484+Q597+Q624 -> 2397.2 | R61: =+R258+R371+R484+R597+R624 -> 5031.3 | W61: =+W258+W371+W484+W597 -> 2695.6 | X61: =+X258+X371+X484+X597 -> 2464.4 | Y61: =+Y258+Y371+Y484+Y597 -> 5160 | AD61: =+AD258+AD371+AD484+AD597 -> 2861.1 | AE61: =+AE258+AE371+AE484+AE597 -> 2554.3 | AF61: =+AF258+AF371+AF484+AF597 -> 5415.4 | AK61: =+AK258+AK371+AK484+AK597 -> 2941.7 | AL61: =+AL258+AL371+AL484+AL597 -> 2733.3 | AM61: =+AM258+AM371+AM484+AM597 -> 5675 | AR61: =+AR258+AR371+AR484+AR597 -> 3282.4 | AS61: =+AS258+AS371+AS484+AS597 -> 3098.3 | AT61: =+AT258+AT371+AT484+AT597 -> 6380.7 | AY61: =+AY258+AY371+AY484+AY597 -> 2709.5 | AZ61: =+AZ258+AZ371+AZ484+AZ597 -> 3302.2 | BA61: =+BA258+BA371+BA484+BA597 -> 6011.7 | BF61: =+BF258+BF371+BF484+BF597 -> 3429.2 | BG61: =+BG258+BG371+BG484+BG597 -> 3650.5 | BH61: =+BH258+BH371+BH484+BH597 -> 7079.7 | BM61: =+BM258+BM371+BM484+BM597 -> 4169.8 | BN61: =+BN258+BN371+BN484+BN597 -> 4212.1 | BO61: =+BO258+BO371+BO484+BO597 -> 8381.9 | BT61: =+BT258+BT371+BT484+BT597 -> 4729.3 | BU61: =+BU258+BU371+BU484+BU597 -> 4393.4 | BV61: =+BV258+BV371+BV484+BV597 -> 9122.7 | CA61: =+CA258+CA371+CA484+CA597 -> 5128.5 | CB61: =+CB258+CB371+CB484+CB597 -> 4636.5 | CC61: =+CC258+CC371+CC484+CC597 -> 9765 | CH61: =+CH258+CH371+CH484+CH597 -> 5261 | CI61: =+CI258+CI371+CI484+CI597 -> 4722.4687 | CJ61: =+CJ258+CJ371+CJ484+CJ597 -> 9983.4687 | CK61: =+CK258+CK371+CK484+CK597 -> 10565.167 | CL61: =+CL258+CL371+CL484+CL597 -> 11250.098 | CM61: =+CM258+CM371+CM484+CM597 -> 11981.085 | CN61: =+CN258+CN371+CN484+CN597 -> 12763.254 | CO61: =+CO258+CO371+CO484+CO597 -> 13597.38 | ... CS61: =+CS258+CS371+CS484+CS597 -> 17527.413
A62: organic growth impact | B62: EURm | C62: =+C259+C372+C485+C598+C625+C652 -> 167.98614 | D62: =+D259+D372+D485+D598+D625+D652 -> 261.86095 | E62: =+E259+E372+E485+E598+E625+E652 -> 346.33131 | F62: =+F259+F372+F485+F598+F625+F652 -> -79.190367 | G62: =+G259+G372+G485+G598+G625+G652 -> -201.09718 | H62: =+H259+H372+H485+H598+H625+H652 -> 324.00649 | I62: =+I259+I372+I485+I598+I625+I652 -> 292.07675 | J62: =+J259+J372+J485+J598+J625+J652 -> 246.8602 | K62: =+K259+K372+K485+K598+K625+K652 -> 321.30887 | L62: =+L259+L372+L485+L598+L625 -> 232.61594 | M62: =+M259+M372+M485+M598+M625 -> 163.78189 | N62: =+N259+N372+N485+N598+N625 -> -2.8595169 | O62: =+O259+O372+O485+O598+O625 -> 160.92238 | P62: =+P259+P372+P485+P598+P625 -> 137.24785 | Q62: =+Q259+Q372+Q485+Q598+Q625 -> 142.61236 | R62: =+R259+R372+R485+R598+R625 -> 279.86021 | W62: =+W259+W372+W485+W598 -> 79.072588 | X62: =+X259+X372+X485+X598 -> 188.24449 | Y62: =+Y259+Y372+Y485+Y598 -> 267.31707 | AD62: =+AD259+AD372+AD485+AD598 -> 270.39361 | AE62: =+AE259+AE372+AE485+AE598 -> 181.46805 | AF62: =+AF259+AF372+AF485+AF598 -> 451.86166 | AK62: =+AK259+AK372+AK485+AK598 -> 243.66125 | AL62: =+AL259+AL372+AL485+AL598 -> 294.91124 | AM62: =+AM259+AM372+AM485+AM598 -> 538.57249 | AR62: =+AR259+AR372+AR485+AR598 -> -569.94018 | AS62: =+AS259+AS372+AS485+AS598 -> 340.38057 | AT62: =+AT259+AT372+AT485+AT598 -> -229.5596 | AY62: =+AY259+AY372+AY485+AY598 -> 838.56917 | AZ62: =+AZ259+AZ372+AZ485+AZ598 -> 273.20724 | BA62: =+BA259+BA372+BA485+BA598 -> 1111.7764 | BF62: =+BF259+BF372+BF485+BF598 -> 483.40148 | BG62: =+BG259+BG372+BG485+BG598 -> 275.17889 | BH62: =+BH259+BH372+BH485+BH598 -> 758.58037 | BM62: =+BM259+BM372+BM485+BM598 -> 609.64479 | BN62: =+BN259+BN372+BN485+BN598 -> 410.5995 | BO62: =+BO259+BO372+BO485+BO598 -> 1020.2443 | BT62: =+BT259+BT372+BT485+BT598 -> 393.08476 | BU62: =+BU259+BU372+BU485+BU598 -> 207.40069 | BV62: =+BV259+BV372+BV485+BV598 -> 600.48545 | CA62: =+CA259+CA372+CA485+CA598 -> 203.35905 | CB62: =+CB259+CB372+CB485+CB598 -> 297.39034 | CC62: =+CC259+CC372+CC485+CC598 -> 500.74939 | CH62: =+CH259+CH372+CH485+CH598 -> 346.72065 | CI62: =+CI259+CI372+CI485+CI598 -> 276.70447 | CJ62: =+CJ259+CJ372+CJ485+CJ598 -> 623.42511 | CK62: =+CK259+CK372+CK485+CK598 -> 724.03103 | CL62: =+CL259+CL372+CL485+CL598 -> 772.61318 | CM62: =+CM259+CM372+CM485+CM598 -> 823.60228 | CN62: =+CN259+CN372+CN485+CN598 -> 878.21769 | CO62: =+CO259+CO372+CO485+CO598 -> 936.51958 | ... CS62: =+CS259+CS372+CS485+CS598 -> 1211.9045
A63: forex impact | B63: EURm | C63: =+C260+C373+C486+C599+C626+C653 -> 39.213861 | D63: =+D260+D373+D486+D599+D626+D653 -> -2.2609524 | E63: =+E260+E373+E486+E599+E626+E653 -> -99.954303 | F63: =+F260+F373+F486+F599+F626+F653 -> -124.82969 | G63: =+G260+G373+G486+G599+G626+G653 -> -18.258823 | H63: =+H260+H373+H486+H599+H626+H653 -> 171.68351 | I63: =+I260+I373+I486+I599+I626+I653 -> -51.919752 | J63: =+J260+J373+J486+J599+J626+J653 -> 157.8125 | K63: =+K260+K373+K486+K599+K626+K653 -> -164.50927 | L63: =+L260+L373+L486+L599+L626 -> -102.11124 | M63: =+M260+M373+M486+M599+M626 -> 209.27411 | N63: =+N260+N373+N486+N599+N626 -> 116.41938 | O63: =+O260+O373+O486+O599+O626 -> 325.69348 | P63: =+P260+P373+P486+P599+P626 -> -103.91625 | Q63: =+Q260+Q373+Q486+Q599+Q626 -> -2.5558368 | R63: =+R260+R373+R486+R599+R626 -> -106.47208 | W63: =+W260+W373+W486+W599 -> 86.427412 | X63: =+X260+X373+X486+X599 -> -148.82133 | Y63: =+Y260+Y373+Y486+Y599 -> -62.393915 | AD63: =+AD260+AD373+AD486+AD599 -> -189.79361 | AE63: =+AE260+AE373+AE486+AE599 -> -28.560592 | AF63: =+AF260+AF373+AF486+AF599 -> -218.3542 | AK63: =+AK260+AK373+AK486+AK599 -> 97.038748 | AL63: =+AL260+AL373+AL486+AL599 -> 34.450919 | AM63: =+AM260+AM373+AM486+AM599 -> 131.48967 | AR63: =+AR260+AR373+AR486+AR599 -> -15.232821 | AS63: =+AS260+AS373+AS486+AS599 -> -156.62567 | AT63: =+AT260+AT373+AT486+AT599 -> -171.8585 | AY63: =+AY260+AY373+AY486+AY599 -> -149.45583 | AZ63: =+AZ260+AZ373+AZ486+AZ599 -> 68.352594 | BA63: =+BA260+BA373+BA486+BA599 -> -81.103237 | BF63: =+BF260+BF373+BF486+BF599 -> 245.30293 | BG63: =+BG260+BG373+BG486+BG599 -> 270.33686 | BH63: =+BH260+BH373+BH486+BH599 -> 515.63979 | BM63: =+BM260+BM373+BM486+BM599 -> -66.785173 | BN63: =+BN260+BN373+BN486+BN599 -> -355.12133 | BO63: =+BO260+BO373+BO486+BO599 -> -421.90651 | BT63: =+BT260+BT373+BT486+BT599 -> -114.31009 | BU63: =+BU260+BU373+BU486+BU599 -> 4.3138683 | BV63: =+BV260+BV373+BV486+BV599 -> -109.99622 | CA63: =+CA260+CA373+CA486+CA599 -> -92.77809 | CB63: =+CB260+CB373+CB486+CB599 -> -265.14306 | CC63: =+CC260+CC373+CC486+CC599 -> -357.92115 | CH63: =+CH260+CH373+CH486+CH599 -> -162.1935 | CI63: =+CI260+CI373+CI486+CI599 -> 56.827881 | CJ63: =+CJ260+CJ373+CJ486+CJ599 -> -105.36562 | CK63: =+CK260+CK373+CK486+CK599 -> -39.100205 | CL63: =+CL260+CL373+CL486+CL599 -> -41.625556 | CM63: =+CM260+CM373+CM486+CM599 -> -41.433724 | CN63: =+CN260+CN373+CN486+CN599 -> -44.091639 | CO63: =+CO260+CO373+CO486+CO599 -> -46.923771 | ... CS63: =+CS260+CS373+CS486+CS599 -> -60.240179
A64: group structure impact | B64: EURm | C64: =+C261+C374+C487+C600+C627+C654 -> 0 | D64: =+D261+D374+D487+D600+D627+D654 -> 0 | E64: =+E261+E374+E487+E600+E627+E654 -> 84.422992 | F64: =+F261+F374+F487+F600+F627+F654 -> 121.72006 | G64: =+G261+G374+G487+G600+G627+G654 -> 52.156 | H64: =+H261+H374+H487+H600+H627+H654 -> 14.31 | I64: =+I261+I374+I487+I600+I627+I654 -> 28.643 | J64: =+J261+J374+J487+J600+J627+J654 -> 30.8273 | K64: =+K261+K374+K487+K600+K627+K654 -> 48.2004 | L64: =+L261+L374+L487+L600+L627 -> 10.4953 | M64: =+M261+M374+M487+M600+M627 -> 27.044 | N64: =+N261+N374+N487+N600+N627 -> 11.74014 | O64: =+O261+O374+O487+O600+O627 -> 38.78414 | P64: =+P261+P374+P487+P600+P627 -> 5.9684 | Q64: =+Q261+Q374+Q487+Q600+Q627 -> -16.856528 | R64: =+R261+R374+R487+R600+R627 -> -10.888128 | W64: =+W261+W374+W487+W600 -> 0 | X64: =+X261+X374+X487+X600 -> 50.47684 | Y64: =+Y261+Y374+Y487+Y600 -> 50.47684 | AD64: =+AD261+AD374+AD487+AD600 -> 0 | AE64: =+AE261+AE374+AE487+AE600 -> 26.09254 | AF64: =+AF261+AF374+AF487+AF600 -> 26.09254 | AK64: =+AK261+AK374+AK487+AK600 -> 0 | AL64: =+AL261+AL374+AL487+AL600 -> 35.63784 | AM64: =+AM261+AM374+AM487+AM600 -> 35.63784 | AR64: =+AR261+AR374+AR487+AR600 -> 12.273 | AS64: =+AS261+AS374+AS487+AS600 -> 20.1451 | AT64: =+AT261+AT374+AT487+AT600 -> 32.4181 | AY64: =+AY261+AY374+AY487+AY600 -> 30.586658 | AZ64: =+AZ261+AZ374+AZ487+AZ600 -> 6.740168 | BA64: =+BA261+BA374+BA487+BA600 -> 37.326826 | BF64: =+BF261+BF374+BF487+BF600 -> 11.895581 | BG64: =+BG261+BG374+BG487+BG600 -> 16.084259 | BH64: =+BH261+BH374+BH487+BH600 -> 27.979841 | BM64: =+BM261+BM374+BM487+BM600 -> 16.640385 | BN64: =+BN261+BN374+BN487+BN600 -> 125.82183 | BO64: =+BO261+BO374+BO487+BO600 -> 142.46222 | BT64: =+BT261+BT374+BT487+BT600 -> 120.42533 | BU64: =+BU261+BU374+BU487+BU600 -> 31.385441 | BV64: =+BV261+BV374+BV487+BV600 -> 151.81077 | CA64: =+CA261+CA374+CA487+CA600 -> 21.919037 | CB64: =+CB261+CB374+CB487+CB600 -> 53.721388 | CC64: =+CC261+CC374+CC487+CC600 -> 75.640425 | CH64: =+CH261+CH374+CH487+CH600 -> 33.62468 | CI64: =+CI261+CI374+CI487+CI600 -> 30.013837 | CJ64: =+CJ261+CJ374+CJ487+CJ600 -> 63.638516 | CK64: =+CK261+CK374+CK487+CK600 -> 0 | CL64: =+CL261+CL374+CL487+CL600 -> 0 | CM64: =+CM261+CM374+CM487+CM600 -> 0 | CN64: =+CN261+CN374+CN487+CN600 -> 0 | CO64: =+CO261+CO374+CO487+CO600 -> 0 | ... CS64: =+CS261+CS374+CS487+CS600 -> 0
A65: Professional Products | B65: EURm | C65: =+C250 -> 406 | D65: =+D250 -> 443 | E65: =+E250 -> 501.7 | F65: =+F250 -> 519 | G65: =+G250 -> 477 | H65: =+H250 -> 552 | I65: =+I250 -> 578.6 | J65: =+J250 -> 615.2 | ... R65: =+R250 -> 688.6 | W65: =+W250 -> 319.9 | X65: =+X250 -> 349.5 | Y65: =+Y250 -> 669.4 | AD65: =+AD250 -> 313.4 | AE65: =+AE250 -> 338.1 | AF65: =+AF250 -> 651.5 | AK65: =+AK250 -> 327.9 | AL65: =+AL250 -> 363.7 | AM65: =+AM250 -> 691.6 | AR65: =+AR250 -> 140 | AS65: =+AS250 -> 441.7 | AT65: =+AT250 -> 581.7 | AY65: =+AY250 -> 363.9 | AZ65: =+AZ250 -> 443 | BA65: =+BA250 -> 806.9 | BF65: =+BF250 -> 458.7 | BG65: =+BG250 -> 494.9 | BH65: =+BH250 -> 953.6 | BM65: =+BM250 -> 490.1 | BN65: =+BN250 -> 515.2 | BO65: =+BO250 -> 1005.3 | BT65: =+BT250 -> 536.7 | BU65: =+BU250 -> 549.5 | BV65: =+BV250 -> 1086.2 | CA65: =+CA250 -> 571.5 | CB65: =+CB250 -> 621.27839 | CC65: =+CC250 -> 1192.7784 | CH65: =+CH250 -> 624.14759 | CI65: =+CI250 -> 699.41946 | CJ65: =+CJ250 -> 1323.5671 | CK65: =+CK250 -> 1423.8359 | CL65: =+CL250 -> 1531.2619 | CM65: =+CM250 -> 1646.3367 | CN65: =+CN250 -> 1769.5849 | CO65: =+CO250 -> 1901.5661 | ... CS65: =+CS250 -> 2529.3725
A66: Consumer Products | B66: EURm | C66: =+C363 -> 1291 | D66: =+D363 -> 1421 | E66: =+E363 -> 1582.4 | F66: =+F363 -> 1566 | G66: =+G363 -> 1577 | H66: =+H363 -> 1765 | I66: =+I363 -> 1859 | J66: =+J363 -> 2050.8 | ... R66: =+R363 -> 2417.1 | W66: =+W363 -> 1267.5 | X66: =+X363 -> 1151.5 | Y66: =+Y363 -> 2419 | AD66: =+AD363 -> 1275.4 | AE66: =+AE363 -> 1152.7 | AF66: =+AF363 -> 2428.1 | AK66: =+AK363 -> 1351.1 | AL66: =+AL363 -> 1223.5 | AM66: =+AM363 -> 2574.6 | AR66: =+AR363 -> 1243.7 | AS66: =+AS363 -> 1144.4 | AT66: =+AT363 -> 2388.1 | AY66: =+AY363 -> 1193.4 | AZ66: =+AZ363 -> 1272.6 | BA66: =+BA363 -> 2466 | BF66: =+BF363 -> 1359.8 | BG66: =+BG363 -> 1415.1 | BH66: =+BH363 -> 2774.9 | BM66: =+BM363 -> 1617.4 | BN66: =+BN363 -> 1497.3 | BO66: =+BO363 -> 3114.7 | BT66: =+BT363 -> 1833.2 | BU66: =+BU363 -> 1543.2 | BV66: =+BV363 -> 3376.4 | CA66: =+CA363 -> 1893.5 | CB66: =+CB363 -> 1539.4505 | CC66: =+CC363 -> 3432.9505 | CH66: =+CH363 -> 1945.5029 | CI66: =+CI363 -> 1632.2628 | CJ66: =+CJ363 -> 3577.7657 | CK66: =+CK363 -> 3758.5031 | CL66: =+CL363 -> 3929.9563 | CM66: =+CM363 -> 4108.8981 | CN66: =+CN363 -> 4295.6458 | CO66: =+CO363 -> 4490.5303 | ... CS66: =+CS363 -> 5358.5409
A67: Luxury Products | B67: EURm | C67: =+C476 -> 723 | D67: =+D476 -> 776 | E67: =+E476 -> 843.8 | F67: =+F476 -> 767 | G67: =+G476 -> 617 | H67: =+H476 -> 791 | I67: =+I476 -> 926.3 | J67: =+J476 -> 1077 | ... R67: =+R476 -> 1622.8 | W67: =+W476 -> 970.2 | X67: =+X476 -> 885.6 | Y67: =+Y476 -> 1855.8 | AD67: =+AD476 -> 1026.7 | AE67: =+AE476 -> 1045.7 | AF67: =+AF476 -> 2072.4 | AK67: =+AK476 -> 1227.3 | AL67: =+AL476 -> 1266.4 | AM67: =+AM476 -> 2493.7 | AR67: =+AR476 -> 892 | AS67: =+AS476 -> 1383.9 | AT67: =+AT476 -> 2275.9 | AY67: =+AY476 -> 1301.9 | AZ67: =+AZ476 -> 1514.4 | BA67: =+BA476 -> 2816.3 | BF67: =+BF476 -> 1647.8 | BG67: =+BG476 -> 1702.6 | BH67: =+BH476 -> 3350.4 | BM67: =+BM476 -> 1687.9 | BN67: =+BN476 -> 1643.9 | BO67: =+BO476 -> 3331.8 | BT67: =+BT476 -> 1661.2 | BU67: =+BU476 -> 1808.5 | BV67: =+BV476 -> 3469.7 | CA67: =+CA476 -> 1708.9 | CB67: =+CB476 -> 1798.0094 | CC67: =+CC476 -> 3506.9094 | CH67: =+CH476 -> 1762.5794 | CI67: =+CI476 -> 1926.7074 | CJ67: =+CJ476 -> 3689.2868 | CK67: =+CK476 -> 3966.2072 | CL67: =+CL476 -> 4283.2701 | CM67: =+CM476 -> 4627.8323 | CN67: =+CN476 -> 4999.2944 | CO67: =+CO476 -> 5399.7113 | ... CS67: =+CS476 -> 7337.6755
A68: Active Cosmetics | B68: EURm | C68: =+C589 -> 187 | D68: =+D589 -> 221 | E68: =+E589 -> 255.8 | F68: =+F589 -> 259 | G68: =+G589 -> 250 | H68: =+H589 -> 278 | I68: =+I589 -> 286.7 | J68: =+J589 -> 311.2 | ... R68: =+R589 -> 431.5 | W68: =+W589 -> 303.5 | X68: =+X589 -> 167.7 | Y68: =+Y589 -> 471.2 | AD68: =+AD589 -> 326.2 | AE68: =+AE589 -> 196.8 | AF68: =+AF589 -> 523 | AK68: =+AK589 -> 376.1 | AL68: =+AL589 -> 244.7 | AM68: =+AM589 -> 620.8 | AR68: =+AR589 -> 433.8 | AS68: =+AS589 -> 332.2 | AT68: =+AT589 -> 766 | AY68: =+AY589 -> 570 | AZ68: =+AZ589 -> 420.5 | BA68: =+BA589 -> 990.5 | BF68: =+BF589 -> 703.5 | BG68: =+BG589 -> 599.5 | BH68: =+BH589 -> 1303 | BM68: =+BM589 -> 933.9 | BN68: =+BN589 -> 737 | BO68: =+BO589 -> 1670.9 | BT68: =+BT589 -> 1097.4 | BU68: =+BU589 -> 735.3 | BV68: =+BV589 -> 1832.7 | CA68: =+CA589 -> 1087.1 | CB68: =+CB589 -> 763.73038 | CC68: =+CC589 -> 1850.8304 | CH68: =+CH589 -> 1146.9219 | CI68: =+CI589 -> 827.62527 | CJ68: =+CJ589 -> 1974.5472 | CK68: =+CK589 -> 2101.5513 | CL68: =+CL589 -> 2236.5968 | CM68: =+CM589 -> 2380.1865 | CN68: =+CN589 -> 2532.8546 | CO68: =+CO589 -> 2695.1679 | ... CS68: =+CS589 -> 3453.4884
A69: The Body Shop | B69: EURm | C69: =+C616 -> 0 | D69: =+D616 -> 58.3 | E69: =+E616 -> 63.8 | F69: =+F616 -> 36.2 | G69: =+G616 -> 54 | H69: =+H616 -> 65 | I69: =+I616 -> 68.1 | J69: =+J616 -> 77.5 | ... R69: =+R616 -> 33.8
A70: Dermatology | B70: EURm | C70: =+C643 -> 53.8 | D70: =+D643 -> 59.4 | E70: =+E643 -> 62 | F70: =+F643 -> 80 | G70: =+G643 -> 85 | H70: =+H643 -> 119 | I70: =+I643 -> 120.1 | J70: =+J643 -> 142.6 | K70: =+K643 -> 116.8
